Workbook
Name TAXRATE: _xludf.LAMBDA(g, i, h, j, k, l, m, IF(g="capital",0.1)+IF(h="port",0.1)+IF(i="citadel",0.05)+IF(j="walls",-0.07)+IF(k="plaza",0.05)+IF(l="temple",0.01)+IF(m="shanty town",0.05))

Sheet New Provinces Summary
B1: Gold Kastar Coins | C1: Total Population | D1: Urban Population | E1: Rural Population | F1: Gold Net Income | G1: Retinues | H1: Knights | I1: Raised Levys | J1: Possible Levys | K1: Urban Population % | L1: Rural Population % | M1: Future Gold
A2: The Crownlands | B2: 201311.58 | C2: ='Province Import (Ignore)'!I5 -> 6198707 | D2: =SUM(Cities!E2:E13) -> 211771 | E2: =C2-D2 -> 5986936 | F2: ='Provincial Economics'!D2-'Provincial Economics'!C2 -> -41088.726 | G2: ='New Retinues Summary'!S3 -> 400 | H2: ='Knights Breakdown'!B2 -> 1942.2476 | I2: =SUM('Duchies Secret Sheet'!$C$16:$C$20) -> 25946 | J2: =IFERROR(__xludf.DUMMYFUNCTION("TO_TEXT(round(RANDBETWEEN(1000,10000)+(C2*0.005)))&TO_TEXT(round(RANDBETWEEN(1000,10000)-(C2*0.005)))"),"38714-26229") -> 38714-26229 | K2: =D2/C2 -> 0.034163738 | L2: =E2/C2 -> 0.96583626 | M2: =F2+B2 -> 160222.86
A3: Dreghold | B3: 42223.454 | C3: ='Province Import (Ignore)'!I4 -> 13047830 | D3: =SUM(Cities!E14:E38) -> 210019 | E3: =C3-D3 -> 12837811 | F3: ='Provincial Economics'!D3-'Provincial Economics'!C3 -> -37872.045 | G3: ='New Retinues Summary'!S4 -> 2000 | H3: ='Knights Breakdown'!B3 -> 3066.8744 | I3: =SUM('Duchies Secret Sheet'!$C$4,'Duchies Secret Sheet'!$C21:$C$26) -> 26554.641 | J3: =IFERROR(__xludf.DUMMYFUNCTION("TO_TEXT(round(RANDBETWEEN(1000,10000)+(C3*0.005)))&TO_TEXT(round(RANDBETWEEN(1000,10000)-(C3*0.005)))"),"67842-62827") -> 67842-62827 | K3: =D3/C3 -> 0.016096086 | L3: =E3/C3 -> 0.98390391 | M3: =F3+B3 -> 4351.4094
A4: Madinglia | B4: 219681.69 | C4: ='Province Import (Ignore)'!I3 -> 3739211 | D4: =SUM(Cities!E39:E50) -> 72536 | E4: =C4-D4 -> 3666675 | F4: ='Provincial Economics'!D4-'Provincial Economics'!C4 -> 1164.8905 | G4: ='New Retinues Summary'!S5 -> 300 | H4: ='Knights Breakdown'!B4 -> 383.80462 | I4: =SUM('Duchies Secret Sheet'!$C$41:$C$45,'Duchies Secret Sheet'!$C$3) -> 0 | J4: =IFERROR(__xludf.DUMMYFUNCTION("TO_TEXT(round(RANDBETWEEN(1000,10000)+(C4*0.005)))&TO_TEXT(round(RANDBETWEEN(1000,10000)-(C4*0.005)))"),"21221-15914") -> 21221-15914 | K4: =D4/C4 -> 0.019398745 | L4: =E4/C4 -> 0.98060126 | M4: =F4+B4 -> 220846.58
A5: Ralim | B5: 185816.13 | C5: ='Province Import (Ignore)'!I7 -> 7694131 | D5: =SUM(Cities!E52:E63) -> 132591 | E5: =C5-D5 -> 7561540 | F5: ='Provincial Economics'!D5-'Provincial Economics'!C5 -> -26961.687 | G5: ='New Retinues Summary'!S6 -> 0 | H5: ='Knights Breakdown'!B5 -> 1353.2702 | I5: =SUM('Duchies Secret Sheet'!$C$6,'Duchies Secret Sheet'!$C$13:$C$15) -> 15833 | J5: =IFERROR(__xludf.DUMMYFUNCTION("TO_TEXT(round(RANDBETWEEN(1000,10000)+(C5*0.005)))&TO_TEXT(round(RANDBETWEEN(1000,10000)-(C5*0.005)))"),"43900-31918") -> 43900-31918 | K5: =D5/C5 -> 0.017232745 | L5: =E5/C5 -> 0.98276725 | M5: =F5+B5 -> 158854.44
A6: Sirong | B6: 76796.648 | C6: ='Province Import (Ignore)'!I6 -> 16040936 | D6: =SUM(Cities!E65:E104) -> 460501 | E6: =C6-D6 -> 15580435 | F6: ='Provincial Economics'!D6-'Provincial Economics'!C6 -> -76847.919 | G6: ='New Retinues Summary'!S7 -> 200 | H6: ='Knights Breakdown'!B6 -> 4214.3773 | I6: =SUM('Duchies Secret Sheet'!$C$5,'Duchies Secret Sheet'!$C$7:$C$12) -> 41000 | J6: =IFERROR(__xludf.DUMMYFUNCTION("TO_TEXT(round(RANDBETWEEN(1000,10000)+(C6*0.005)))&TO_TEXT(round(RANDBETWEEN(1000,10000)-(C6*0.005)))"),"85311-76707") -> 85311-76707 | K6: =D6/C6 -> 0.028707863 | L6: =E6/C6 -> 0.97129214 | M6: =F6+B6 -> -51.271419
A7: Swanhall | B7: 68991.167 | C7: ='Province Import (Ignore)'!I2 -> 17007036 | D7: =SUM(Cities!E105:E166) -> 579594 | E7: =C7-D7 -> 16427442 | F7: ='Provincial Economics'!D7-'Provincial Economics'!C7 -> -37545.637 | G7: ='New Retinues Summary'!S8 -> 0 | H7: ='Knights Breakdown'!B7 -> 5603.8644 | I7: =SUM('Duchies Secret Sheet'!$C$2,'Duchies Secret Sheet'!$C$27:$C$40) -> 21849.36 | J7: =IFERROR(__xludf.DUMMYFUNCTION("TO_TEXT(round(RANDBETWEEN(1000,10000)+(C7*0.005)))&TO_TEXT(round(RANDBETWEEN(1000,10000)-(C7*0.005)))"),"89956-82393") -> 89956-82393 | K7: =D7/C7 -> 0.03407966 | L7: =E7/C7 -> 0.96592034 | M7: =F7+B7 -> 31445.53
A8: Total | B8: =SUM(B2:B7) -> 794820.66 | C8: =SUM(C2:C7) -> 63727851 | D8: =SUM(D2:D7) -> 1667012 | E8: =SUM(E2:E7) -> 62060839 | F8: =SUM(F2:F7) -> -219151.12 | G8: =SUM(G2:G7) -> 2900 | H8: =SUM(H2:H7) -> 16564.439 | I8: =SUM(I2:I7) -> 131183 | J8: =SUM('Provincial Secret Sheet'!E1:E6) -> 302999.68 | M8: =SUM(M2:M7) -> 575669.54
A9: Average | B9: =AVERAGE(B2:B7) -> 132470.11 | C9: =AVERAGE(C2:C7) -> 10621308 | D9: =AVERAGE(D2:D7) -> 277835.33 | E9: =AVERAGE(E2:E7) -> 10343473 | F9: =AVERAGE(F2:F7) -> -36525.187 | G9: =AVERAGE(G2:G7) -> 483.33333 | H9: =AVERAGE(H2:H7) -> 2760.7398 | I9: =AVERAGE(I2:I7) -> 21863.833 | J9: =J8/6 -> 50499.946 | K9: =AVERAGE(K2:K7) -> 0.024946473 | L9: =AVERAGE(L2:L7) -> 0.97505353 | M9: =AVERAGE(M2:M7) -> 95944.923

Sheet Duchies Summary
A1: Duchy | B1: Capital | C1: Province | D1: Net Income | E1: Gold Kastars | F1: Raised Levies | G1: Possible Levies | H1: Urban Households | I1: Rural Households | J1: Total Population | K1: Urban Population | L1: Rural Population | M1: Urban% | N1: Rural% | O1: Knights | P1: Knight Tradition | Q1: Rural Knights | R1: Urban Knights | T1: Future Gold
A2: ='Duchies Import'!B:B -> Swanhall | B2: ='Duchies Import'!C:C -> Swanhall | C2: ='Ducal Economics'!B2 -> Swanhall | E2: 1 | F2: ='Duchies Secret Sheet'!C2:C45 -> 2949.3599 | G2: =IFERROR(__xludf.DUMMYFUNCTION("TO_TEXT(round(RANDBETWEEN(100,3000)+('Duchies Secret Sheet'!E2)))&TO_TEXT(round(RANDBETWEEN(100,1500)-('Duchies Secret Sheet'!E2)))"),"5569-2449") -> 5569-2449 | H2: =K2/3.5 -> 12258.571 | I2: =L2/3.5 -> 244303.14 | J2: ='Duchies Import'!I2 -> 897966 | K2: ='Duchies Import'!K2 -> 42905 | L2: ='Duchies Import'!J2 -> 855061 | M2: =K2/J2 -> 0.047780205 | N2: =L2/J2 -> 0.95221979 | O2: =Q2+R2 -> 342.6322 | P2: 0.8 | Q2: =L2*P2*0.00025 -> 171.0122 | R2: =P2*K2*0.005 -> 171.62 | T2: =E2+D2 -> 1
A3: ='Duchies Import'!B:B -> Slutiarm | B3: ='Duchies Import'!C:C -> Slutiarm | C3: ='Ducal Economics'!B3 -> Madinglia | E3: 1 | F3: ='Duchies Secret Sheet'!C3:C46 -> 0 | G3: =IFERROR(__xludf.DUMMYFUNCTION("TO_TEXT(round(RANDBETWEEN(100,3000)+('Duchies Secret Sheet'!E3)))&TO_TEXT(round(RANDBETWEEN(100,1500)-('Duchies Secret Sheet'!E3)))"),"3542-638") -> 3542-638 | H3: =K3/3.5 -> 6136 | I3: =L3/3.5 -> 79026 | J3: ='Duchies Import'!I3 -> 298067 | K3: ='Duchies Import'!K3 -> 21476 | L3: ='Duchies Import'!J3 -> 276591 | M3: =K3/J3 -> 0.072050915 | N3: =L3/J3 -> 0.92794909 | O3: =Q3+R3 -> 52.958325 | P3: 0.3 | Q3: =L3*P3*0.00025 -> 20.744325 | R3: =P3*K3*0.005 -> 32.214 | T3: =E3+D3 -> 1
A4: ='Duchies Import'!B:B -> Dreghold | B4: ='Duchies Import'!C:C -> Dreghold | C4: ='Ducal Economics'!B4 -> Dreghold | E4: 1 | F4: 2000 | G4: =IFERROR(__xludf.DUMMYFUNCTION("TO_TEXT(round(RANDBETWEEN(100,3000)+('Duchies Secret Sheet'!E4)))&TO_TEXT(round(RANDBETWEEN(100,1500)-('Duchies Secret Sheet'!E4)))"),"4633-2213") -> 4633-2213 | H4: =K4/3.5 -> 28761.714 | I4: =L4/3.5 -> 414572.86 | J4: ='Duchies Import'!I4 -> 1551671 | K4: ='Duchies Import'!K4 -> 100666 | L4: ='Duchies Import'!J4 -> 1451005 | M4: =K4/J4 -> 0.064875866 | N4: =L4/J4 -> 0.93512413 | O4: =Q4+R4 -> 623.5785 | P4: 0.72 | Q4: =L4*P4*0.00025 -> 261.1809 | R4: =P4*K4*0.005 -> 362.3976 | T4: =E4+D4 -> 1
A5: ='Duchies Import'!B:B -> Sirong | B5: ='Duchies Import'!C:C -> Sirong | C5: ='Ducal Economics'!B5 -> Sirong | D5: ='Ducal Economics'!C5-'Ducal Economics'!D5 -> -17003.811 | E5: -7034.2971 | F5: ='Duchies Secret Sheet'!C5:C48 -> 10000 | G5: =IFERROR(__xludf.DUMMYFUNCTION("TO_TEXT(round(RANDBETWEEN(100,3000)+('Duchies Secret Sheet'!E5)))&TO_TEXT(round(RANDBETWEEN(100,1500)-('Duchies Secret Sheet'!E5)))"),"13640-10136") -> 13640-10136 | H5: =K5/3.5 -> 16931.143 | I5: =L5/3.5 -> 629376.57 | J5: ='Duchies Import'!I5 -> 2262077 | K5: ='Duchies Import'!K5 -> 59259 | L5: ='Duchies Import'!J5 -> 2202818 | M5: =K5/J5 -> 0.026196721 | N5: =L5/J5 -> 0.97380328 | O5: =Q5+R5 -> 575.95966 | P5: 0.68 | Q5: =L5*P5*0.00025 -> 374.47906 | R5: =P5*K5*0.005 -> 201.4806 | T5: =E5+D5 -> -24038.108
A6: ='Duchies Import'!B:B -> Brookward | B6: ='Duchies Import'!C:C -> Brookward | C6: ='Ducal Economics'!B6 -> Ralim | E6: 1 | F6: ='Duchies Secret Sheet'!C6:C49 -> 6528 | G6: =IFERROR(__xludf.DUMMYFUNCTION("TO_TEXT(round(RANDBETWEEN(100,3000)+('Duchies Secret Sheet'!E6)))&TO_TEXT(round(RANDBETWEEN(100,1500)-('Duchies Secret Sheet'!E6)))"),"9182-5954") -> 9182-5954 | H6: =K6/3.5 -> 23154.571 | I6: =L6/3.5 -> 349852.86 | J6: ='Duchies Import'!I6 -> 1305527 | K6: ='Duchies Import'!K6 -> 81041 | L6: ='Duchies Import'!J6 -> 1224485 | M6: =K6/J6 -> 0.062075315 | N6: =L6/J6 -> 0.93792392 | O6: =Q6+R6 -> 377.00291 | P6: 0.53 | Q6: =L6*P6*0.00025 -> 162.24426 | R6: =P6*K6*0.005 -> 214.75865 | T6: =E6+D6 -> 1
A7: ='Duchies Import'!B:B -> Vhalian Marches | B7: ='Duchies Import'!C:C -> Vhalthin | C7: ='Ducal Economics'!B7 -> Sirong | E7: 1 | F7: ='Duchies Secret Sheet'!C7:C50 -> 20000 | G7: =IFERROR(__xludf.DUMMYFUNCTION("TO_TEXT(round(RANDBETWEEN(100,3000)+('Duchies Secret Sheet'!E7)))&TO_TEXT(round(RANDBETWEEN(100,1500)-('Duchies Secret Sheet'!E7)))"),"28820-26375") -> 28820-26375 | H7: =K7/3.5 -> 19134.571 | I7: =L7/3.5 -> 1549696.3 | J7: ='Duchies Import'!I7 -> 5490909 | K7: ='Duchies Import'!K7 -> 66971 | L7: ='Duchies Import'!J7 -> 5423937 | M7: =K7/J7 -> 0.012196705 | N7: =L7/J7 -> 0.98780311 | O7: =Q7+R7 -> 1149.7707 | P7: 0.68 | Q7: =L7*P7*0.00025 -> 922.06929 | R7: =P7*K7*0.005 -> 227.7014 | T7: =E7+D7 -> 1
A8: ='Duchies Import'!B:B -> Southern Shores | B8: ='Duchies Import'!C:C -> Alhas | C8: ='Ducal Economics'!B8 -> Sirong | D8: ='Ducal Economics'!C8-'Ducal Economics'!D8 -> -8550.6549 | E8: -955.89437 | F8: ='Duchies Secret Sheet'!C8:C51 -> 5000 | G8: =IFERROR(__xludf.DUMMYFUNCTION("TO_TEXT(round(RANDBETWEEN(100,3000)+('Duchies Secret Sheet'!E8)))&TO_TEXT(round(RANDBETWEEN(100,1500)-('Duchies Secret Sheet'!E8)))"),"8332-4977") -> 8332-4977 | H8: =K8/3.5 -> 9194 | I8: =L8/3.5 -> 340568 | J8: ='Duchies Import'!I8 -> 1224167 | K8: ='Duchies Import'!K8 -> 32179 | L8: ='Duchies Import'!J8 -> 1191988 | M8: =K8/J8 -> 0.026286446 | N8: =L8/J8 -> 0.97371355 | O8: =Q8+R8 -> 312.04656 | P8: 0.68 | Q8: =L8*P8*0.00025 -> 202.63796 | R8: =P8*K8*0.005 -> 109.4086 | T8: =E8+D8 -> -9506.5493
A9: ='Duchies Import'!B:B -> Dregsten Bay | B9: ='Duchies Import'!C:C -> Dryvaterga | C9: ='Ducal Economics'!B9 -> Sirong | D9: ='Ducal Economics'!C9-'Ducal Economics'!D9 -> 3227.3489 | E9: 7654.6979 | F9: ='Duchies Secret Sheet'!C9:C52 -> 0 | G9: =IFERROR(__xludf.DUMMYFUNCTION("TO_TEXT(round(RANDBETWEEN(100,3000)+('Duchies Secret Sheet'!E9)))&TO_TEXT(round(RANDBETWEEN(100,1500)-('Duchies Secret Sheet'!E9)))"),"11465-9705") -> 11465-9705 | H9: =K9/3.5 -> 18818.286 | I9: =L9/3.5 -> 601768.86 | J9: ='Duchies Import'!I9 -> 2172056 | K9: ='Duchies Import'!K9 -> 65864 | L9: ='Duchies Import'!J9 -> 2106191 | M9: =K9/J9 -> 0.030323343 | N9: =L9/J9 -> 0.9696762 | O9: =Q9+R9 -> 581.99007 | P9: 0.68 | Q9: =L9*P9*0.00025 -> 358.05247 | R9: =P9*K9*0.005 -> 223.9376 | T9: =E9+D9 -> 10882.047
A10: ='Duchies Import'!B:B -> Amber Shores | B10: ='Duchies Import'!C:C -> Amber Waters | C10: ='Ducal Economics'!B10 -> Sirong | D10: ='Ducal Economics'!C10-'Ducal Economics'!D10 -> 813.28075 | E10: 13319.527 | F10: ='Duchies Secret Sheet'!C10:C53 -> 0 | G10: =IFERROR(__xludf.DUMMYFUNCTION("TO_TEXT(round(RANDBETWEEN(100,3000)+('Duchies Secret Sheet'!E10)))&TO_TEXT(round(RANDBETWEEN(100,1500)-('Duchies Secret Sheet'!E10)))"),"5658-3243") -> 5658-3243 | H10: =K10/3.5 -> 2838.2857 | I10: =L10/3.5 -> 253476 | J10: ='Duchies Import'!I10 -> 897100 | K10: ='Duchies Import'!K10 -> 9934 | L10: ='Duchies Import'!J10 -> 887166 | M10: =K10/J10 -> 0.011073459 | N10: =L10/J10 -> 0.98892654 | O10: =Q10+R10 -> 184.59382 | P10: 0.68 | Q10: =L10*P10*0.00025 -> 150.81822 | R10: =P10*K10*0.005 -> 33.7756 | T10: =E10+D10 -> 14132.807
A11: ='Duchies Import'!B:B -> Griffin's Bay | B11: ='Duchies Import'!C:C -> Ulport | C11: ='Ducal Economics'!B11 -> Sirong | D11: ='Ducal Economics'!C11-'Ducal Economics'!D11 -> -9.0832771 | E11: 33918.251 | F11: ='Duchies Secret Sheet'!C11:C54 -> 2000 | G11: =IFERROR(__xludf.DUMMYFUNCTION("TO_TEXT(round(RANDBETWEEN(100,3000)+('Duchies Secret Sheet'!E11)))&TO_TEXT(round(RANDBETWEEN(100,1500)-('Duchies Secret Sheet'!E11)))"),"11397-10320") -> 11397-10320 | H11: =K11/3.5 -> 33452.857 | I11: =L11/3.5 -> 609732.29 | J11: ='Duchies Import'!I11 -> 2251148 | K11: ='Duchies Import'!K11 -> 117085 | L11: ='Duchies Import'!J11 -> 2134063 | M11: =K11/J11 -> 0.05201124 | N11: =L11/J11 -> 0.94798876 | O11: =Q11+R11 -> 760.87971 | P11: 0.68 | Q11: =L11*P11*0.00025 -> 362.79071 | R11: =P11*K11*0.005 -> 398.089 | T11: =E11+D11 -> 33909.167
A12: ='Duchies Import'!B:B -> Lesserlands | B12: ='Duchies Import'!C:C -> Sirongrasp | C12: ='Ducal Economics'!B12 -> Sirong | D12: ='Ducal Economics'!C12-'Ducal Economics'!D12 -> -6290.9465 | E12: 5381.4815 | F12: ='Duchies Secret Sheet'!C12:C55 -> 4000 | G12: =IFERROR(__xludf.DUMMYFUNCTION("TO_TEXT(round(RANDBETWEEN(100,3000)+('Duchies Secret Sheet'!E12)))&TO_TEXT(round(RANDBETWEEN(100,1500)-('Duchies Secret Sheet'!E12)))"),"10709-7423") -> 10709-7423 | H12: =K12/3.5 -> 8498.5714 | I12: =L12/3.5 -> 470965.43 | J12: ='Duchies Import'!I12 -> 1678124 | K12: ='Duchies Import'!K12 -> 29745 | L12: ='Duchies Import'!J12 -> 1648379 | M12: =K12/J12 -> 0.01772515 | N12: =L12/J12 -> 0.98227485 | O12: =Q12+R12 -> 381.35743 | P12: 0.68 | Q12: =L12*P12*0.00025 -> 280.22443 | R12: =P12*K12*0.005 -> 101.133 | T12: =E12+D12 -> -909.46496
A13: ='Duchies Import'!B:B -> ShadowWood | B13: ='Duchies Import'!C:C -> Shadowtown | C13: ='Ducal Economics'!B13 -> Ralim | D13: ='Ducal Economics'!C13-'Ducal Economics'!D13 -> -1090.5649 | E13: 12984.916 | F13: ='Duchies Secret Sheet'!C13:C56 -> 1200 | G13: =IFERROR(__xludf.DUMMYFUNCTION("TO_TEXT(round(RANDBETWEEN(100,3000)+('Duchies Secret Sheet'!E13)))&TO_TEXT(round(RANDBETWEEN(100,1500)-('Duchies Secret Sheet'!E13)))"),"10722-8888") -> 10722-8888 | H13: =K13/3.5 -> 616.85714 | I13: =L13/3.5 -> 582255.43 | J13: ='Duchies Import'!I13 -> 2040053 | K13: ='Duchies Import'!K13 -> 2159 | L13: ='Duchies Import'!J13 -> 2037894 | M13: =K13/J13 -> 0.0010583058 | N13: =L13/J13 -> 0.99894169 | O13: =Q13+R13 -> 275.7423 | P13: 0.53 | Q13: =L13*P13*0.00025 -> 270.02096 | R13: =P13*K13*0.005 -> 5.72135 | T13: =E13+D13 -> 11894.351
A14: ='Duchies Import'!B:B -> Mondwatch | B14: ='Duchies Import'!C:C -> Bear Hall | C14: ='Ducal Economics'!B14 -> Ralim | D14: ='Ducal Economics'!C14-'Ducal Economics'!D14 -> -4505.773 | E14: 13118.043 | F14: ='Duchies Secret Sheet'!C14:C57 -> 3405 | G14: =IFERROR(__xludf.DUMMYFUNCTION("TO_TEXT(round(RANDBETWEEN(100,3000)+('Duchies Secret Sheet'!E14)))&TO_TEXT(round(RANDBETWEEN(100,1500)-('Duchies Secret Sheet'!E14)))"),"10854-9114") -> 10854-9114 | H14: =K14/3.5 -> 10846.571 | I14: =L14/3.5 -> 590251.43 | J14: ='Duchies Import'!I14 -> 2103843 | K14: ='Duchies Import'!K14 -> 37963 | L14: ='Duchies Import'!J14 -> 2065880 | M14: =K14/J14 -> 0.018044597 | N14: =L14/J14 -> 0.9819554 | O14: =Q14+R14 -> 374.33105 | P14: 0.53 | Q14: =L14*P14*0.00025 -> 273.7291 | R14: =P14*K14*0.005 -> 100.60195 | T14: =E14+D14 -> 8612.2699
A15: ='Duchies Import'!B:B -> Ratermarch | B15: ='Duchies Import'!C:C -> Raterehall | C15: ='Ducal Economics'!B15 -> Ralim | D15: ='Ducal Economics'!C15-'Ducal Economics'!D15 -> -7564.9251 | E15: 3715.6737 | F15: ='Duchies Secret Sheet'!C15:C58 -> 4700 | G15: =IFERROR(__xludf.DUMMYFUNCTION("TO_TEXT(round(RANDBETWEEN(100,3000)+('Duchies Secret Sheet'!E15)))&TO_TEXT(round(RANDBETWEEN(100,1500)-('Duchies Secret Sheet'!E15)))"),"11643-9460") -> 11643-9460 | H15: =K15/3.5 -> 6225.7143 | I15: =L15/3.5 -> 611941.43 | J15: ='Duchies Import'!I15 -> 2163584 | K15: ='Duchies Import'!K15 -> 21790 | L15: ='Duchies Import'!J15 -> 2141795 | M15: =K15/J15 -> 0.010071252 | N15: =L15/J15 -> 0.98992921 | O15: =Q15+R15 -> 341.53134 | P15: 0.53 | Q15: =L15*P15*0.00025 -> 283.78784 | R15: =P15*K15*0.005 -> 57.7435 | T15: =E15+D15 -> -3849.2515
A16: ='Duchies Import'!B:B -> Vinh | B16: ='Duchies Import'!C:C -> Vinh | C16: ='Ducal Economics'!B16 -> Crownlands | D16: ='Ducal Economics'!C16-'Ducal Economics'!D16 -> -10656.278 | E16: -5976.5009 | F16: ='Duchies Secret Sheet'!C16:C59 -> 5995 | G16: =IFERROR(__xludf.DUMMYFUNCTION("TO_TEXT(round(RANDBETWEEN(100,3000)+('Duchies Secret Sheet'!E16)))&TO_TEXT(round(RANDBETWEEN(100,1500)-('Duchies Secret Sheet'!E16)))"),"8869-5829") -> 8869-5829 | H16: =K16/3.5 -> 6925.1429 | I16: =L16/3.5 -> 335663.71 | J16: ='Duchies Import'!I16 -> 1199062 | K16: ='Duchies Import'!K16 -> 24238 | L16: ='Duchies Import'!J16 -> 1174823 | M16: =K16/J16 -> 0.020214134 | N16: =L16/J16 -> 0.97978503 | O16: =Q16+R16 -> 315.32077 | P16: 0.76 | Q16: =L16*P16*0.00025 -> 223.21637 | R16: =P16*K16*0.005 -> 92.1044 | T16: =E16+D16 -> -16632.779
A17: ='Duchies Import'!B:B -> Drelme | B17: ='Duchies Import'!C:C -> Drelme | C17: ='Ducal Economics'!B17 -> Crownlands | D17: ='Ducal Economics'!C17-'Ducal Economics'!D17 -> -9277.997 | E17: -2041.9726 | F17: ='Duchies Secret Sheet'!C17:C60 -> 5390 | G17: =IFERROR(__xludf.DUMMYFUNCTION("TO_TEXT(round(RANDBETWEEN(100,3000)+('Duchies Secret Sheet'!E17)))&TO_TEXT(round(RANDBETWEEN(100,1500)-('Duchies Secret Sheet'!E17)))"),"6900-3954") -> 6900-3954 | H17: =K17/3.5 -> 9776.5714 | I17: =L17/3.5 -> 298210.57 | J17: ='Duchies Import'!I17 -> 1077956 | K17: ='Duchies Import'!K17 -> 34218 | L17: ='Duchies Import'!J17 -> 1043737 | M17: =K17/J17 -> 0.031743411 | N17: =L17/J17 -> 0.96825566 | O17: =Q17+R17 -> 328.33843 | P17: 0.76 | Q17: =L17*P17*0.00025 -> 198.31003 | R17: =P17*K17*0.005 -> 130.0284 | T17: =E17+D17 -> -11319.97
A18: ='Duchies Import'!B:B -> Oal's Reach | B18: ='Duchies Import'!C:C -> Oaledale | C18: ='Ducal Economics'!B18 -> Crownlands | D18: ='Ducal Economics'!C18-'Ducal Economics'!D18 -> -11058.497 | E18: -8672.4759 | F18: ='Duchies Secret Sheet'!C18:C61 -> 6061 | G18: =IFERROR(__xludf.DUMMYFUNCTION("TO_TEXT(round(RANDBETWEEN(100,3000)+('Duchies Secret Sheet'!E18)))&TO_TEXT(round(RANDBETWEEN(100,1500)-('Duchies Secret Sheet'!E18)))"),"6540-5589") -> 6540-5589 | H18: =K18/3.5 -> 7175.7143 | I18: =L18/3.5 -> 339148 | J18: ='Duchies Import'!I18 -> 1212133 | K18: ='Duchies Import'!K18 -> 25115 | L18: ='Duchies Import'!J18 -> 1187018 | M18: =K18/J18 -> 0.020719674 | N18: =L18/J18 -> 0.97928033 | O18: =Q18+R18 -> 320.97042 | P18: 0.76 | Q18: =L18*P18*0.00025 -> 225.53342 | R18: =P18*K18*0.005 -> 95.437 | T18: =E18+D18 -> -19730.973
A19: ='Duchies Import'!B:B -> Swiftme | B19: ='Duchies Import'!C:C -> Swiftme | C19: ='Ducal Economics'!B19 -> Crownlands | D19: ='Ducal Economics'!C19-'Ducal Economics'!D19 -> -12630.654 | E19: -2675.8862 | F19: ='Duchies Secret Sheet'!C19:C62 -> 7500 | G19: =IFERROR(__xludf.DUMMYFUNCTION("TO_TEXT(round(RANDBETWEEN(100,3000)+('Duchies Secret Sheet'!E19)))&TO_TEXT(round(RANDBETWEEN(100,1500)-('Duchies Secret Sheet'!E19)))"),"13124-11430") -> 13124-11430 | H19: =K19/3.5 -> 10590.857 | I19: =L19/3.5 -> 701065.14 | J19: ='Duchies Import'!I19 -> 2490796 | K19: ='Duchies Import'!K19 -> 37068 | L19: ='Duchies Import'!J19 -> 2453728 | M19: =K19/J19 -> 0.01488199 | N19: =L19/J19 -> 0.98511801 | O19: =Q19+R19 -> 607.06672 | P19: 0.76 | Q19: =L19*P19*0.00025 -> 466.20832 | R19: =P19*K19*0.005 -> 140.8584 | T19: =E19+D19 -> -15306.54
A20: ='Duchies Import'!B:B -> Heartwell | B20: ='Duchies Import'!C:C -> Heartwell | C20: ='Ducal Economics'!B20 -> Crownlands | D20: ='Ducal Economics'!C20-'Ducal Economics'!D20 -> 1783.8763 | E20: 30054.887 | F20: ='Duchies Secret Sheet'!C20:C63 -> 1000 | G20: =IFERROR(__xludf.DUMMYFUNCTION("TO_TEXT(round(RANDBETWEEN(100,3000)+('Duchies Secret Sheet'!E20)))&TO_TEXT(round(RANDBETWEEN(100,1500)-('Duchies Secret Sheet'!E20)))"),"2061-1136") -> 2061-1136 | H20: =K20/3.5 -> 28602.571 | I20: =L20/3.5 -> 75322 | J20: ='Duchies Import'!I20 -> 363736 | K20: ='Duchies Import'!K20 -> 100109 | L20: ='Duchies Import'!J20 -> 263627 | M20: =K20/J20 -> 0.27522434 | N20: =L20/J20 -> 0.72477566 | O20: =Q20+R20 -> 430.50333 | P20: 0.76 | Q20: =L20*P20*0.00025 -> 50.08913 | R20: =P20*K20*0.005 -> 380.4142 | T20: =E20+D20 -> 31838.763
A21: ='Duchies Import'!B:B -> Pearlpass | B21: ='Duchies Import'!C:C -> Pearlpass | C21: ='Ducal Economics'!B21 -> Dreghold | D21: ='Ducal Economics'!C21-'Ducal Economics'!D21 -> 2734.5408 | E21: 29600.767 | F21: ='Duchies Secret Sheet'!C21:C64 -> 0 | G21: =IFERROR(__xludf.DUMMYFUNCTION("TO_TEXT(round(RANDBETWEEN(100,3000)+('Duchies Secret Sheet'!E21)))&TO_TEXT(round(RANDBETWEEN(100,1500)-('Duchies Secret Sheet'!E21)))"),"7738-5184") -> 7738-5184 | H21: =K21/3.5 -> 6772.8571 | I21: =L21/3.5 -> 907391.14 | J21: ='Duchies Import'!I21 -> 3199574 | K21: ='Duchies Import'!K21 -> 23705 | L21: ='Duchies Import'!J21 -> 3175869 | M21: =K21/J21 -> 0.0074087988 | N21: =L21/J21 -> 0.9925912 | O21: =Q21+R21 -> 656.99442 | P21: 0.72 | Q21: =L21*P21*0.00025 -> 571.65642 | R21: =P21*K21*0.005 -> 85.338 | T21: =E21+D21 -> 32335.308
A22: ='Duchies Import'!B:B -> Prince's Boot | B22: ='Duchies Import'!C:C -> Draven | C22: ='Ducal Economics'!B22 -> Dreghold | D22: ='Ducal Economics'!C22-'Ducal Economics'!D22 -> 1000.5227 | E22: 1510.704 | F22: ='Duchies Secret Sheet'!C22:C65 -> 0 | G22: =IFERROR(__xludf.DUMMYFUNCTION("TO_TEXT(round(RANDBETWEEN(100,3000)+('Duchies Secret Sheet'!E22)))&TO_TEXT(round(RANDBETWEEN(100,1500)-('Duchies Secret Sheet'!E22)))"),"9291-6575") -> 9291-6575 | H22: =K22/3.5 -> 933.71429 | I22: =L22/3.5 -> 429714.86 | J22: ='Duchies Import'!I22 -> 1507269 | K22: ='Duchies Import'!K22 -> 3268 | L22: ='Duchies Import'!J22 -> 1504002 | M22: =K22/J22 -> 0.0021681598 | N22: =L22/J22 -> 0.9978325 | O22: =Q22+R22 -> 282.48516 | P22: 0.72 | Q22: =L22*P22*0.00025 -> 270.72036 | R22: =P22*K22*0.005 -> 11.7648 | T22: =E22+D22 -> 2511.2267
A23: ='Duchies Import'!B:B -> Swan's Reach | B23: ='Duchies Import'!C:C -> Swangeld | C23: ='Ducal Economics'!B23 -> Dreghold | D23: ='Ducal Economics'!C23-'Ducal Economics'!D23 -> -6234.1524 | E23: -6741.7716 | F23: ='Duchies Secret Sheet'!C23:C66 -> 4300 | G23: =IFERROR(__xludf.DUMMYFUNCTION("TO_TEXT(round(RANDBETWEEN(100,3000)+('Duchies Secret Sheet'!E23)))&TO_TEXT(round(RANDBETWEEN(100,1500)-('Duchies Secret Sheet'!E23)))"),"15557-11934") -> 15557-11934 | H23: =K23/3.5 -> 8056 | I23: =L23/3.5 -> 799389.43 | J23: ='Duchies Import'!I23 -> 2826059 | K23: ='Duchies Import'!K23 -> 28196 | L23: ='Duchies Import'!J23 -> 2797863 | M23: =K23/J23 -> 0.0099771449 | N23: =L23/J23 -> 0.99002286 | O23: =Q23+R23 -> 605.12094 | P23: 0.72 | Q23: =L23*P23*0.00025 -> 503.61534 | R23: =P23*K23*0.005 -> 101.5056 | T23: =E23+D23 -> -12975.924
A24: ='Duchies Import'!B:B -> Malhold | B24: ='Duchies Import'!C:C -> Malhold | C24: ='Ducal Economics'!B24 -> Dreghold | D24: ='Ducal Economics'!C24-'Ducal Economics'!D24 -> -11576.388 | E24: 2601.3103 | F24: ='Duchies Secret Sheet'!C24:C67 -> 6974 | G24: =IFERROR(__xludf.DUMMYFUNCTION("TO_TEXT(round(RANDBETWEEN(100,3000)+('Duchies Secret Sheet'!E24)))&TO_TEXT(round(RANDBETWEEN(100,1500)-('Duchies Secret Sheet'!E24)))"),"7127-6081") -> 7127-6081 | H24: =K24/3.5 -> 25764.286 | I24: =L24/3.5 -> 372775.71 | J24: ='Duchies Import'!I24 -> 1394890 | K24: ='Duchies Import'!K24 -> 90175 | L24: ='Duchies Import'!J24 -> 1304715 | M24: =K24/J24 -> 0.064646675 | N24: =L24/J24 -> 0.93535333 | O24: =Q24+R24 -> 559.4787 | P24: 0.72 | Q24: =L24*P24*0.00025 -> 234.8487 | R24: =P24*K24*0.005 -> 324.63 | T24: =E24+D24 -> -8975.0774
A25: ='Duchies Import'!B:B -> Westleden | B25: ='Duchies Import'!C:C -> Westleden | C25: ='Ducal Economics'!B25 -> Dreghold | D25: ='Ducal Economics'!C25-'Ducal Economics'!D25 -> -12110.879 | E25: -8193.1111 | F25: ='Duchies Secret Sheet'!C25:C68 -> 6600 | G25: =IFERROR(__xludf.DUMMYFUNCTION("TO_TEXT(round(RANDBETWEEN(100,3000)+('Duchies Secret Sheet'!E25)))&TO_TEXT(round(RANDBETWEEN(100,1500)-('Duchies Secret Sheet'!E25)))"),"8700-5305") -> 8700-5305 | H25: =K25/3.5 -> 5765.7143 | I25: =L25/3.5 -> 372313.71 | J25: ='Duchies Import'!I25 -> 1323278 | K25: ='Duchies Import'!K25 -> 20180 | L25: ='Duchies Import'!J25 -> 1303098 | M25: =K25/J25 -> 0.015250008 | N25: =L25/J25 -> 0.98474999 | O25: =Q25+R25 -> 307.20564 | P25: 0.72 | Q25: =L25*P25*0.00025 -> 234.55764 | R25: =P25*K25*0.005 -> 72.648 | T25: =E25+D25 -> -20303.99
A26: ='Duchies Import'!B:B -> Shurestar | B26: ='Duchies Import'!C:C -> Shurestar | C26: ='Ducal Economics'!B26 -> Dreghold | D26: ='Ducal Economics'!C26-'Ducal Economics'!D26 -> -10487.884 | E26: -2954.3171 | F26: ='Duchies Secret Sheet'!C26:C69 -> 5992 | G26: =IFERROR(__xludf.DUMMYFUNCTION("TO_TEXT(round(RANDBETWEEN(100,3000)+('Duchies Secret Sheet'!E26)))&TO_TEXT(round(RANDBETWEEN(100,1500)-('Duchies Secret Sheet'!E26)))"),"7300-5738") -> 7300-5738 | H26: =K26/3.5 -> 12832.286 | I26: =L26/3.5 -> 329549.71 | J26: ='Duchies Import'!I26 -> 1198337 | K26: ='Duchies Import'!K26 -> 44913 | L26: ='Duchies Import'!J26 -> 1153424 | M26: =K26/J26 -> 0.03747944 | N26: =L26/J26 -> 0.96252056 | O26: =Q26+R26 -> 369.30312 | P26: 0.72 | Q26: =L26*P26*0.00025 -> 207.61632 | R26: =P26*K26*0.005 -> 161.6868 | T26: =E26+D26 -> -13442.201
A27: ='Duchies Import'!B:B -> Raven's Reach | B27: ='Duchies Import'!C:C -> Westle | C27: ='Ducal Economics'!B27 -> Swanhall | D27: ='Ducal Economics'!C27-'Ducal Economics'!D27 -> 2419.92 | E27: 27779.28 | F27: ='Duchies Secret Sheet'!C27:C70 -> 0 | G27: =IFERROR(__xludf.DUMMYFUNCTION("TO_TEXT(round(RANDBETWEEN(100,3000)+('Duchies Secret Sheet'!E27)))&TO_TEXT(round(RANDBETWEEN(100,1500)-('Duchies Secret Sheet'!E27)))"),"11613-8176") -> 11613-8176 | H27: =K27/3.5 -> 11928 | I27: =L27/3.5 -> 527581.71 | J27: ='Duchies Import'!I27 -> 1888284 | K27: ='Duchies Import'!K27 -> 41748 | L27: ='Duchies Import'!J27 -> 1846536 | M27: =K27/J27 -> 0.022108962 | N27: =L27/J27 -> 0.97789104 | O27: =Q27+R27 -> 536.2992 | P27: 0.8 | Q27: =L27*P27*0.00025 -> 369.3072 | R27: =P27*K27*0.005 -> 166.992 | T27: =E27+D27 -> 30199.2
A28: ='Duchies Import'!B:B -> Northfold | B28: ='Duchies Import'!C:C -> Northfold Manor | C28: ='Ducal Economics'!B28 -> Swanhall | D28: ='Ducal Economics'!C28-'Ducal Economics'!D28 -> 782.41535 | E28: 13041.738 | F28: ='Duchies Secret Sheet'!C28:C71 -> 0 | G28: =IFERROR(__xludf.DUMMYFUNCTION("TO_TEXT(round(RANDBETWEEN(100,3000)+('Duchies Secret Sheet'!E28)))&TO_TEXT(round(RANDBETWEEN(100,1500)-('Duchies Secret Sheet'!E28)))"),"5000-1613") -> 5000-1613 | H28: =K28/3.5 -> 6694.2857 | I28: =L28/3.5 -> 121411.14 | J28: ='Duchies Import'!I28 -> 448368 | K28: ='Duchies Import'!K28 -> 23430 | L28: ='Duchies Import'!J28 -> 424939 | M28: =K28/J28 -> 0.052256182 | N28: =L28/J28 -> 0.94774605 | O28: =Q28+R28 -> 178.7078 | P28: 0.8 | Q28: =L28*P28*0.00025 -> 84.9878 | R28: =P28*K28*0.005 -> 93.72 | T28: =E28+D28 -> 13824.154
A29: ='Duchies Import'!B:B -> Blackstone | B29: ='Duchies Import'!C:C -> Anhelm | C29: ='Ducal Economics'!B29 -> Swanhall | D29: ='Ducal Economics'!C29-'Ducal Economics'!D29 -> 2985.575 | E29: 32870.175 | F29: ='Duchies Secret Sheet'!C29:C72 -> 0 | G29: =IFERROR(__xludf.DUMMYFUNCTION("TO_TEXT(round(RANDBETWEEN(100,3000)+('Duchies Secret Sheet'!E29)))&TO_TEXT(round(RANDBETWEEN(100,1500)-('Duchies Secret Sheet'!E29)))"),"11584-9048") -> 11584-9048 | H29: =K29/3.5 -> 16136.571 | I29: =L29/3.5 -> 585954 | J29: ='Duchies Import'!I29 -> 2107318 | K29: ='Duchies Import'!K29 -> 56478 | L29: ='Duchies Import'!J29 -> 2050839 | M29: =K29/J29 -> 0.026800891 | N29: =L29/J29 -> 0.97319863 | O29: =Q29+R29 -> 636.0798 | P29: 0.8 | Q29: =L29*P29*0.00025 -> 410.1678 | R29: =P29*K29*0.005 -> 225.912 | T29: =E29+D29 -> 35855.75
A30: ='Duchies Import'!B:B -> Ravenmark | B30: ='Duchies Import'!C:C -> Blackfeather Hall | C30: ='Ducal Economics'!B30 -> Swanhall | D30: ='Ducal Economics'!C30-'Ducal Economics'!D30 -> 1082.1621 | E30: 15739.459 | F30: ='Duchies Secret Sheet'!C30:C73 -> 0 | G30: =IFERROR(__xludf.DUMMYFUNCTION("TO_TEXT(round(RANDBETWEEN(100,3000)+('Duchies Secret Sheet'!E30)))&TO_TEXT(round(RANDBETWEEN(100,1500)-('Duchies Secret Sheet'!E30)))"),"4411-2724") -> 4411-2724 | H30: =K30/3.5 -> 7136.2857 | I30: =L30/3.5 -> 225574 | J30: ='Duchies Import'!I30 -> 814486 | K30: ='Duchies Import'!K30 -> 24977 | L30: ='Duchies Import'!J30 -> 789509 | M30: =K30/J30 -> 0.030665966 | N30: =L30/J30 -> 0.96933403 | O30: =Q30+R30 -> 257.8098 | P30: 0.8 | Q30: =L30*P30*0.00025 -> 157.9018 | R30: =P30*K30*0.005 -> 99.908 | T30: =E30+D30 -> 16821.621
A31: ='Duchies Import'!B:B -> Wet Shoor | B31: ='Duchies Import'!C:C -> Shaterse | C31: ='Ducal Economics'!B31 -> Swanhall | D31: ='Ducal Economics'!C31-'Ducal Economics'!D31 -> 718.66886 | E31: 12468.02 | F31: ='Duchies Secret Sheet'!C31:C74 -> 0 | G31: =IFERROR(__xludf.DUMMYFUNCTION("TO_TEXT(round(RANDBETWEEN(100,3000)+('Duchies Secret Sheet'!E31)))&TO_TEXT(round(RANDBETWEEN(100,1500)-('Duchies Secret Sheet'!E31)))"),"6819-4762") -> 6819-4762 | H31: =K31/3.5 -> 4313.1429 | I31: =L31/3.5 -> 317570 | J31: ='Duchies Import'!I31 -> 1126591 | K31: ='Duchies Import'!K31 -> 15096 | L31: ='Duchies Import'!J31 -> 1111495 | M31: =K31/J31 -> 0.013399716 | N31: =L31/J31 -> 0.98660028 | O31: =Q31+R31 -> 282.683 | P31: 0.8 | Q31: =L31*P31*0.00025 -> 222.299 | R31: =P31*K31*0.005 -> 60.384 | T31: =E31+D31 -> 13186.689
A32: ='Duchies Import'!B:B -> Quickwatch | B32: ='Duchies Import'!C:C -> Quickwatch | C32: ='Ducal Economics'!B32 -> Swanhall | D32: ='Ducal Economics'!C32-'Ducal Economics'!D32 -> 2138.9188 | E32: 25250.269 | F32: ='Duchies Secret Sheet'!C32:C75 -> 0 | G32: =IFERROR(__xludf.DUMMYFUNCTION("TO_TEXT(round(RANDBETWEEN(100,3000)+('Duchies Secret Sheet'!E32)))&TO_TEXT(round(RANDBETWEEN(100,1500)-('Duchies Secret Sheet'!E32)))"),"13409-10257") -> 13409-10257 | H32: =K32/3.5 -> 13266.286 | I32: =L32/3.5 -> 591470.29 | J32: ='Duchies Import'!I32 -> 2116578 | K32: ='Duchies Import'!K32 -> 46432 | L32: ='Duchies Import'!J32 -> 2070146 | M32: =K32/J32 -> 0.021937297 | N32: =L32/J32 -> 0.9780627 | O32: =Q32+R32 -> 599.7572 | P32: 0.8 | Q32: =L32*P32*0.00025 -> 414.0292 | R32: =P32*K32*0.005 -> 185.728 | T32: =E32+D32 -> 27389.188
A33: ='Duchies Import'!B:B -> The Deepwood | B33: ='Duchies Import'!C:C -> Deepmoor | C33: ='Ducal Economics'!B33 -> Swanhall | D33: ='Ducal Economics'!C33-'Ducal Economics'!D33 -> 1601.8739 | E33: 20416.865 | F33: ='Duchies Secret Sheet'!C33:C76 -> 0 | G33: =IFERROR(__xludf.DUMMYFUNCTION("TO_TEXT(round(RANDBETWEEN(100,3000)+('Duchies Secret Sheet'!E33)))&TO_TEXT(round(RANDBETWEEN(100,1500)-('Duchies Secret Sheet'!E33)))"),"6122-3429") -> 6122-3429 | H33: =K33/3.5 -> 10368.571 | I33: =L33/3.5 -> 234896.57 | J33: ='Duchies Import'!I33 -> 858428 | K33: ='Duchies Import'!K33 -> 36290 | L33: ='Duchies Import'!J33 -> 822138 | M33: =K33/J33 -> 0.042274949 | N33: =L33/J33 -> 0.95772505 | O33: =Q33+R33 -> 309.5876 | P33: 0.8 | Q33: =L33*P33*0.00025 -> 164.4276 | R33: =P33*K33*0.005 -> 145.16 | T33: =E33+D33 -> 22018.739
A34: ='Duchies Import'!B:B -> Swan's Shoor | B34: ='Duchies Import'!C:C -> Swan's Shoor | C34: ='Ducal Economics'!B34 -> Swanhall | D34: ='Ducal Economics'!C34-'Ducal Economics'!D34 -> -7670.9128 | E34: 16961.785 | F34: ='Duchies Secret Sheet'!C34:C77 -> 5000 | G34: =IFERROR(__xludf.DUMMYFUNCTION("TO_TEXT(round(RANDBETWEEN(100,3000)+('Duchies Secret Sheet'!E34)))&TO_TEXT(round(RANDBETWEEN(100,1500)-('Duchies Secret Sheet'!E34)))"),"6366-3768") -> 6366-3768 | H34: =K34/3.5 -> 20429.714 | I34: =L34/3.5 -> 270154.57 | J34: ='Duchies Import'!I34 -> 1017045 | K34: ='Duchies Import'!K34 -> 71504 | L34: ='Duchies Import'!J34 -> 945541 | M34: =K34/J34 -> 0.07030564 | N34: =L34/J34 -> 0.92969436 | O34: =Q34+R34 -> 475.1242 | P34: 0.8 | Q34: =L34*P34*0.00025 -> 189.1082 | R34: =P34*K34*0.005 -> 286.016 | T34: =E34+D34 -> 9290.8724
A35: ='Duchies Import'!B:B -> The Shield | B35: ='Duchies Import'!C:C -> The Shield | C35: ='Ducal Economics'!B35 -> Swanhall | D35: ='Ducal Economics'!C35-'Ducal Economics'!D35 -> 1735.0813 | E35: 21615.732 | F35: ='Duchies Secret Sheet'!C35:C78 -> 0 | G35: =IFERROR(__xludf.DUMMYFUNCTION("TO_TEXT(round(RANDBETWEEN(100,3000)+('Duchies Secret Sheet'!E35)))&TO_TEXT(round(RANDBETWEEN(100,1500)-('Duchies Secret Sheet'!E35)))"),"6663-5391") -> 6663-5391 | H35: =K35/3.5 -> 9838.5714 | I35: =L35/3.5 -> 358161.71 | J35: ='Duchies Import'!I35 -> 1288001 | K35: ='Duchies Import'!K35 -> 34435 | L35: ='Duchies Import'!J35 -> 1253566 | M35: =K35/J35 -> 0.026735228 | N35: =L35/J35 -> 0.97326477 | O35: =Q35+R35 -> 388.4532 | P35: 0.8 | Q35: =L35*P35*0.00025 -> 250.7132 | R35: =P35*K35*0.005 -> 137.74 | T35: =E35+D35 -> 23350.813
A36: ='Duchies Import'!B:B -> Elreach | B36: ='Duchies Import'!C:C -> Elreach | C36: ='Ducal Economics'!B36 -> Swanhall | D36: ='Ducal Economics'!C36-'Ducal Economics'!D36 -> 1678.5852 | E36: 21107.267 | F36: ='Duchies Secret Sheet'!C36:C79 -> 0 | G36: =IFERROR(__xludf.DUMMYFUNCTION("TO_TEXT(round(RANDBETWEEN(100,3000)+('Duchies Secret Sheet'!E36)))&TO_TEXT(round(RANDBETWEEN(100,1500)-('Duchies Secret Sheet'!E36)))"),"7735-6755") -> 7735-6755 | H36: =K36/3.5 -> 12170.857 | I36: =L36/3.5 -> 419140.57 | J36: ='Duchies Import'!I36 -> 1509590 | K36: ='Duchies Import'!K36 -> 42598 | L36: ='Duchies Import'!J36 -> 1466992 | M36: =K36/J36 -> 0.028218258 | N36: =L36/J36 -> 0.97178174 | O36: =Q36+R36 -> 463.7904 | P36: 0.8 | Q36: =L36*P36*0.00025 -> 293.3984 | R36: =P36*K36*0.005 -> 170.392 | T36: =E36+D36 -> 22785.852
A37: ='Duchies Import'!B:B -> Mightkeep | B37: ='Duchies Import'!C:C -> Mightkeep | C37: ='Ducal Economics'!B37 -> Swanhall | D37: ='Ducal Economics'!C37-'Ducal Economics'!D37 -> -8242.7007 | E37: 19815.693 | F37: ='Duchies Secret Sheet'!C37:C80 -> 5500 | G37: =IFERROR(__xludf.DUMMYFUNCTION("TO_TEXT(round(RANDBETWEEN(100,3000)+('Duchies Secret Sheet'!E37)))&TO_TEXT(round(RANDBETWEEN(100,1500)-('Duchies Secret Sheet'!E37)))"),"5824-4504") -> 5824-4504 | H37: =K37/3.5 -> 25851.714 | I37: =L37/3.5 -> 293600.57 | J37: ='Duchies Import'!I37 -> 1118082 | K37: ='Duchies Import'!K37 -> 90481 | L37: ='Duchies Import'!J37 -> 1027602 | M37: =K37/J37 -> 0.080925192 | N37: =L37/J37 -> 0.9190757 | O37: =Q37+R37 -> 567.4444 | P37: 0.8 | Q37: =L37*P37*0.00025 -> 205.5204 | R37: =P37*K37*0.005 -> 361.924 | T37: =E37+D37 -> 11572.993
A38: ='Duchies Import'!B:B -> Mightfall | B38: ='Duchies Import'!C:C -> Mightfall | C38: ='Ducal Economics'!B38 -> Swanhall | D38: ='Ducal Economics'!C38-'Ducal Economics'!D38 -> -8599.2328 | E38: 8606.9052 | F38: ='Duchies Secret Sheet'!C38:C81 -> 5000 | G38: =IFERROR(__xludf.DUMMYFUNCTION("TO_TEXT(round(RANDBETWEEN(100,3000)+('Duchies Secret Sheet'!E38)))&TO_TEXT(round(RANDBETWEEN(100,1500)-('Duchies Secret Sheet'!E38)))"),"7553-4744") -> 7553-4744 | H38: =K38/3.5 -> 11254.857 | I38: =L38/3.5 -> 294712.29 | J38: ='Duchies Import'!I38 -> 1070885 | K38: ='Duchies Import'!K38 -> 39392 | L38: ='Duchies Import'!J38 -> 1031493 | M38: =K38/J38 -> 0.036784529 | N38: =L38/J38 -> 0.96321547 | O38: =Q38+R38 -> 363.8666 | P38: 0.8 | Q38: =L38*P38*0.00025 -> 206.2986 | R38: =P38*K38*0.005 -> 157.568 | T38: =E38+D38 -> 7.6724286
A39: ='Duchies Import'!B:B -> Eguard | B39: ='Duchies Import'!C:C -> Eguard | C39: ='Ducal Economics'!B39 -> Swanhall | D39: ='Ducal Economics'!C39-'Ducal Economics'!D39 -> -5163.021 | E39: 13932.811 | F39: ='Duchies Secret Sheet'!C39:C82 -> 3400 | G39: =IFERROR(__xludf.DUMMYFUNCTION("TO_TEXT(round(RANDBETWEEN(100,3000)+('Duchies Secret Sheet'!E39)))&TO_TEXT(round(RANDBETWEEN(100,1500)-('Duchies Secret Sheet'!E39)))"),"6122-2125") -> 6122-2125 | H39: =K39/3.5 -> 10153.714 | I39: =L39/3.5 -> 189582.57 | J39: ='Duchies Import'!I39 -> 699077 | K39: ='Duchies Import'!K39 -> 35538 | L39: ='Duchies Import'!J39 -> 663539 | M39: =K39/J39 -> 0.050835602 | N39: =L39/J39 -> 0.9491644 | O39: =Q39+R39 -> 274.8598 | P39: 0.8 | Q39: =L39*P39*0.00025 -> 132.7078 | R39: =P39*K39*0.005 -> 142.152 | T39: =E39+D39 -> 8769.7896
A40: ='Duchies Import'!B:B -> Lonely Light | B40: ='Duchies Import'!C:C -> Lonely Light | C40: ='Ducal Economics'!B40 -> Swanhall | D40: ='Ducal Economics'!C40-'Ducal Economics'!D40 -> 246.94898 | E40: 8222.5408 | F40: ='Duchies Secret Sheet'!C40:C83 -> 0 | G40: =IFERROR(__xludf.DUMMYFUNCTION("TO_TEXT(round(RANDBETWEEN(100,3000)+('Duchies Secret Sheet'!E40)))&TO_TEXT(round(RANDBETWEEN(100,1000)-('Duchies Secret Sheet'!E40)))"),"2080176") -> 2080176 | H40: =K40/3.5 -> 2473.1429 | I40: =L40/3.5 -> 14642.286 | J40: ='Duchies Import'!I40 -> 59904 | K40: ='Duchies Import'!K40 -> 8656 | L40: ='Duchies Import'!J40 -> 51248 | M40: =K40/J40 -> 0.14449786 | N40: =L40/J40 -> 0.85550214 | O40: =Q40+R40 -> 44.8736 | P40: 0.8 | Q40: =L40*P40*0.00025 -> 10.2496 | R40: =P40*K40*0.005 -> 34.624 | T40: =E40+D40 -> 8469.4898
A41: ='Duchies Import'!B:B -> The Valley | B41: ='Duchies Import'!C:C -> Yeobury | C41: ='Ducal Economics'!B41 -> Madinglia | D41: ='Ducal Economics'!C41-'Ducal Economics'!D41 -> 643.87653 | E41: 11794.889 | F41: ='Duchies Secret Sheet'!C41:C84 -> 0 | G41: =IFERROR(__xludf.DUMMYFUNCTION("TO_TEXT(round(RANDBETWEEN(100,3000)+('Duchies Secret Sheet'!E41)))&TO_TEXT(round(RANDBETWEEN(100,1500)-('Duchies Secret Sheet'!E41)))"),"7107-4959") -> 7107-4959 | H41: =K41/3.5 -> 318.57143 | I41: =L41/3.5 -> 295267.71 | J41: ='Duchies Import'!I41 -> 1034552 | K41: ='Duchies Import'!K41 -> 1115 | L41: ='Duchies Import'!J41 -> 1033437 | M41: =K41/J41 -> 0.0010777612 | N41: =L41/J41 -> 0.99892224 | O41: =Q41+R41 -> 79.180275 | P41: 0.3 | Q41: =L41*P41*0.00025 -> 77.507775 | R41: =P41*K41*0.005 -> 1.6725 | T41: =E41+D41 -> 12438.765
A42: ='Duchies Import'!B:B -> The Knolls | B42: ='Duchies Import'!C:C -> Newtown | C42: ='Ducal Economics'!B42 -> Madinglia | D42: ='Ducal Economics'!C42-'Ducal Economics'!D42 -> 931.68479 | E42: 14385.163 | F42: ='Duchies Secret Sheet'!C42:C85 -> 0 | G42: =IFERROR(__xludf.DUMMYFUNCTION("TO_TEXT(round(RANDBETWEEN(100,3000)+('Duchies Secret Sheet'!E42)))&TO_TEXT(round(RANDBETWEEN(100,1500)-('Duchies Secret Sheet'!E42)))"),"7805-4792") -> 7805-4792 | H42: =K42/3.5 -> 2808.8571 | I42: =L42/3.5 -> 329283.43 | J42: ='Duchies Import'!I42 -> 1162323 | K42: ='Duchies Import'!K42 -> 9831 | L42: ='Duchies Import'!J42 -> 1152492 | M42: =K42/J42 -> 0.008458062 | N42: =L42/J42 -> 0.99154194 | O42: =Q42+R42 -> 101.1834 | P42: 0.3 | Q42: =L42*P42*0.00025 -> 86.4369 | R42: =P42*K42*0.005 -> 14.7465 | T42: =E42+D42 -> 15316.848
A43: ='Duchies Import'!B:B -> Persterton Pass | B43: ='Duchies Import'!C:C -> Persterton | C43: ='Ducal Economics'!B43 -> Madinglia | D43: ='Ducal Economics'!C43-'Ducal Economics'!D43 -> 330.65434 | E43: 8975.889 | F43: ='Duchies Secret Sheet'!C43:C86 -> 0 | G43: =IFERROR(__xludf.DUMMYFUNCTION("TO_TEXT(round(RANDBETWEEN(100,3000)+('Duchies Secret Sheet'!E43)))&TO_TEXT(round(RANDBETWEEN(100,1500)-('Duchies Secret Sheet'!E43)))"),"3433-1324") -> 3433-1324 | H43: =K43/3.5 -> 2138.2857 | I43: =L43/3.5 -> 86484.571 | J43: ='Duchies Import'!I43 -> 310180 | K43: ='Duchies Import'!K43 -> 7484 | L43: ='Duchies Import'!J43 -> 302696 | M43: =K43/J43 -> 0.024127926 | N43: =L43/J43 -> 0.97587207 | O43: =Q43+R43 -> 33.9282 | P43: 0.3 | Q43: =L43*P43*0.00025 -> 22.7022 | R43: =P43*K43*0.005 -> 11.226 | T43: =E43+D43 -> 9306.5434
A44: ='Duchies Import'!B:B -> Rordgoz | B44: ='Duchies Import'!C:C -> Rordgoz | C44: ='Ducal Economics'!B44 -> Madinglia | D44: ='Ducal Economics'!C44-'Ducal Economics'!D44 -> 365.00954 | E44: 9285.0859 | F44: ='Duchies Secret Sheet'!C44:C87 -> 0 | G44: =IFERROR(__xludf.DUMMYFUNCTION("TO_TEXT(round(RANDBETWEEN(100,3000)+('Duchies Secret Sheet'!E44)))&TO_TEXT(round(RANDBETWEEN(100,1500)-('Duchies Secret Sheet'!E44)))"),"3037-2468") -> 3037-2468 | H44: =K44/3.5 -> 528.28571 | I44: =L44/3.5 -> 158785.43 | J44: ='Duchies Import'!I44 -> 557598 | K44: ='Duchies Import'!K44 -> 1849 | L44: ='Duchies Import'!J44 -> 555749 | M44: =K44/J44 -> 0.003316009 | N44: =L44/J44 -> 0.99668399 | O44: =Q44+R44 -> 44.454675 | P44: 0.3 | Q44: =L44*P44*0.00025 -> 41.681175 | R44: =P44*K44*0.005 -> 2.7735 | T44: =E44+D44 -> 9650.0954
A45: ='Duchies Import'!B:B -> Briduan | B45: ='Duchies Import'!C:C -> Brid | C45: ='Ducal Economics'!B45 -> Madinglia | D45: ='Ducal Economics'!C45-'Ducal Economics'!D45 -> 265.50698 | E45: 8389.5629 | F45: ='Duchies Secret Sheet'!C45:C88 -> 0 | G45: =IFERROR(__xludf.DUMMYFUNCTION("TO_TEXT(round(RANDBETWEEN(100,3000)+('Duchies Secret Sheet'!E45)))&TO_TEXT(round(RANDBETWEEN(100,1500)-('Duchies Secret Sheet'!E45)))"),"3868-1121") -> 3868-1121 | H45: =K45/3.5 -> 533.42857 | I45: =L45/3.5 -> 109277.43 | J45: ='Duchies Import'!I45 -> 384337 | K45: ='Duchies Import'!K45 -> 1867 | L45: ='Duchies Import'!J45 -> 382471 | M45: =K45/J45 -> 0.004857716 | N45: =L45/J45 -> 0.99514489 | O45: =Q45+R45 -> 31.485825 | P45: 0.3 | Q45: =L45*P45*0.00025 -> 28.685325 | R45: =P45*K45*0.005 -> 2.8005 | T45: =E45+D45 -> 8655.0698
A46: Total | D46: =SUM(D2:D45) -> -131237.9 | E46: =SUM(E2:E45) -> 419278.16 | H46: =SUM(H2:H45) -> 488406.57 | I46: =SUM(I2:I45) -> 17711881 | J46: =SUM(J2:J45) -> 63701009 | K46: =SUM(K2:K45) -> 1709423 | L46: =SUM(L2:L45) -> 61991585 | O46: =SUM(O2:O45) -> 16786.731 | Q46: =SUM(Q2:Q45) -> 10648.294 | R46: =SUM(R2:R45) -> 6138.4375
A47: Average | D47: =AVERAGE(D2:D45) -> -3365.0745 | E47: =AVERAGE(E2:E45) -> 9529.0491 | H47: =AVERAGE(H2:H45) -> 11100.149 | I47: =AVERAGE(I2:I45) -> 402542.76 | J47: =AVERAGE(J2:J45) -> 1447750.2 | K47: =AVERAGE(K2:K45) -> 38850.523 | L47: =AVERAGE(L2:L45) -> 1408899.7 | M47: =AVERAGE(M2:M45) -> 0.037296978 | N47: =AVERAGE(N2:N45) -> 0.96270309 | O47: =AVERAGE(O2:O45) -> 381.51662 | Q47: =AVERAGE(Q2:Q45) -> 242.00668 | R47: =AVERAGE(R2:R45) -> 139.50994

Sheet Knights Breakdown
B1: Knights | C1: Knight Tradition | D1: Knight Wages | E1: Urban Population | F1: Urban Modifier | G1: Urban Knights | H1: Rural Population | I1: Rural Modifier | J1: Rural Knights
A2: Crownlands | B2: =(G2+J2) -> 1942.2476 | C2: 0.76 | D2: =B2*1.25 -> 2427.8095 | E2: ='New Provinces Summary'!D2 -> 211771 | F2: 0.005 | G2: =F2*E2*C2 -> 804.7298 | H2: ='New Provinces Summary'!E2 -> 5986936 | I2: 0.00025 | J2: =H2*I2*C2 -> 1137.5178
A3: Dreghold | B3: =(G3+J3) -> 3066.8744 | C3: 0.72 | D3: =B3*1.25 -> 3833.593 | E3: ='New Provinces Summary'!D3 -> 210019 | F3: =F2 -> 0.005 | G3: =F3*E3*C3 -> 756.0684 | H3: ='New Provinces Summary'!E3 -> 12837811 | I3: 0.00025 | J3: =H3*I3*C3 -> 2310.806
A4: Madinglia | B4: =(G4+J4) -> 383.80462 | C4: 0.3 | D4: =B4*1.25 -> 479.75578 | E4: ='New Provinces Summary'!D4 -> 72536 | F4: =F3 -> 0.005 | G4: =F4*E4*C4 -> 108.804 | H4: ='New Provinces Summary'!E4 -> 3666675 | I4: 0.00025 | J4: =H4*I4*C4 -> 275.00063
A5: Ralim | B5: =(G5+J5) -> 1353.2702 | C5: 0.53 | D5: =B5*1.25 -> 1691.5878 | E5: ='New Provinces Summary'!D5 -> 132591 | F5: =F4 -> 0.005 | G5: =F5*E5*C5 -> 351.36615 | H5: ='New Provinces Summary'!E5 -> 7561540 | I5: 0.00025 | J5: =H5*I5*C5 -> 1001.9041
A6: Sirong | B6: =(G6+J6) -> 4214.3773 | C6: 0.68 | D6: =B6*1.25 -> 5267.9717 | E6: ='New Provinces Summary'!D6 -> 460501 | F6: =F5 -> 0.005 | G6: =F6*E6*C6 -> 1565.7034 | H6: ='New Provinces Summary'!E6 -> 15580435 | I6: 0.00025 | J6: =H6*I6*C6 -> 2648.6739
A7: Swanhall | B7: =(G7+J7) -> 5603.8644 | C7: 0.8 | D7: =B7*1.25 -> 7004.8305 | E7: ='New Provinces Summary'!D7 -> 579594 | F7: =F6 -> 0.005 | G7: =F7*E7*C7 -> 2318.376 | H7: ='New Provinces Summary'!E7 -> 16427442 | I7: 0.00025 | J7: =H7*I7*C7 -> 3285.4884

Sheet Character Index
A1: Name | B1: House | C1: Current Age | D1: Age at Start | E1: Age at Death | F1: Status | G1: Years Since Start | H1: Age if Alive | I1: Intrigue | J1: Combat | K1: Diplomacy | L1: Stewardship | M1: Average Skill | N1: Birth Year | O1: Current Year | P1: Death Year
A2: Gabren | B2: Princeps | C2: =IF(F2="Alive",D2+G2," ") | D2: 18 | E2: 20 | F2: Dead | G2: 5 | H2: =IF(F2="Dead",G2+D2," ") -> 23 | I2: 60 | J2: 40 | K2: 60 | L2: 35 | M2: =IF(SUM(I2:L2)>0,AVERAGE(I2:L2)," ") -> 48.75 | N2: =O2-G2-D2 -> 1166 | O2: 1189 | P2: =IF(E2>0, N2+E2,"") -> 1186
A3: Armin | B3: Princeps | C3: =IF(F3="Alive",D3+G3," ") | D3: 17 | E3: 21 | F3: Dead | G3: 5 | H3: =IF(F3="Dead",G3+D3," ") -> 22 | I3: 35 | J3: 125 | K3: 50 | L3: 40 | M3: =IF(SUM(I3:L3)>0,AVERAGE(I3:L3)," ") -> 62.5 | N3: =O3-G3-D3 -> 1167 | O3: 1189 | P3: =IF(E3>0, N3+E3,"") -> 1188
A4: Frederick | B4: Senton | C4: =IF(F4="Alive",D4+G4," ") | D4: 43 | E4: 43 | F4: Dead | G4: 5 | H4: =IF(F4="Dead",G4+D4," ") -> 48 | M4: =IF(SUM(I4:L4)>0,AVERAGE(I4:L4)," ") | N4: =O4-G4-D4 -> 1141 | O4: 1189 | P4: =IF(E4>0, N4+E4,"") -> 1184
A5: Marian | B5: Senton | C5: =IF(F5="Alive",D5+G5," ") -> 43 | D5: 38 | F5: Alive | G5: 5 | H5: =IF(F5="Dead",G5+D5," ") | M5: =IF(SUM(I5:L5)>0,AVERAGE(I5:L5)," ") | N5: =O5-G5-D5 -> 1146 | O5: 1189 | P5: =IF(E5>0, N5+E5,"")
A6: John | B6: Senton | C6: =IF(F6="Alive",D6+G6," ") | D6: 22 | E6: 25 | F6: Dead | G6: 5 | H6: =IF(F6="Dead",G6+D6," ") -> 27 | I6: 65 | J6: 45 | K6: 90 | L6: 80 | M6: =IF(SUM(I6:L6)>0,AVERAGE(I6:L6)," ") -> 70 | N6: =O6-G6-D6 -> 1162 | O6: 1189 | P6: =IF(E6>0, N6+E6,"") -> 1187
A7: Jory | B7: Senton | C7: =IF(F7="Alive",D7+G7," ") -> 22 | D7: 17 | F7: Alive | G7: 5 | H7: =IF(F7="Dead",G7+D7," ") | I7: 35 | J7: 110 | K7: 80 | L7: 40 | M7: =IF(SUM(I7:L7)>0,AVERAGE(I7:L7)," ") -> 66.25 | N7: =O7-G7-D7 -> 1167 | O7: 1189 | P7: =IF(E7>0, N7+E7,"")
A8: Jason | B8: Senton | C8: =IF(F8="Alive",D8+G8," ") -> 20 | D8: 15 | F8: Alive | G8: 5 | H8: =IF(F8="Dead",G8+D8," ") | I8: 50 | J8: 90 | K8: 65 | L8: 45 | M8: =IF(SUM(I8:L8)>0,AVERAGE(I8:L8)," ") -> 62.5 | N8: =O8-G8-D8 -> 1169 | O8: 1189 | P8: =IF(E8>0, N8+E8,"")
A9: Jenny | B9: Senton | C9: =IF(F9="Alive",D9+G9," ") -> 17 | D9: 12 | F9: Alive | G9: 5 | H9: =IF(F9="Dead",G9+D9," ") | M9: =IF(SUM(I9:L9)>0,AVERAGE(I9:L9)," ") | N9: =O9-G9-D9 -> 1172 | O9: 1189 | P9: =IF(E9>0, N9+E9,"")
A10: Jerod | B10: Senton | C10: =IF(F10="Alive",D10+G10," ") -> 15 | D10: 10 | F10: Alive | G10: 5 | H10: =IF(F10="Dead",G10+D10," ") | I10: 60 | J10: 55 | K10: 75 | L10: 90 | M10: =IF(SUM(I10:L10)>0,AVERAGE(I10:L10)," ") -> 70 | N10: =O10-G10-D10 -> 1174 | O10: 1189 | P10: =IF(E10>0, N10+E10,"")
A11: Garin | B11: Hearston | C11: =IF(F11="Alive",D11+G11," ") | D11: 61 | E11: 64 | F11: Dead | G11: 5 | H11: =IF(F11="Dead",G11+D11," ") -> 66 | I11: 60 | J11: 10 | K11: 90 | L11: 80 | M11: =IF(SUM(I11:L11)>0,AVERAGE(I11:L11)," ") -> 60 | N11: =O11-G11-D11 -> 1123 | O11: 1189 | P11: =IF(E11>0, N11+E11,"") -> 1187
A12: Harrison | B12: Hearston | C12: =IF(F12="Alive",D12+G12," ") -> 40 | D12: 35 | F12: Alive | G12: 5 | H12: =IF(F12="Dead",G12+D12," ") | I12: 80 | J12: 60 | K12: 50 | L12: 90 | M12: =IF(SUM(I12:L12)>0,AVERAGE(I12:L12)," ") -> 70 | N12: =O12-G12-D12 -> 1149 | O12: 1189 | P12: =IF(E12>0, N12+E12,"")
A13: John | B13: Hearston | C13: =IF(F13="Alive",D13+G13," ") -> 35 | D13: 30 | F13: Alive | G13: 5 | H13: =IF(F13="Dead",G13+D13," ") | I13: 55 | J13: 70 | K13: 100 | L13: 50 | M13: =IF(SUM(I13:L13)>0,AVERAGE(I13:L13)," ") -> 68.75 | N13: =O13-G13-D13 -> 1154 | O13: 1189 | P13: =IF(E13>0, N13+E13,"")
A14: Anne | B14: Hearston | C14: =IF(F14="Alive",D14+G14," ") -> 22 | D14: 17 | F14: Alive | G14: 5 | H14: =IF(F14="Dead",G14+D14," ") | I14: 50 | J14: 30 | K14: 90 | L14: 75 | M14: =IF(SUM(I14:L14)>0,AVERAGE(I14:L14)," ") -> 61.25 | N14: =O14-G14-D14 -> 1167 | O14: 1189 | P14: =IF(E14>0, N14+E14,"")
A15: Robert | B15: Hearston | C15: =IF(F15="Alive",D15+G15," ") -> 20 | D15: 15 | F15: Alive | G15: 5 | H15: =IF(F15="Dead",G15+D15," ") | I15: 65 | J15: 80 | K15: 90 | L15: 75 | M15: =IF(SUM(I15:L15)>0,AVERAGE(I15:L15)," ") -> 77.5 | N15: =O15-G15-D15 -> 1169 | O15: 1189 | P15: =IF(E15>0, N15+E15,"")
A16: Arthur | B16: Hearston | C16: =IF(F16="Alive",D16+G16," ") -> 18 | D16: 13 | F16: Alive | G16: 5 | H16: =IF(F16="Dead",G16+D16," ") | I16: 80 | J16: 75 | K16: 55 | L16: 65 | M16: =IF(SUM(I16:L16)>0,AVERAGE(I16:L16)," ") -> 68.75 | N16: =O16-G16-D16 -> 1171 | O16: 1189 | P16: =IF(E16>0, N16+E16,"")
A17: Frederick | B17: Reynar | C17: =IF(F17="Alive",D17+G17," ") -> 53 | D17: 48 | F17: Alive | G17: 5 | H17: =IF(F17="Dead",G17+D17," ") | M17: =IF(SUM(I17:L17)>0,AVERAGE(I17:L17)," ") | N17: =O17-G17-D17 -> 1136 | O17: 1189 | P17: =IF(E17>0, N17+E17,"")
A18: Elena | B18: Reynar | C18: =IF(F18="Alive",D18+G18," ") -> 19 | D18: 14 | F18: Alive | G18: 5 | H18: =IF(F18="Dead",G18+D18," ") | I18: 80 | J18: 20 | K18: 75 | L18: 65 | M18: =IF(SUM(I18:L18)>0,AVERAGE(I18:L18)," ") -> 60 | N18: =O18-G18-D18 -> 1170 | O18: 1189 | P18: =IF(E18>0, N18+E18,"")
A19: Ignisell | B19: Ardere | C19: =IF(F19="Alive",D19+G19," ") -> 34 | D19: 29 | F19: Alive | G19: 5 | H19: =IF(F19="Dead",G19+D19," ") | I19: 105 | J19: 20 | K19: 90 | L19: 55 | M19: =IF(SUM(I19:L19)>0,AVERAGE(I19:L19)," ") -> 67.5 | N19: =O19-G19-D19 -> 1155 | O19: 1189 | P19: =IF(E19>0, N19+E19,"")
A20: Reed | B20: Lowborn | C20: =IF(F20="Alive",D20+G20," ") -> 34 | D20: 29 | F20: Alive | G20: 5 | H20: =IF(F20="Dead",G20+D20," ") | I20: 120 | J20: 15 | K20: 70 | L20: 100 | M20: =IF(SUM(I20:L20)>0,AVERAGE(I20:L20)," ") -> 76.25 | N20: =O20-G20-D20 -> 1155 | O20: 1189 | P20: =IF(E20>0, N20+E20,"")
A21: Wilson | B21: Carthen | C21: =IF(F21="Alive",D21+G21," ") -> 25 | D21: 20 | F21: Alive | G21: 5 | H21: =IF(F21="Dead",G21+D21," ") | M21: =IF(SUM(I21:L21)>0,AVERAGE(I21:L21)," ") | N21: =O21-G21-D21 -> 1164 | O21: 1189 | P21: =IF(E21>0, N21+E21,"")
A22: Atia | B22: Carthen | C22: =IF(F22="Alive",D22+G22," ") | D22: 26 | E22: 26 | F22: Dead | G22: 5 | H22: =IF(F22="Dead",G22+D22," ") -> 31 | I22: 65 | J22: 10 | K22: 110 | L22: 50 | M22: =IF(SUM(I22:L22)>0,AVERAGE(I22:L22)," ") -> 58.75 | N22: =O22-G22-D22 -> 1158 | O22: 1189 | P22: =IF(E22>0, N22+E22,"") -> 1184
A23: Cimon | B23: Carthen | C23: =IF(F23="Alive",D23+G23," ") | D23: 35 | G23: 5 | H23: =IF(F23="Dead",G23+D23," ") | I23: 100 | J23: 45 | K23: 65 | L23: 50 | M23: =IF(SUM(I23:L23)>0,AVERAGE(I23:L23)," ") -> 65 | N23: =O23-G23-D23 -> 1149 | O23: 1189 | P23: =IF(E23>0, N23+E23,"")
A24: Chelsey | B24: Carthen | C24: =IF(F24="Alive",D24+G24," ") | G24: 5 | H24: =IF(F24="Dead",G24+D24," ") | M24: =IF(SUM(I24:L24)>0,AVERAGE(I24:L24)," ") | N24: =O24-G24-D24 -> 1184 | O24: 1189 | P24: =IF(E24>0, N24+E24,"")
G25: 5 | H25: =IF(F25="Dead",G25+D25," ") | N25: =O25-G25-D25 -> 1184 | O25: 1189 | P25: =IF(E25>0, N25+E25,"")
G26: 5 | H26: =IF(F26="Dead",G26+D26," ") | N26: =O26-G26-D26 -> 1184 | O26: 1189 | P26: =IF(E26>0, N26+E26,"")
G27: 5 | H27: =IF(F27="Dead",G27+D27," ") | N27: =O27-G27-D27 -> 1184 | O27: 1189 | P27: =IF(E27>0, N27+E27,"")
G28: 5 | N28: =O28-G28-D28 -> 1184 | O28: 1189 | P28: =IF(E28>0, N28+E28,"")
G29: 5 | N29: =O29-G29-D29 -> 1184 | O29: 1189 | P29: =IF(E29>0, N29+E29,"")
G30: 5 | N30: =O30-G30-D30 -> 1184 | O30: 1189 | P30: =IF(E30>0, N30+E30,"")
G31: 5 | N31: =O31-G31-D31 -> 1184 | O31: 1189 | P31: =IF(E31>0, N31+E31,"")
G32: 5 | N32: =O32-G32-D32 -> 1184 | O32: 1189 | P32: =IF(E32>0, N32+E32,"")
G33: 5 | N33: =O33-G33-D33 -> 1184 | O33: 1189 | P33: =IF(E33>0, N33+E33,"")
G34: 5 | N34: =O34-G34-D34 -> 1184 | O34: 1189 | P34: =IF(E34>0, N34+E34,"")
G35: 5 | N35: =O35-G35-D35 -> 1184 | O35: 1189 | P35: =IF(E35>0, N35+E35,"")
G36: 5 | N36: =O36-G36-D36 -> -5 | P36: =IF(E36>0, N36+E36,"")
G37: 5 | N37: =O37-G37-D37 -> -5 | P37: =IF(E37>0, N37+E37,"")
A50: Average | I50: =AVERAGE(I2:I49) -> 68.529412 | J50: =AVERAGE(J2:J49) -> 52.941176 | K50: =AVERAGE(K2:K49) -> 76.764706 | L50: =AVERAGE(L2:L49) -> 63.823529 | M50: =AVERAGE(M2:M49) -> 65.514706
A51: Median | I51: =MEDIAN(I2:I49) -> 65 | J51: =MEDIAN(J2:J49) -> 45 | K51: =MEDIAN(K2:K49) -> 75 | L51: =MEDIAN(L2:L49) -> 65 | M51: =MEDIAN(M2:M49) -> 66.25

Sheet Characters
A1: Name | B1: Wilson Carthen | C1: Reed Carthen | D1: Cimon Carthen | E1: Edmund Konthern II | F1: Emilan Konthern | G1: Ellan Konthern | H1: Harrison Hearston | I1: John Hearston | J1: Robert Hearston | K1: Ignisell Ardere | L1: Aura Letum | M1: Edrick of Ravenmark | N1: Jason Senton | O1: Gabren Princeps | P1: John Senton | Q1: Gordon Merek | R1: Philson Merek | S1: Henry Merek | T1: Atia Carthen | U1: Colin 'Pearl' | V1: Sir Marcus Ferrum | W1: Garin Hearston | X1: Armin Princeps | Z1: Avg | AA1: Median
A2: Discord Username | B2: vengeance014 | C2: ICBM | D2: penuppy | E2: banaenae | F2: jasuiman | G2: veronyx | H2: lucid219 | I2: en56yaw4536 | J2: thebookman10 | K2: okwithme | L2: rub.rubens11 | M2: RAW | N2: Smach | O2: TheClickBateM8 | P2: admiwart | Q2: TheGuy | R2: bigbois744 | S2: .titanlord | T2: rub.rubens11 | U2: Squidkid13 | V2: .titanlord | W2: amibcool | X2: surewarboii
A3: House | B3: Carthen | C3: Lowborn | D3: Carthen | E3: Konthern | F3: Konthern | G3: Konthern | H3: Hearston | I3: Hearston | J3: Hearston | K3: Ardere | L3: Letum | M3: Lowborn | N3: Senton | O3: Merek | P3: Senton | Q3: Merek | R3: Merek | S3: Merek | T3: Carthen | U3: Lowborn | V3: Ferrum | W3: Hearston | X3: Princeps
A4: Age | B4: 23 | C4: 33 | D4: 39 | E4: 44 | F4: 20 | G4: 22 | H4: 38 | I4: 35 | J4: 18 | K4: 33 | L4: 21 | M4: 30 | N4: 19 | O4: 20 | P4: 25 | Q4: 21 | R4: 43 | S4: 23 | T4: 26 | U4: 31 | V4: 22 | W4: 64 | X4: 20 | Z4: =AVERAGE(B4:T4) -> 28.052632 | AA4: =MEDIAN(B4:T4) -> 25
A5: Gender | B5: Male | C5: Male | D5: Male | E5: Male | F5: Male | G5: Female | H5: Male | I5: Male | J5: Male | K5: Male | L5: Female (?) | N5: Male | O5: Male | P5: Male | Q5: Male | R5: Male | S5: Male | T5: Female | U5: Male | V5: Male (?) | W5: Male | X5: Male
A6: Stress Level | B6: 0 | C6: 0 | D6: 0 | E6: 0 | F6: 0 | H6: 1 | I6: 0.5 | L6: 100000 | O6: 0 | Q6: 0 | R6: 0 | S6: 0 | T6: 0 | V6: 1.01 | W6: 0 | X6: 0
A7: Intrigue Skill | B7: 70 | C7: 120 | D7: 100 | E7: 20 | F7: 55 | G7: 100 | H7: 80 | I7: 55 | J7: 65 | K7: 105 | L7: 100 | M7: 50 | N7: 50 | O7: 60 | P7: 65 | Q7: 50 | R7: 60 | S7: 50 | T7: 65 | U7: 80 | V7: 70 | W7: 60 | X7: 35 | Z7: =AVERAGE(B7:T7) -> 69.473684 | AA7: =MEDIAN(B7:T7) -> 65
A8: Combat Skill | B8: 85 | C8: 15 | D8: 45 | E8: 75 | F8: 90 | G8: 20 | H8: 60 | I8: 70 | J8: 80 | K8: 20 | L8: 15 | M8: 50 | N8: 90 | O8: 40 | P8: 45 | Q8: 90 | R8: 40 | S8: 80 | T8: 10 | U8: 70 | V8: 110 | W8: 10 | X8: 125 | Z8: =AVERAGE(B8:T8) -> 53.684211 | AA8: =MEDIAN(B8:T8) -> 50
A9: Diplomacy Skill | B9: 50 | C9: 70 | D9: 65 | E9: 85 | F9: 35 | G9: 90 | H9: 50 | I9: 100 | J9: 90 | K9: 90 | L9: 75 | M9: 50 | N9: 65 | O9: 60 | P9: 90 | Q9: 30 | R9: 100 | S9: 40 | T9: 110 | U9: 85 | V9: 65 | W9: 90 | X9: 50 | Z9: =AVERAGE(B9:T9) -> 70.789474 | AA9: =MEDIAN(B9:T9) -> 70
A10: Stewardship Skill | B10: 20 | C10: 100 | D10: 50 | E10: 70 | F10: 60 | G10: 45 | H10: 90 | I10: 50 | J10: 75 | K10: 55 | L10: 65 | M10: 50 | N10: 45 | O10: 35 | P10: 80 | Q10: 80 | R10: 50 | S10: 70 | T10: 50 | U10: 40 | V10: 35 | W10: 80 | X10: 40 | Z10: =AVERAGE(B10:T10) -> 60 | AA10: =MEDIAN(B10:T10) -> 55
A11: Avg Skill | B11: =B12/4 -> 56.25 | C11: =C12/4 -> 76.25 | D11: =D12/4 -> 65 | E11: =E12/4 -> 62.5 | F11: =F12/4 -> 60 | G11: =G12/4 -> 63.75 | H11: =H12/4 -> 70 | I11: =I12/4 -> 68.75 | ... X11: =X12/4 -> 62.5 | Z11: =AVERAGE(B11:T11) -> 63.486842 | AA11: =MEDIAN(B11:T11) -> 62.5
A12: Total Skill | B12: =SUM(B7:B10) -> 225 | C12: =SUM(C7:C10) -> 305 | D12: =SUM(D7:D10) -> 260 | E12: =SUM(E7:E10) -> 250 | F12: =SUM(F7:F10) -> 240 | G12: =SUM(G7:G10) -> 255 | H12: =SUM(H7:H10) -> 280 | I12: =SUM(I7:I10) -> 275 | ... X12: =SUM(X7:X10) -> 250 | Z12: =AVERAGE(B12:T12) -> 253.94737 | AA12: =MEDIAN(B12:T12) -> 250
A14: Future Age | B14: =B4+1 -> 24 | C14: =C4+1 -> 34 | D14: =D4+1 -> 40 | E14: =E4+1 -> 45 | F14: =F4+1 -> 21 | G14: =G4+1 -> 23 | H14: =H4+1 -> 39 | I14: =I4+1 -> 36 | ... N14: =N4+1 -> 20 | U14: =U4+1 -> 32 | V14: =V4+1 -> 23 | W14: =W4+1 -> 65 | X14: =X4+1 -> 21

Sheet NPCs
A1: Name | B1: Sir Finley Lowborn | C1: Sir Jory Senton | D1: Maxwell Smithson | E1: Sir Seiron "The Old" | F1: The Patriarch | G1: Frederick Reynar | H1: Elena Reynar | I1: Anne Hearston | J1: Val Ecton | L1: Avg | M1: Median
A2: House | C2: Senton | D2: Smithson | F2: Unknown | G2: Reynar | H2: Reynar | I2: Hearston | J2: Ecton
A3: Age | B3: 24 | C3: 21 | D3: 38 | E3: 53 | F3: 47 | G3: 52 | H3: 18 | I3: 20 | J3: 19 | L3: =AVERAGE(B3:J3) -> 32.444444 | M3: =MEDIAN(B3:J3) -> 24
A4: Gender | B4: Male | C4: Male | D4: Male | E4: Male | F4: Male | G4: Male | H4: Female | I4: Female
A5: Intrigue Skill | B5: 65 | C5: 35 | D5: 0 | E5: 40 | F5: ??? | G5: 50 | H5: 80 | I5: 50 | J5: 55 | L5: =AVERAGE(B5:J5) -> 46.875 | M5: =MEDIAN(B5:J5) -> 50
A6: Combat Skill | B6: 85 | C6: 110 | D6: 105 | E6: 70 | F6: ??? | G6: 80 | H6: 20 | I6: 30 | J6: 90 | L6: =AVERAGE(B6:J6) -> 73.75 | M6: =MEDIAN(B6:J6) -> 82.5
A7: Diplomacy Skill | B7: 30 | C7: 80 | D7: 35 | E7: 45 | F7: ??? | G7: 75 | H7: 75 | I7: 90 | J7: 75 | L7: =AVERAGE(B7:J7) -> 63.125 | M7: =MEDIAN(B7:J7) -> 75
A8: Stewardship Skill | B8: 40 | C8: 40 | D8: 40 | E8: 60 | F8: ??? | G8: 45 | H8: 65 | I8: 75 | J8: 60 | L8: =AVERAGE(B8:J8) -> 53.125 | M8: =MEDIAN(B8:J8) -> 52.5
B9: =SUM(B5:B8) -> 220 | C9: =SUM(C5:C8) -> 265 | D9: =SUM(D5:D8) -> 180 | E9: =SUM(E5:E8) -> 215 | F9: =SUM(F5:F8) -> 0 | G9: =SUM(G5:G8) -> 250 | H9: =SUM(H5:H8) -> 240 | I9: =SUM(I5:I8) -> 245 | J9: =SUM(J5:J8) -> 280 | L9: =AVERAGE(B9:J9) -> 210.55556 | M9: =MEDIAN(B9:J9) -> 240
B10: =B3+1 -> 25 | C10: =C3+1 -> 22 | D10: =D3+1 -> 39 | E10: =E3+1 -> 54 | F10: =F3+1 -> 48 | G10: =G3+1 -> 53 | H10: =H3+1 -> 19 | I10: =I3+1 -> 21 | J10: =J3+1 -> 20

Sheet Secret Sheet
A1: Crownlands | B1: 0 | C1: 0 | D1: =C1-F1 -> 0 | E1: =(Provinces!C2*0.005)-F1 -> 30993.535 | F1: =SUM(G1:I1) -> 0 | I1: =(C1*0.02)*J1 -> 0 | K1: =IF(AND('The Crown'!B2<0,C1>0),1,0) -> 0
A2: Dreghold | B2: 0.25 | C2: 55000 | D2: =C2-F2 -> 45561 | E2: =(Provinces!C3*0.005)-F2 -> 55800.15 | F2: =SUM(G2:I2) -> 9439 | G2: 1034 | H2: 4005 | I2: =(C2*0.02)*J2 -> 4400 | J2: 4 | K2: =IF(AND(Provinces!B3<0,C2>0),1,0) -> 1
A3: Madinglia | B3: 0 | C3: 18000 | D3: =C3-F3 -> 18000 | E3: =(Provinces!C4*0.005)-F3 -> 18696.055 | F3: =SUM(G3:I3) -> 0 | I3: =(C3*0.02)*J3 -> 0 | K3: =IF(AND(Provinces!B4<0,C3>0),1,0) -> 0
A4: Pearlpass | B4: 0.25 | C4: 0 | D4: =C4-F4 -> 0 | E4: =(Provinces!C5*0.005)-F4 -> 15912.62 | F4: =SUM(G4:I4) -> 0 | I4: =(C4*0.02)*J4 -> 0 | K4: =IF(AND(Provinces!B5<0,C4>0),1,0) -> 0
A5: Ralim | B5: 0.25 | C5: 0 | D5: =C5-F5 -> 0 | E5: =(Provinces!C6*0.005)-F5 -> 38470.655 | F5: =SUM(G5:I5) -> 0 | I5: =(C5*0.02)*J5 -> 0 | K5: =IF(AND(Provinces!B6<0,C5>0),1,0) -> 0
A6: Sirong | B6: 0.25 | C6: 26500 | D6: =C6-F6 -> 16275 | E6: =(Provinces!C7*0.005)-F6 -> 69979.68 | F6: =SUM(G6:I6) -> 10225 | G6: 4000 | H6: 4105 | I6: =(C6*0.02)*J6 -> 2120 | J6: 4 | K6: =IF(AND(Provinces!B7<0,C6>0),1,0) -> 1
A7: Swanhall | B7: 0.25 | C7: 3000 | D7: =C7-F7 -> 1111 | E7: =(Provinces!C8*0.005)-F7 -> 83146.18 | F7: =SUM(G7:I7) -> 1889 | G7: 1035 | H7: 854 | I7: =(C7*0.02)*J7 -> 0 | K7: =IF(AND(Provinces!B8<0,C7>0),1,0) -> 0
B8: Province Tax Rates | C8: Raised Levies | D8: True Raised | E8: True Possible Levies | F8: Casualties | G8: Injured | H8: Dead | I8: Deserted | J8: Ticks Without Pay | K8: Without Pay T/F | L8: Current Casualties | M8: Tentative Casualties | N8: Future Casualties

Sheet Lesser House Dominions
B1: Gold Kastar Coins | C1: Total Population | D1: Urban Population | E1: Rural Population | F1: Gold Net Income | G1: Retinues | H1: Raised Levys | I1: Possible Levys | J1: Projected Gold | K1: Urban Population % | L1: Rural Population %
A2: Sentons | B2: -1889.438 | C2: =D2+E2 -> 468927 | D2: =Cities!E102 -> 19353 | E2: 449574 | F2: =Economics!B9-Economics!C9 -> 749.27992 | G2: ='Retinue Breakdown'!R10 -> 50 | I2: =C2*0.005 -> 2344.635 | J2: =B2+F2 -> -1140.1581 | K2: =D2/C2 -> 0.041270816 | L2: =E2/C2 -> 0.95872918 | M2: =B2+F2 -> -1140.1581
B3: 0 | J3: =B3+F3 -> 0 | K3: =D3/C3 -> #DIV/0! | L3: =E3/C3 -> #DIV/0! | M3: =B3+F3 -> 0
B4: 0 | J4: =B4+F4 -> 0 | K4: =D4/C4 -> #DIV/0! | L4: =E4/C4 -> #DIV/0! | M4: =B4+F4 -> 0
B5: 0 | J5: =B5+F5 -> 0 | K5: =D5/C5 -> #DIV/0! | L5: =E5/C5 -> #DIV/0! | M5: =B5+F5 -> 0
B6: 0 | J6: =B6+F6 -> 0 | K6: =D6/C6 -> #DIV/0! | L6: =E6/C6 -> #DIV/0! | M6: =B6+F6 -> 0
B7: 0 | J7: =B7+F7 -> 0 | K7: =D7/C7 -> #DIV/0! | L7: =E7/C7 -> #DIV/0! | M7: =B7+F7 -> 0
B8: 0 | J8: =B8+F8 -> 0 | K8: =D8/C8 -> #DIV/0! | L8: =E8/C8 -> #DIV/0! | M8: =B8+F8 -> 0
A9: Average | B9: =AVERAGE(B2:B8) -> -269.91972 | C9: =AVERAGE(C2:C8) -> 468927 | D9: =AVERAGE(D2:D8) -> 19353 | E9: =AVERAGE(E2:E8) -> 449574 | F9: =AVERAGE(F2:F8) -> 749.27992 | G9: =AVERAGE(G2:G8) -> 50 | I9: =AVERAGE('Secret Sheet'!E1:E7) -> 44714.125 | J9: =AVERAGE(J2:J8) -> -162.87973 | K9: =AVERAGE(K2:K8) -> #DIV/0! | L9: =AVERAGE(L2:L8) -> #DIV/0! | M9: =B9+F9 -> 479.3602
A10: Total | B10: =SUM(B2:B8) -> -1889.438 | C10: =SUM(C2:C8) -> 468927 | D10: =SUM(D2:D8) -> 19353 | E10: =SUM(E2:E8) -> 449574 | F10: =SUM(F2:F8) -> 749.27992 | G10: =SUM(G2:G8) -> 50 | I10: =SUM('Secret Sheet'!E1:E7) -> 312998.88 | J10: =SUM(J2:J8) -> -1140.1581 | M10: =B10+F10 -> -1140.1581

Sheet Economics
B1: Gold Income | C1: Gold Spending | D1: Final Total Tax Income | E1: Raw Total Tax Income | F1: Urban Tax Income | G1: Rural Tax Income | H1: Diplomatic Income | I1: Total Military Spending | J1: Retinue Spending | K1: Levy Spending | L1: Diplomatic Spending
A2: Crownlands | D2: =E2*(1-'Secret Sheet'!B1) -> 7416.5166 | E2: =SUM(F2:G2) -> 7416.5166 | F2: =SUM(Cities!P3:P13) -> 3824.355 | G2: ='Price Sheet (Ignore)'!$G$2*((Provinces!E2/5)*'Price Sheet (Ignore)'!$I$2) -> 3592.1616 | H2: 0 | I2: =J2+K2 -> 2917.9483 | J2: ='Retinue Breakdown'!R12 -> 2670 | K2: =Provinces!H2*2+'Secret Sheet'!E1*0.008 -> 247.94828 | L2: 500
A3: Dreghold | B3: =D3+H3 -> 8787.5312 | C3: =I3+L3 -> 93068.401 | D3: =E3*(1-'Secret Sheet'!B2) -> 8787.5312 | E3: =SUM(F3:G3) -> 11716.708 | F3: =SUM(Cities!P4:P14) -> 4014.0217 | G3: ='Price Sheet (Ignore)'!$G$2*((Provinces!E3/5)*'Price Sheet (Ignore)'!$I$2) -> 7702.6866 | H3: 0 | I3: =J3+K3 -> 93068.401 | J3: ='Retinue Breakdown'!R13 -> 1500 | K3: =Provinces!H3*2+'Secret Sheet'!E2*0.008 -> 91568.401 | L3: 0
A4: Madinglia | B4: =D4+H4 -> 7240.3267 | C4: =I4+L4 -> 38649.568 | D4: =E4*(1-'Secret Sheet'!B3) -> 6040.3267 | E4: =SUM(F4:G4) -> 6040.3267 | F4: =SUM(Cities!P5:P15) -> 3840.3217 | G4: ='Price Sheet (Ignore)'!$G$2*((Provinces!E4/5)*'Price Sheet (Ignore)'!$I$2) -> 2200.005 | H4: 1200 | I4: =J4+K4 -> 38649.568 | J4: ='Retinue Breakdown'!R14 -> 2500 | K4: =Provinces!H4*2+'Secret Sheet'!E3*0.008 -> 36149.568 | L4: 0
A5: Pearlpass | B5: =D5+H5 -> 4684.7541 | C5: =I5+L5 -> 1627.301 | D5: =E5*(1-'Secret Sheet'!B4) -> 4684.7541 | E5: =SUM(F5:G5) -> 6246.3388 | F5: =SUM(Cities!P6:P16) -> 4350.37 | G5: ='Price Sheet (Ignore)'!$G$2*((Provinces!E5/5)*'Price Sheet (Ignore)'!$I$2) -> 1895.9688 | H5: 0 | I5: =J5+K5 -> 1627.301 | J5: ='Retinue Breakdown'!R15 -> 1500 | K5: =Provinces!H5*2+'Secret Sheet'!E4*0.008 -> 127.30096 | L5: 0
A6: Ralim | B6: =D6+H6 -> 6617.7505 | C6: =I6+L6 -> 1807.7652 | D6: =E6*(1-'Secret Sheet'!B5) -> 6617.7505 | E6: =SUM(F6:G6) -> 8823.6673 | F6: =SUM(Cities!P7:P17) -> 4286.7433 | G6: ='Price Sheet (Ignore)'!$G$2*((Provinces!E6/5)*'Price Sheet (Ignore)'!$I$2) -> 4536.924 | H6: 0 | I6: =J6+K6 -> 1807.7652 | J6: ='Retinue Breakdown'!R16 -> 1500 | K6: =Provinces!H6*2+'Secret Sheet'!E5*0.008 -> 307.76524 | L6: 0
A7: Sirong | B7: =D7+H7 -> 9860.1282 | C7: =I7+L7 -> 34709.837 | D7: =E7*(1-'Secret Sheet'!B6) -> 9860.1282 | E7: =SUM(F7:G7) -> 13146.838 | F7: =SUM(Cities!P8:P18) -> 3798.5767 | G7: ='Price Sheet (Ignore)'!$G$2*((Provinces!E7/5)*'Price Sheet (Ignore)'!$I$2) -> 9348.261 | H7: 0 | I7: =J7+K7 -> 34709.837 | J7: ='Retinue Breakdown'!R17 -> 1600 | K7: =Provinces!H7*2+'Secret Sheet'!E6*0.008 -> 33109.837 | L7: 0
A8: Swanhall | B8: =D8+H8 -> 10699.256 | C8: =I8+L8 -> 4387.1694 | D8: =E8*(1-'Secret Sheet'!B7) -> 10149.256 | E8: =SUM(F8:G8) -> 13532.342 | F8: =SUM(Cities!P9:P19) -> 3675.8767 | G8: ='Price Sheet (Ignore)'!$G$2*((Provinces!E8/5)*'Price Sheet (Ignore)'!$I$2) -> 9856.4652 | H8: 550 | I8: =J8+K8 -> 4387.1694 | J8: ='Retinue Breakdown'!R18 -> 1500 | K8: =Provinces!H8*2+'Secret Sheet'!E7*0.008 -> 2887.1694 | L8: 0
A9: Sentons | B9: =D9+H9 -> 2268.037 | C9: =I9+L9 -> 1518.7571 | D9: =E9 -> 1768.037 | E9: =SUM(F9:G9) -> 1768.037 | F9: =Cities!P102 -> 419.315 | G9: ='Price Sheet (Ignore)'!$G$2*(('Lesser House Dominions'!E2)*'Price Sheet (Ignore)'!$I$2) -> 1348.722 | H9: 500 | I9: =J9+K9 -> 1518.7571 | J9: ='Retinue Breakdown'!R19 -> 1500 | K9: ='Lesser House Dominions'!H2*2+'Lesser House Dominions'!I2*0.008 -> 18.75708 | L9: 0
A10: The Crown | B10: =D10+H10+D2 -> 20782.99 | C10: =I2+L2 -> 3417.9483 | D10: =(E11-D11) -> 13366.473 | H10: =H2 -> 0 | I10: =I2 -> 2917.9483 | J10: =J2 -> 2670 | K10: =K2 -> 247.94828 | L10: 0
A11: Total | B11: =D11+H11 -> 55306.264 | C11: =E11+I11 -> 244090.73 | D11: =SUM(D2:D8) -> 53556.264 | E11: =SUM(E2:E8) -> 66922.737 | F11: =SUM(F2:F8) -> 27790.265 | G11: =SUM(G2:G8) -> 39132.472 | H11: =SUM(H2:H8) -> 1750 | I11: =SUM(I2:I8) -> 177167.99 | J11: =SUM(J2:J8) -> 12770 | K11: =SUM(K2:K8) -> 164397.99 | L11: =SUM(L2:L10) -> 500
A12: Average | B12: =D12+H12 -> 7900.8948 | C12: =E12+I12 -> 34870.104 | D12: =AVERAGE(D2:D8) -> 7650.8948 | E12: =AVERAGE(E2:E8) -> 9560.391 | F12: =AVERAGE(F2:F8) -> 3970.0379 | G12: =AVERAGE(G2:G8) -> 5590.3532 | H12: =AVERAGE(H2:H8) -> 250 | I12: =AVERAGE(I2:I8) -> 25309.713 | J12: =AVERAGE(J2:J8) -> 1824.2857 | K12: =AVERAGE(K2:K8) -> 23485.427 | L12: =AVERAGE(L2:L8) -> 71.428571

Sheet Retinue Breakdown
B1: Infantrymen | G1: Archers | L1: Cavalry
B2: Tier I | C2: Tier II | D2: Tier III | E2: Tier IV | F2: Tier V | G2: Tier I | H2: Tier II | I2: Tier III | J2: Tier IV | K2: Tier V | L2: Tier I | M2: Tier II | N2: Tier III | O2: Tier IV | P2: Tier V | Q2: Horse Archers | R2: Total
A3: The Crown | B3: 0 | C3: 0 | D3: 20 | E3: 0 | F3: 35 | G3: 0 | H3: 0 | I3: 40 | J3: 0 | K3: 0 | L3: 0 | M3: 0 | N3: 0 | O3: 0 | P3: 3 | Q3: 15 | R3: =SUM(B3:Q3) -> 113
A4: Dreghold | B4: 0 | C4: 0 | D4: 0 | E4: 0 | F4: 50 | G4: 0 | H4: 0 | I4: 0 | J4: 0 | K4: 0 | L4: 0 | M4: 0 | N4: 0 | O4: 0 | P4: 0 | Q4: 0 | R4: =SUM(B4:Q4) -> 50
A5: Madinglia | B5: 150 | C5: 0 | D5: 0 | E5: 0 | F5: 50 | G5: 50 | H5: 0 | I5: 0 | J5: 0 | K5: 0 | L5: 0 | M5: 0 | N5: 0 | O5: 0 | P5: 0 | Q5: 0 | R5: =SUM(B5:Q5) -> 250
A6: Pearlpass | B6: 0 | C6: 0 | D6: 0 | E6: 0 | F6: 50 | G6: 0 | H6: 0 | I6: 0 | J6: 0 | K6: 0 | L6: 0 | M6: 0 | N6: 0 | O6: 0 | P6: 0 | Q6: 0 | R6: =SUM(B6:Q6) -> 50
A7: Ralim | B7: 0 | C7: 0 | D7: 0 | E7: 0 | F7: 50 | G7: 0 | H7: 0 | I7: 0 | J7: 0 | K7: 0 | L7: 0 | M7: 0 | N7: 0 | O7: 0 | P7: 0 | Q7: 0 | R7: =SUM(B7:Q7) -> 50
A8: Sirong | B8: 0 | C8: 0 | D8: 0 | E8: 0 | F8: 50 | G8: 20 | H8: 0 | I8: 0 | J8: 0 | K8: 0 | L8: 0 | M8: 0 | N8: 0 | O8: 0 | P8: 0 | Q8: 0 | R8: =SUM(B8:Q8) -> 70
A9: Swanhall | B9: 0 | C9: 0 | D9: 0 | E9: 0 | F9: 50 | G9: 0 | H9: 0 | I9: 0 | J9: 0 | K9: 0 | L9: 0 | M9: 0 | N9: 0 | O9: 0 | P9: 0 | Q9: 0 | R9: =SUM(B9:Q9) -> 50
A10: Sentons | B10: 0 | C10: 0 | D10: 0 | E10: 0 | F10: 50 | G10: 0 | H10: 0 | I10: 0 | J10: 0 | K10: 0 | L10: 0 | M10: 0 | N10: 0 | O10: 0 | P10: 0 | Q10: 0 | R10: =SUM(B10:Q10) -> 50
B11: Infantry Costs | G11: Archer Costs | L11: Cavalry Costs | R11: Total Cost
A12: The Crown | B12: =B3*5 -> 0 | C12: =C3*10 -> 0 | D12: =D3*15 -> 300 | E12: =E3*20 -> 0 | F12: =F3*30 -> 1050 | G12: =G3*5 -> 0 | H12: =H3*10 -> 0 | I12: =I3*15 -> 600 | J12: =J3*20 -> 0 | K12: =K3*30 -> 0 | L12: =L3*10 -> 0 | M12: =M3*15 -> 0 | N12: =N3*25 -> 0 | O12: =O3*30 -> 0 | P12: =P3*40 -> 120 | Q12: =Q3*40 -> 600 | R12: =SUM(B12:Q12) -> 2670
A13: Dreghold | B13: =B4*5 -> 0 | C13: =C4*10 -> 0 | D13: =D4*15 -> 0 | E13: =E4*20 -> 0 | F13: =F4*30 -> 1500 | G13: =G4*5 -> 0 | H13: =H4*10 -> 0 | I13: =I4*15 -> 0 | J13: =J4*20 -> 0 | K13: =K4*30 -> 0 | L13: =L4*10 -> 0 | M13: =M4*15 -> 0 | N13: =N4*25 -> 0 | O13: =O4*30 -> 0 | P13: =P4*40 -> 0 | Q13: =Q4*40 -> 0 | R13: =SUM(B13:Q13) -> 1500
A14: Madinglia | B14: =B5*5 -> 750 | C14: =C5*10 -> 0 | D14: =D5*15 -> 0 | E14: =E5*20 -> 0 | F14: =F5*30 -> 1500 | G14: =G5*5 -> 250 | H14: =H5*10 -> 0 | I14: =I5*15 -> 0 | J14: =J5*20 -> 0 | K14: =K5*30 -> 0 | L14: =L5*10 -> 0 | M14: =M5*15 -> 0 | N14: =N5*25 -> 0 | O14: =O5*30 -> 0 | P14: =P5*40 -> 0 | Q14: =Q5*40 -> 0 | R14: =SUM(B14:Q14) -> 2500
A15: Pearlpass | B15: =B6*5 -> 0 | C15: =C6*10 -> 0 | D15: =D6*15 -> 0 | E15: =E6*20 -> 0 | F15: =F6*30 -> 1500 | G15: =G6*5 -> 0 | H15: =H6*10 -> 0 | I15: =I6*15 -> 0 | J15: =J6*20 -> 0 | K15: =K6*30 -> 0 | L15: =L6*10 -> 0 | M15: =M6*15 -> 0 | N15: =N6*25 -> 0 | O15: =O6*30 -> 0 | P15: =P6*40 -> 0 | Q15: =Q6*40 -> 0 | R15: =SUM(B15:Q15) -> 1500
A16: Ralim | B16: =B7*5 -> 0 | C16: =C7*10 -> 0 | D16: =D7*15 -> 0 | E16: =E7*20 -> 0 | F16: =F7*30 -> 1500 | G16: =G7*5 -> 0 | H16: =H7*10 -> 0 | I16: =I7*15 -> 0 | J16: =J7*20 -> 0 | K16: =K7*30 -> 0 | L16: =L7*10 -> 0 | M16: =M7*15 -> 0 | N16: =N7*25 -> 0 | O16: =O7*30 -> 0 | P16: =P7*40 -> 0 | Q16: =Q7*40 -> 0 | R16: =SUM(B16:Q16) -> 1500
A17: Sirong | B17: =B8*5 -> 0 | C17: =C8*10 -> 0 | D17: =D8*15 -> 0 | E17: =E8*20 -> 0 | F17: =F8*30 -> 1500 | G17: =G8*5 -> 100 | H17: =H8*10 -> 0 | I17: =I8*15 -> 0 | J17: =J8*20 -> 0 | K17: =K8*30 -> 0 | L17: =L8*10 -> 0 | M17: =M8*15 -> 0 | N17: =N8*25 -> 0 | O17: =O8*30 -> 0 | P17: =P8*40 -> 0 | Q17: =Q8*40 -> 0 | R17: =SUM(B17:Q17) -> 1600
A18: Swanhall | B18: =B9*5 -> 0 | C18: =C9*10 -> 0 | D18: =D9*15 -> 0 | E18: =E9*20 -> 0 | F18: =F9*30 -> 1500 | G18: =G9*5 -> 0 | H18: =H9*10 -> 0 | I18: =I9*15 -> 0 | J18: =J9*20 -> 0 | K18: =K9*30 -> 0 | L18: =L9*10 -> 0 | M18: =M9*15 -> 0 | N18: =N9*25 -> 0 | O18: =O9*30 -> 0 | P18: =P9*40 -> 0 | Q18: =Q9*40 -> 0 | R18: =SUM(B18:Q18) -> 1500
A19: Sentons | B19: =B10*5 -> 0 | C19: =C10*10 -> 0 | D19: =D10*15 -> 0 | E19: =E10*20 -> 0 | F19: =F10*30 -> 1500 | G19: =G10*5 -> 0 | H19: =H10*10 -> 0 | I19: =I10*15 -> 0 | J19: =J10*20 -> 0 | K19: =K10*30 -> 0 | L19: =L10*10 -> 0 | M19: =M10*15 -> 0 | N19: =N10*25 -> 0 | O19: =O10*30 -> 0 | P19: =P10*40 -> 0 | Q19: =Q10*40 -> 0 | R19: =SUM(B19:Q19) -> 1500

Sheet New Retinues Summary
C1: Infantrymen | H1: Archers | M1: Cavalry
C2: Tier I | D2: Tier II | E2: Tier III | F2: Tier IV | G2: Tier V | H2: Tier I | I2: Tier II | J2: Tier III | K2: Tier IV | L2: Tier V | M2: Tier I | N2: Tier II | O2: Tier III | P2: Tier IV | Q2: Tier V | R2: Horse Archers | S2: Total
A3: The Crown | B3: Count | C3: ='New Retinues Breakdown'!C4*'New Retinues Breakdown'!C7*'New Retinues Breakdown'!C$35 -> 0 | D3: ='New Retinues Breakdown'!D4*'New Retinues Breakdown'!D7*'New Retinues Breakdown'!D$35 -> 0 | E3: ='New Retinues Breakdown'!E4*'New Retinues Breakdown'!E7*'New Retinues Breakdown'!E$35 -> 100 | F3: ='New Retinues Breakdown'!F4*'New Retinues Breakdown'!F7*'New Retinues Breakdown'!F$35 -> 0 | G3: ='New Retinues Breakdown'!G4*'New Retinues Breakdown'!G7*'New Retinues Breakdown'!G$35 -> 100 | H3: ='New Retinues Breakdown'!H4*'New Retinues Breakdown'!H7*'New Retinues Breakdown'!H$35 -> 0 | I3: ='New Retinues Breakdown'!I4*'New Retinues Breakdown'!I7*'New Retinues Breakdown'!I$35 -> 0 | J3: ='New Retinues Breakdown'!J4*'New Retinues Breakdown'!J7*'New Retinues Breakdown'!J$35 -> 100 | ... R3: ='New Retinues Breakdown'!R4*'New Retinues Breakdown'!R7*'New Retinues Breakdown'!R$35 -> 50 | S3: =SUM(C3:R3) -> 400
A4: Dreghold | B4: Count | C4: ='New Retinues Breakdown'!C9*'New Retinues Breakdown'!C12*'New Retinues Breakdown'!C$35 -> 0 | D4: ='New Retinues Breakdown'!D9*'New Retinues Breakdown'!D12*'New Retinues Breakdown'!D$35 -> 0 | E4: ='New Retinues Breakdown'!E9*'New Retinues Breakdown'!E12*'New Retinues Breakdown'!E$35 -> 800 | F4: ='New Retinues Breakdown'!F9*'New Retinues Breakdown'!F12*'New Retinues Breakdown'!F$35 -> 800 | G4: ='New Retinues Breakdown'!G9*'New Retinues Breakdown'!G12*'New Retinues Breakdown'!G$35 -> 0 | H4: ='New Retinues Breakdown'!H9*'New Retinues Breakdown'!H12*'New Retinues Breakdown'!H$35 -> 0 | I4: ='New Retinues Breakdown'!I9*'New Retinues Breakdown'!I12*'New Retinues Breakdown'!I$35 -> 0 | J4: ='New Retinues Breakdown'!J9*'New Retinues Breakdown'!J12*'New Retinues Breakdown'!J$35 -> 200 | ... R4: ='New Retinues Breakdown'!R9*'New Retinues Breakdown'!R12*'New Retinues Breakdown'!R$35 -> 0 | S4: =SUM(C4:R4) -> 2000
A5: Madinglia | B5: Count | C5: ='New Retinues Breakdown'!C14*'New Retinues Breakdown'!C17*'New Retinues Breakdown'!C$35 -> 200 | D5: ='New Retinues Breakdown'!D14*'New Retinues Breakdown'!D17*'New Retinues Breakdown'!D$35 -> 0 | E5: ='New Retinues Breakdown'!E14*'New Retinues Breakdown'!E17*'New Retinues Breakdown'!E$35 -> 0 | F5: ='New Retinues Breakdown'!F14*'New Retinues Breakdown'!F17*'New Retinues Breakdown'!F$35 -> 0 | G5: ='New Retinues Breakdown'!G14*'New Retinues Breakdown'!G17*'New Retinues Breakdown'!G$35 -> 0 | H5: ='New Retinues Breakdown'!H14*'New Retinues Breakdown'!H17*'New Retinues Breakdown'!H$35 -> 100 | I5: ='New Retinues Breakdown'!I14*'New Retinues Breakdown'!I17*'New Retinues Breakdown'!I$35 -> 0 | J5: ='New Retinues Breakdown'!J14*'New Retinues Breakdown'!J17*'New Retinues Breakdown'!J$35 -> 0 | ... R5: ='New Retinues Breakdown'!R14*'New Retinues Breakdown'!R17*'New Retinues Breakdown'!R$35 -> 0 | S5: =SUM(C5:R5) -> 300
A6: Ralim | B6: Count | C6: ='New Retinues Breakdown'!C19*'New Retinues Breakdown'!C22*'New Retinues Breakdown'!C$35 -> 0 | D6: ='New Retinues Breakdown'!D19*'New Retinues Breakdown'!D22*'New Retinues Breakdown'!D$35 -> 0 | E6: ='New Retinues Breakdown'!E19*'New Retinues Breakdown'!E22*'New Retinues Breakdown'!E$35 -> 0 | F6: ='New Retinues Breakdown'!F19*'New Retinues Breakdown'!F22*'New Retinues Breakdown'!F$35 -> 0 | G6: ='New Retinues Breakdown'!G19*'New Retinues Breakdown'!G22*'New Retinues Breakdown'!G$35 -> 0 | H6: ='New Retinues Breakdown'!H19*'New Retinues Breakdown'!H22*'New Retinues Breakdown'!H$35 -> 0 | I6: ='New Retinues Breakdown'!I19*'New Retinues Breakdown'!I22*'New Retinues Breakdown'!I$35 -> 0 | J6: ='New Retinues Breakdown'!J19*'New Retinues Breakdown'!J22*'New Retinues Breakdown'!J$35 -> 0 | ... R6: ='New Retinues Breakdown'!R19*'New Retinues Breakdown'!R22*'New Retinues Breakdown'!R$35 -> 0 | S6: =SUM(C6:R6) -> 0
A7: Sirong | B7: Count | C7: ='New Retinues Breakdown'!C24*'New Retinues Breakdown'!C27*'New Retinues Breakdown'!C$35 -> 100 | D7: ='New Retinues Breakdown'!D24*'New Retinues Breakdown'!D27*'New Retinues Breakdown'!D$35 -> 0 | E7: ='New Retinues Breakdown'!E24*'New Retinues Breakdown'!E27*'New Retinues Breakdown'!E$35 -> 0 | F7: ='New Retinues Breakdown'!F24*'New Retinues Breakdown'!F27*'New Retinues Breakdown'!F$35 -> 0 | G7: ='New Retinues Breakdown'!G24*'New Retinues Breakdown'!G27*'New Retinues Breakdown'!G$35 -> 0 | H7: ='New Retinues Breakdown'!H24*'New Retinues Breakdown'!H27*'New Retinues Breakdown'!H$35 -> 100 | I7: ='New Retinues Breakdown'!I24*'New Retinues Breakdown'!I27*'New Retinues Breakdown'!I$35 -> 0 | J7: ='New Retinues Breakdown'!J24*'New Retinues Breakdown'!J27*'New Retinues Breakdown'!J$35 -> 0 | ... R7: ='New Retinues Breakdown'!R24*'New Retinues Breakdown'!R27*'New Retinues Breakdown'!R$35 -> 0 | S7: =SUM(C7:R7) -> 200
A8: Swanhall | B8: Count | C8: ='New Retinues Breakdown'!C29*'New Retinues Breakdown'!C32*'New Retinues Breakdown'!C$35 -> 0 | D8: ='New Retinues Breakdown'!D29*'New Retinues Breakdown'!D32*'New Retinues Breakdown'!D$35 -> 0 | E8: ='New Retinues Breakdown'!E29*'New Retinues Breakdown'!E32*'New Retinues Breakdown'!E$35 -> 0 | F8: ='New Retinues Breakdown'!F29*'New Retinues Breakdown'!F32*'New Retinues Breakdown'!F$35 -> 0 | G8: ='New Retinues Breakdown'!G29*'New Retinues Breakdown'!G32*'New Retinues Breakdown'!G$35 -> 0 | H8: ='New Retinues Breakdown'!H29*'New Retinues Breakdown'!H32*'New Retinues Breakdown'!H$35 -> 0 | I8: ='New Retinues Breakdown'!I29*'New Retinues Breakdown'!I32*'New Retinues Breakdown'!I$35 -> 0 | J8: ='New Retinues Breakdown'!J29*'New Retinues Breakdown'!J32*'New Retinues Breakdown'!J$35 -> 0 | ... R8: ='New Retinues Breakdown'!R29*'New Retinues Breakdown'!R32*'New Retinues Breakdown'!R$35 -> 0 | S8: =SUM(C8:R8) -> 0
A9: The Crown | B9: Cost | C9: ='New Retinues Breakdown'!C6 -> 0 | D9: ='New Retinues Breakdown'!D6 -> 0 | E9: ='New Retinues Breakdown'!E6 -> 100 | F9: ='New Retinues Breakdown'!F6 -> 0 | G9: ='New Retinues Breakdown'!G6 -> 100 | H9: ='New Retinues Breakdown'!H6 -> 0 | I9: ='New Retinues Breakdown'!I6 -> 0 | J9: ='New Retinues Breakdown'!J6 -> 100 | ... R9: ='New Retinues Breakdown'!R6 -> 100 | S9: =SUM(C9:R9) -> 500
A10: Dreghold | B10: Cost | C10: ='New Retinues Breakdown'!C11 -> 0 | D10: ='New Retinues Breakdown'!D11 -> 0 | E10: ='New Retinues Breakdown'!E11 -> 800 | F10: ='New Retinues Breakdown'!F11 -> 800 | G10: ='New Retinues Breakdown'!G11 -> 0 | H10: ='New Retinues Breakdown'!H11 -> 0 | I10: ='New Retinues Breakdown'!I11 -> 0 | J10: ='New Retinues Breakdown'!J11 -> 200 | ... S10: ='New Retinues Breakdown'!S11 -> 2100
A11: Madinglia | B11: Cost | C11: ='New Retinues Breakdown'!C16 -> 100 | D11: ='New Retinues Breakdown'!D16 -> 0 | E11: ='New Retinues Breakdown'!E16 -> 0 | F11: ='New Retinues Breakdown'!F16 -> 0 | G11: ='New Retinues Breakdown'!G16 -> 0 | H11: ='New Retinues Breakdown'!H16 -> 50 | I11: ='New Retinues Breakdown'!I16 -> 0 | J11: ='New Retinues Breakdown'!J16 -> 0 | ... R11: ='New Retinues Breakdown'!R16 -> 0 | S11: =SUM(C11:R11) -> 150
A12: Ralim | B12: Cost | C12: ='New Retinues Breakdown'!C21 -> 0 | D12: ='New Retinues Breakdown'!D21 -> 0 | E12: ='New Retinues Breakdown'!E21 -> 0 | F12: ='New Retinues Breakdown'!F21 -> 0 | G12: ='New Retinues Breakdown'!G21 -> 0 | H12: ='New Retinues Breakdown'!H21 -> 0 | I12: ='New Retinues Breakdown'!I21 -> 0 | J12: ='New Retinues Breakdown'!J21 -> 0 | ... R12: ='New Retinues Breakdown'!R21 -> 0 | S12: =SUM(C12:R12) -> 0
A13: Sirong | B13: Cost | C13: ='New Retinues Breakdown'!C26 -> 50 | D13: ='New Retinues Breakdown'!D26 -> 0 | E13: ='New Retinues Breakdown'!E26 -> 0 | F13: ='New Retinues Breakdown'!F26 -> 0 | G13: ='New Retinues Breakdown'!G26 -> 0 | H13: ='New Retinues Breakdown'!H26 -> 50 | I13: ='New Retinues Breakdown'!I26 -> 0 | J13: ='New Retinues Breakdown'!J26 -> 0 | ... R13: ='New Retinues Breakdown'!R26 -> 0 | S13: =SUM(C13:R13) -> 100
A14: Swanhall | B14: Cost | C14: ='New Retinues Breakdown'!C31 -> 0 | D14: ='New Retinues Breakdown'!D31 -> 0 | E14: ='New Retinues Breakdown'!E31 -> 0 | F14: ='New Retinues Breakdown'!F31 -> 0 | G14: ='New Retinues Breakdown'!G31 -> 0 | H14: ='New Retinues Breakdown'!H31 -> 0 | I14: ='New Retinues Breakdown'!I31 -> 0 | J14: ='New Retinues Breakdown'!J31 -> 0 | ... R14: ='New Retinues Breakdown'!R31 -> 0 | S14: =SUM(C14:R14) -> 0

Sheet Provincial Economics
B1: Gold Income | C1: Gold Spending | D1: Total Untaxed Income | E1: Total Tax Income | F1: Desmene Tax Income | G1: Vassal Tax Income | H1: Diplomatic Income | I1: Liege Tax Spending | J1: Total Military Spending | K1: Retinue Spending | L1: Knights Wages | M1: Levy Spending | N1: Diplomatic Spending
A2: Crownlands | B2: =D2*(1-'Provincial Secret Sheet'!B1) -> 13984.831 | C2: =J2+N2 -> 55073.557 | D2: =E2+H2 -> 13984.831 | E2: =SUM(F2:G2) -> 12184.831 | F2: ='Ducal Economics'!E20 -> 3798.4257 | G2: =SUM('Ducal Economics'!I16:I20)+(SUM(D3:D7)-SUM(B3:B7)) -> 8386.4054 | H2: 1800 | I2: =D2-B2 -> 0 | J2: =SUM(K2:M2) -> 55073.557 | K2: ='New Retinues Summary'!S9 -> 500 | L2: ='Knights Breakdown'!D2 -> 2427.8095 | M2: ='New Provinces Summary'!I2*2+'Provincial Secret Sheet'!E1*0.008 -> 52145.747 | N2: 0
A3: Dreghold | B3: =D3*(1-'Provincial Secret Sheet'!B2) -> 21579.155 | C3: =J3+N3 -> 59451.2 | D3: =E3+H3 -> 21579.155 | E3: =SUM(F3:H3) -> 15279.155 | F3: ='Ducal Economics'!E4 -> 3876.8602 | G3: =SUM('Ducal Economics'!I4,'Ducal Economics'!I21:I26) -> 5102.2947 | H3: 6300 | I3: =D3-B3 -> 0 | J3: =SUM(K3:M3) -> 59451.2 | K3: ='New Retinues Summary'!S10 -> 2100 | L3: ='Knights Breakdown'!D3 -> 3833.593 | M3: ='New Provinces Summary'!I3*2+'Provincial Secret Sheet'!E2*0.008 -> 53517.607 | N3: 0
A4: Madinglia | B4: =D4*(1-'Provincial Secret Sheet'!B3) -> 1458.3964 | C4: =J4+N4 -> 779.63806 | D4: =E4+H4 -> 1944.5286 | E4: =SUM(F4:H4) -> 1944.5286 | F4: ='Ducal Economics'!E3 -> 789.7235 | G4: =SUM('Ducal Economics'!I41:I45,'Ducal Economics'!I3) -> 1154.8051 | H4: 0 | I4: =D4-B4 -> 486.13215 | J4: =SUM(K4:M4) -> 779.63806 | K4: ='New Retinues Summary'!S11 -> 150 | L4: ='Knights Breakdown'!D4 -> 479.75578 | M4: ='New Provinces Summary'!I4*2+'Provincial Secret Sheet'!E3*0.008 -> 149.88228 | N4: 0
A5: Ralim | B5: =D5*(1-'Provincial Secret Sheet'!B4) -> 5025.3155 | C5: =J5+N5 -> 33662.108 | D5: =E5+H5 -> 6700.4206 | E5: =SUM(F5:H5) -> 6700.4206 | F5: ='Ducal Economics'!E6 -> 3600.0564 | G5: =SUM('Ducal Economics'!I6,'Ducal Economics'!I13:I15) -> 3100.3642 | H5: 0 | I5: =D5-B5 -> 1675.1052 | J5: =SUM(K5:M5) -> 33662.108 | K5: ='New Retinues Summary'!S12 -> 0 | L5: ='Knights Breakdown'!D5 -> 1691.5878 | M5: ='New Provinces Summary'!I5*2+'Provincial Secret Sheet'!E4*0.008 -> 31970.52 | N5: 0
A6: Sirong | B6: =D6*(1-'Provincial Secret Sheet'!B5) -> 8369.3069 | C6: =J6+N6 -> 88006.995 | D6: =E6+H6 -> 11159.076 | E6: =SUM(F6:H6) -> 11159.076 | F6: ='Ducal Economics'!E7 -> 4717.9266 | G6: =SUM('Ducal Economics'!I5,'Ducal Economics'!I7:I12) -> 6441.1492 | H6: 0 | I6: =D6-B6 -> 2789.769 | J6: =SUM(K6:M6) -> 88006.995 | K6: ='New Retinues Summary'!S13 -> 100 | L6: ='Knights Breakdown'!D6 -> 5267.9717 | M6: ='New Provinces Summary'!I6*2+'Provincial Secret Sheet'!E5*0.008 -> 82639.023 | N6: 0
A7: Swanhall | B7: =D7*(1-'Provincial Secret Sheet'!B6) -> 13826.412 | C7: =J7+N7 -> 51372.049 | D7: =E7+H7 -> 13826.412 | E7: =SUM(F7:H7) -> 12160.412 | F7: ='Ducal Economics'!E2 -> 1831.0121 | G7: =SUM('Ducal Economics'!I2,'Ducal Economics'!I27:I40) -> 8663.3999 | H7: 1666 | I7: =D7-B7 -> 0 | J7: =SUM(K7:M7) -> 51372.049 | K7: ='New Retinues Summary'!S14 -> 0 | L7: ='Knights Breakdown'!D7 -> 7004.8305 | M7: ='New Provinces Summary'!I7*2+'Provincial Secret Sheet'!E6*0.008 -> 44367.219 | N7: 0
A8: Total | B8: =SUM(B2:B7) -> 64243.417 | C8: =SUM(C2:C7) -> 288345.55 | D8: =SUM(D2:D7) -> 69194.423 | E8: =SUM(E2:E7) -> 59428.423 | F8: =SUM(F2:F7) -> 18614.005 | G8: =SUM(G2:G7) -> 32848.419 | H8: =SUM(H2:H7) -> 9766 | I8: =SUM(I2:I7) -> 4951.0063 | ... N8: =SUM(N2:N7) -> 0
A9: Average | B9: =AVERAGE(B2:B7) -> 10707.236 | C9: =AVERAGE(C2:C7) -> 48057.591 | D9: =AVERAGE(D2:D7) -> 11532.404 | E9: =AVERAGE(E2:E7) -> 9904.7372 | F9: =AVERAGE(F2:F7) -> 3102.3341 | G9: =AVERAGE(G2:G7) -> 5474.7364 | H9: =AVERAGE(H2:H7) -> 1627.6667 | I9: =AVERAGE(I2:I7) -> 825.16771 | ... N9: =AVERAGE(N2:N7) -> 0

Sheet New Retinues Breakdown
C1: Infantrymen | H1: Archers | M1: Cavalry
C2: Tier I | D2: Tier II | E2: Tier III | F2: Tier IV | G2: Tier V | H2: Tier I | I2: Tier II | J2: Tier III | K2: Tier IV | L2: Tier V | M2: Tier I | N2: Tier II | O2: Tier III | P2: Tier IV | Q2: Tier V | R2: Horse Archers | S2: Total
A3: The Crown | B3: Current Count | C3: =IFERROR(__xludf.DUMMYFUNCTION("TO_TEXT(C7*100*C4)&TO_TEXT(""/"")&TO_TEXT(C4*100)"),"0/0") -> 0/0 | D3: =IFERROR(__xludf.DUMMYFUNCTION("TO_TEXT(D7*100*D4)&TO_TEXT(""/"")&TO_TEXT(D4*100)"),"0/0") -> 0/0 | E3: =IFERROR(__xludf.DUMMYFUNCTION("TO_TEXT(E7*100*E4)&TO_TEXT(""/"")&TO_TEXT(E4*100)"),"100/100") -> 100/100 | F3: =IFERROR(__xludf.DUMMYFUNCTION("TO_TEXT(F7*100*F4)&TO_TEXT(""/"")&TO_TEXT(F4*100)"),"0/0") -> 0/0 | G3: =IFERROR(__xludf.DUMMYFUNCTION("TO_TEXT(G7*100*G4)&TO_TEXT(""/"")&TO_TEXT(G4*100)"),"100/100") -> 100/100 | H3: =IFERROR(__xludf.DUMMYFUNCTION("TO_TEXT(H7*100*H4)&TO_TEXT(""/"")&TO_TEXT(H4*100)"),"0/0") -> 0/0 | I3: =IFERROR(__xludf.DUMMYFUNCTION("TO_TEXT(I7*100*I4)&TO_TEXT(""/"")&TO_TEXT(I4*100)"),"0/0") -> 0/0 | J3: =IFERROR(__xludf.DUMMYFUNCTION("TO_TEXT(J7*100*J4)&TO_TEXT(""/"")&TO_TEXT(J4*100)"),"100/100") -> 100/100 | K3: =IFERROR(__xludf.DUMMYFUNCTION("TO_TEXT(K7*100*K4)&TO_TEXT(""/"")&TO_TEXT(K4*100)"),"0/0") -> 0/0 | L3: =IFERROR(__xludf.DUMMYFUNCTION("TO_TEXT(L7*100*L4)&TO_TEXT(""/"")&TO_TEXT(L4*100)"),"0/0") -> 0/0 | M3: =IFERROR(__xludf.DUMMYFUNCTION("TO_TEXT((M7/2)*100*M4)&TO_TEXT(""/"")&TO_TEXT(M4*50)"),"0/0") -> 0/0 | N3: =IFERROR(__xludf.DUMMYFUNCTION("TO_TEXT((N7/2)*100*N4)&TO_TEXT(""/"")&TO_TEXT(N4*50)"),"0/0") -> 0/0 | O3: =IFERROR(__xludf.DUMMYFUNCTION("TO_TEXT((O7/2)*100*O4)&TO_TEXT(""/"")&TO_TEXT(O4*50)"),"0/0") -> 0/0 | P3: =IFERROR(__xludf.DUMMYFUNCTION("TO_TEXT((P7/2)*100*P4)&TO_TEXT(""/"")&TO_TEXT(P4*50)"),"0/0") -> 0/0 | Q3: =IFERROR(__xludf.DUMMYFUNCTION("TO_TEXT((Q7/2)*100*Q4)&TO_TEXT(""/"")&TO_TEXT(Q4*50)"),"50/50") -> 50/50 | R3: =IFERROR(__xludf.DUMMYFUNCTION("TO_TEXT((R7/2)*100*R4)&TO_TEXT(""/"")&TO_TEXT(R4*50)"),"50/50") -> 50/50 | S3: =(SUM(M4:R4)*50)+SUM(C4:L4)*100 -> 400
B4: Regiments | C4: 0 | D4: 0 | E4: 1 | F4: 0 | G4: 1 | H4: 0 | I4: 0 | J4: 1 | K4: 0 | L4: 0 | M4: 0 | N4: 0 | O4: 0 | P4: 0 | Q4: 1 | R4: 1
B5: Reinforcing | C5: TRUE | D5: TRUE | E5: TRUE | F5: TRUE | G5: TRUE | H5: TRUE | I5: TRUE | J5: TRUE | K5: TRUE | L5: TRUE | M5: TRUE | N5: TRUE | O5: TRUE | P5: TRUE | Q5: TRUE | R5: TRUE
B6: Cost | C6: =((C7*(C4*C$35)*C$33)+IF(C5,(((1-C7)*C$35)*C$34*C4))) -> 0 | D6: =((D7*(D4*D$35)*D$33)+IF(D5,(((1-D7)*D$35)*D$34*D4))) -> 0 | E6: =((E7*(E4*E$35)*E$33)+IF(E5,(((1-E7)*E$35)*E$34*E4))) -> 100 | F6: =((F7*(F4*F$35)*F$33)+IF(F5,(((1-F7)*F$35)*F$34*F4))) -> 0 | G6: =((G7*(G4*G$35)*G$33)+IF(G5,(((1-G7)*G$35)*G$34*G4))) -> 100 | H6: =((H7*(H4*H$35)*H$33)+IF(H5,(((1-H7)*H$35)*H$34*H4))) -> 0 | I6: =((I7*(I4*I$35)*I$33)+IF(I5,(((1-I7)*I$35)*I$34*I4))) -> 0 | J6: =((J7*(J4*J$35)*J$33)+IF(J5,(((1-J7)*J$35)*J$34*J4))) -> 100 | ... R6: =((R7*(R4*R$35)*R$33)+IF(R5,(((1-R7)*R$35)*R$34*R4))) -> 100 | S6: =SUM(B6:R6) -> 500
B7: Cohesion | C7: 0 | D7: 0 | E7: 1 | F7: 0 | G7: 1 | H7: 0 | I7: 0 | J7: 1 | K7: 0 | L7: 0 | M7: 0 | N7: 0 | O7: 0 | P7: 0 | Q7: 1 | R7: 1
A8: Dreghold | B8: Current Count | C8: =IFERROR(__xludf.DUMMYFUNCTION("TO_TEXT(C12*100*C9)&TO_TEXT(""/"")&TO_TEXT(C9*100)"),"0/0") -> 0/0 | D8: =IFERROR(__xludf.DUMMYFUNCTION("TO_TEXT(D12*100*D9)&TO_TEXT(""/"")&TO_TEXT(D9*100)"),"0/0") -> 0/0 | E8: =IFERROR(__xludf.DUMMYFUNCTION("TO_TEXT(E12*100*E9)&TO_TEXT(""/"")&TO_TEXT(E9*100)"),"800/800") -> 800/800 | F8: =IFERROR(__xludf.DUMMYFUNCTION("TO_TEXT(F12*100*F9)&TO_TEXT(""/"")&TO_TEXT(F9*100)"),"800/800") -> 800/800 | G8: =IFERROR(__xludf.DUMMYFUNCTION("TO_TEXT(G12*100*G9)&TO_TEXT(""/"")&TO_TEXT(G9*100)"),"0/0") -> 0/0 | H8: =IFERROR(__xludf.DUMMYFUNCTION("TO_TEXT(H12*100*H9)&TO_TEXT(""/"")&TO_TEXT(H9*100)"),"0/0") -> 0/0 | I8: =IFERROR(__xludf.DUMMYFUNCTION("TO_TEXT(I12*100*I9)&TO_TEXT(""/"")&TO_TEXT(I9*100)"),"0/0") -> 0/0 | J8: =IFERROR(__xludf.DUMMYFUNCTION("TO_TEXT(J12*100*J9)&TO_TEXT(""/"")&TO_TEXT(J9*100)"),"200/200") -> 200/200 | K8: =IFERROR(__xludf.DUMMYFUNCTION("TO_TEXT(K12*100*K9)&TO_TEXT(""/"")&TO_TEXT(K9*100)"),"100/100") -> 100/100 | L8: =IFERROR(__xludf.DUMMYFUNCTION("TO_TEXT(L12*100*L9)&TO_TEXT(""/"")&TO_TEXT(L9*100)"),"0/0") -> 0/0 | M8: =IFERROR(__xludf.DUMMYFUNCTION("TO_TEXT((M12/2)*100*M9)&TO_TEXT(""/"")&TO_TEXT(M9*50)"),"0/0") -> 0/0 | N8: =IFERROR(__xludf.DUMMYFUNCTION("TO_TEXT((N12/2)*100*N9)&TO_TEXT(""/"")&TO_TEXT(N9*50)"),"0/0") -> 0/0 | O8: =IFERROR(__xludf.DUMMYFUNCTION("TO_TEXT((O12/2)*100*O9)&TO_TEXT(""/"")&TO_TEXT(O9*50)"),"50/50") -> 50/50 | P8: =IFERROR(__xludf.DUMMYFUNCTION("TO_TEXT((P12/2)*100*P9)&TO_TEXT(""/"")&TO_TEXT(P9*50)"),"50/50") -> 50/50 | Q8: =IFERROR(__xludf.DUMMYFUNCTION("TO_TEXT((Q12/2)*100*Q9)&TO_TEXT(""/"")&TO_TEXT(Q9*50)"),"0/0") -> 0/0 | R8: =IFERROR(__xludf.DUMMYFUNCTION("TO_TEXT((R12/2)*100*R9)&TO_TEXT(""/"")&TO_TEXT(R9*50)"),"0/0") -> 0/0 | S8: =(SUM(M9:R9)*50)+SUM(C9:L9)*100 -> 2000
B9: Regiments | C9: 0 | D9: 0 | E9: 8 | F9: 8 | G9: 0 | H9: 0 | I9: 0 | J9: 2 | K9: 1 | L9: 0 | M9: 0 | N9: 0 | O9: 1 | P9: 1 | Q9: 0 | R9: 0
B10: Reinforcing | C10: TRUE | D10: TRUE | E10: TRUE | F10: TRUE | G10: TRUE | H10: TRUE | I10: TRUE | J10: TRUE | K10: TRUE | L10: TRUE | M10: TRUE | N10: TRUE | O10: TRUE | P10: TRUE | Q10: TRUE | R10: TRUE
B11: Cost | C11: =((C12*(C9*C$35)*C$33)+IF(C10,(((1-C12)*C$35)*C$34*C9))) -> 0 | D11: =((D12*(D9*D$35)*D$33)+IF(D10,(((1-D12)*D$35)*D$34*D9))) -> 0 | E11: =((E12*(E9*E$35)*E$33)+IF(E10,(((1-E12)*E$35)*E$34*E9))) -> 800 | F11: =((F12*(F9*F$35)*F$33)+IF(F10,(((1-F12)*F$35)*F$34*F9))) -> 800 | G11: =((G12*(G9*G$35)*G$33)+IF(G10,(((1-G12)*G$35)*G$34*G9))) -> 0 | H11: =((H12*(H9*H$35)*H$33)+IF(H10,(((1-H12)*H$35)*H$34*H9))) -> 0 | I11: =((I12*(I9*I$35)*I$33)+IF(I10,(((1-I12)*I$35)*I$34*I9))) -> 0 | J11: =((J12*(J9*J$35)*J$33)+IF(J10,(((1-J12)*J$35)*J$34*J9))) -> 200 | ... R11: =((R12*(R9*R$35)*R$33)+IF(R10,(((1-R12)*R$35)*R$34*R9))) -> 0 | S11: =SUM(B11:R11) -> 2100
B12: Cohesion | C12: 0 | D12: 0 | E12: 1 | F12: 1 | G12: 0 | H12: 0 | I12: 0 | J12: 1 | K12: 1 | L12: 0 | M12: 0 | N12: 0 | O12: 1 | P12: 1 | Q12: 0 | R12: 0
A13: Madinglia | B13: Current Count | C13: =IFERROR(__xludf.DUMMYFUNCTION("TO_TEXT(C17*100*C14)&TO_TEXT(""/"")&TO_TEXT(C14*100)"),"200/200") -> 200/200 | D13: =IFERROR(__xludf.DUMMYFUNCTION("TO_TEXT(D17*100*D14)&TO_TEXT(""/"")&TO_TEXT(D14*100)"),"0/0") -> 0/0 | E13: =IFERROR(__xludf.DUMMYFUNCTION("TO_TEXT(E17*100*E14)&TO_TEXT(""/"")&TO_TEXT(E14*100)"),"0/0") -> 0/0 | F13: =IFERROR(__xludf.DUMMYFUNCTION("TO_TEXT(F17*100*F14)&TO_TEXT(""/"")&TO_TEXT(F14*100)"),"0/0") -> 0/0 | G13: =IFERROR(__xludf.DUMMYFUNCTION("TO_TEXT(G17*100*G14)&TO_TEXT(""/"")&TO_TEXT(G14*100)"),"0/0") -> 0/0 | H13: =IFERROR(__xludf.DUMMYFUNCTION("TO_TEXT(H17*100*H14)&TO_TEXT(""/"")&TO_TEXT(H14*100)"),"100/100") -> 100/100 | I13: =IFERROR(__xludf.DUMMYFUNCTION("TO_TEXT(I17*100*I14)&TO_TEXT(""/"")&TO_TEXT(I14*100)"),"0/0") -> 0/0 | J13: =IFERROR(__xludf.DUMMYFUNCTION("TO_TEXT(J17*100*J14)&TO_TEXT(""/"")&TO_TEXT(J14*100)"),"0/0") -> 0/0 | K13: =IFERROR(__xludf.DUMMYFUNCTION("TO_TEXT(K17*100*K14)&TO_TEXT(""/"")&TO_TEXT(K14*100)"),"0/0") -> 0/0 | L13: =IFERROR(__xludf.DUMMYFUNCTION("TO_TEXT(L17*100*L14)&TO_TEXT(""/"")&TO_TEXT(L14*100)"),"0/0") -> 0/0 | M13: =IFERROR(__xludf.DUMMYFUNCTION("TO_TEXT((M17/2)*100*M14)&TO_TEXT(""/"")&TO_TEXT(M14*50)"),"0/0") -> 0/0 | N13: =IFERROR(__xludf.DUMMYFUNCTION("TO_TEXT((N17/2)*100*N14)&TO_TEXT(""/"")&TO_TEXT(N14*50)"),"0/0") -> 0/0 | O13: =IFERROR(__xludf.DUMMYFUNCTION("TO_TEXT((O17/2)*100*O14)&TO_TEXT(""/"")&TO_TEXT(O14*50)"),"0/0") -> 0/0 | P13: =IFERROR(__xludf.DUMMYFUNCTION("TO_TEXT((P17/2)*100*P14)&TO_TEXT(""/"")&TO_TEXT(P14*50)"),"0/0") -> 0/0 | Q13: =IFERROR(__xludf.DUMMYFUNCTION("TO_TEXT((Q17/2)*100*Q14)&TO_TEXT(""/"")&TO_TEXT(Q14*50)"),"0/0") -> 0/0 | R13: =IFERROR(__xludf.DUMMYFUNCTION("TO_TEXT((R17/2)*100*R14)&TO_TEXT(""/"")&TO_TEXT(R14*50)"),"0/0") -> 0/0 | S13: =(SUM(M14:R14)*50)+SUM(C14:L14)*100 -> 300
B14: Regiments | C14: 2 | D14: 0 | E14: 0 | F14: 0 | G14: 0 | H14: 1 | I14: 0 | J14: 0 | K14: 0 | L14: 0 | M14: 0 | N14: 0 | O14: 0 | P14: 0 | Q14: 0 | R14: 0
B15: Reinforcing | C15: TRUE | D15: TRUE | E15: TRUE | F15: TRUE | G15: TRUE | H15: TRUE | I15: TRUE | J15: TRUE | K15: TRUE | L15: TRUE | M15: TRUE | N15: TRUE | O15: TRUE | P15: TRUE | Q15: TRUE | R15: TRUE
B16: Cost | C16: =((C17*(C14*C$35)*C$33)+IF(C15,(((1-C17)*C$35)*C$34*C14))) -> 100 | D16: =((D17*(D14*D$35)*D$33)+IF(D15,(((1-D17)*D$35)*D$34*D14))) -> 0 | E16: =((E17*(E14*E$35)*E$33)+IF(E15,(((1-E17)*E$35)*E$34*E14))) -> 0 | F16: =((F17*(F14*F$35)*F$33)+IF(F15,(((1-F17)*F$35)*F$34*F14))) -> 0 | G16: =((G17*(G14*G$35)*G$33)+IF(G15,(((1-G17)*G$35)*G$34*G14))) -> 0 | H16: =((H17*(H14*H$35)*H$33)+IF(H15,(((1-H17)*H$35)*H$34*H14))) -> 50 | I16: =((I17*(I14*I$35)*I$33)+IF(I15,(((1-I17)*I$35)*I$34*I14))) -> 0 | J16: =((J17*(J14*J$35)*J$33)+IF(J15,(((1-J17)*J$35)*J$34*J14))) -> 0 | ... R16: =((R17*(R14*R$35)*R$33)+IF(R15,(((1-R17)*R$35)*R$34*R14))) -> 0 | S16: =SUM(B16:R16) -> 150
B17: Cohesion | C17: 1 | D17: 0 | E17: 0 | F17: 0 | G17: 0 | H17: 1 | I17: 0 | J17: 0 | K17: 0 | L17: 0 | M17: 0 | N17: 0 | O17: 0 | P17: 0 | Q17: 0 | R17: 0
A18: Ralim | B18: Current Count | C18: =IFERROR(__xludf.DUMMYFUNCTION("TO_TEXT(C22*100*C19)&TO_TEXT(""/"")&TO_TEXT(C19*100)"),"0/0") -> 0/0 | D18: =IFERROR(__xludf.DUMMYFUNCTION("TO_TEXT(D22*100*D19)&TO_TEXT(""/"")&TO_TEXT(D19*100)"),"0/0") -> 0/0 | E18: =IFERROR(__xludf.DUMMYFUNCTION("TO_TEXT(E22*100*E19)&TO_TEXT(""/"")&TO_TEXT(E19*100)"),"0/0") -> 0/0 | F18: =IFERROR(__xludf.DUMMYFUNCTION("TO_TEXT(F22*100*F19)&TO_TEXT(""/"")&TO_TEXT(F19*100)"),"0/0") -> 0/0 | G18: =IFERROR(__xludf.DUMMYFUNCTION("TO_TEXT(G22*100*G19)&TO_TEXT(""/"")&TO_TEXT(G19*100)"),"0/0") -> 0/0 | H18: =IFERROR(__xludf.DUMMYFUNCTION("TO_TEXT(H22*100*H19)&TO_TEXT(""/"")&TO_TEXT(H19*100)"),"0/0") -> 0/0 | I18: =IFERROR(__xludf.DUMMYFUNCTION("TO_TEXT(I22*100*I19)&TO_TEXT(""/"")&TO_TEXT(I19*100)"),"0/0") -> 0/0 | J18: =IFERROR(__xludf.DUMMYFUNCTION("TO_TEXT(J22*100*J19)&TO_TEXT(""/"")&TO_TEXT(J19*100)"),"0/0") -> 0/0 | K18: =IFERROR(__xludf.DUMMYFUNCTION("TO_TEXT(K22*100*K19)&TO_TEXT(""/"")&TO_TEXT(K19*100)"),"0/0") -> 0/0 | L18: =IFERROR(__xludf.DUMMYFUNCTION("TO_TEXT(L22*100*L19)&TO_TEXT(""/"")&TO_TEXT(L19*100)"),"0/0") -> 0/0 | M18: =IFERROR(__xludf.DUMMYFUNCTION("TO_TEXT((M22/2)*100*M19)&TO_TEXT(""/"")&TO_TEXT(M19*50)"),"0/0") -> 0/0 | N18: =IFERROR(__xludf.DUMMYFUNCTION("TO_TEXT((N22/2)*100*N19)&TO_TEXT(""/"")&TO_TEXT(N19*50)"),"0/0") -> 0/0 | O18: =IFERROR(__xludf.DUMMYFUNCTION("TO_TEXT((O22/2)*100*O19)&TO_TEXT(""/"")&TO_TEXT(O19*50)"),"0/0") -> 0/0 | P18: =IFERROR(__xludf.DUMMYFUNCTION("TO_TEXT((P22/2)*100*P19)&TO_TEXT(""/"")&TO_TEXT(P19*50)"),"0/0") -> 0/0 | Q18: =IFERROR(__xludf.DUMMYFUNCTION("TO_TEXT((Q22/2)*100*Q19)&TO_TEXT(""/"")&TO_TEXT(Q19*50)"),"0/0") -> 0/0 | R18: =IFERROR(__xludf.DUMMYFUNCTION("TO_TEXT((R22/2)*100*R19)&TO_TEXT(""/"")&TO_TEXT(R19*50)"),"0/0") -> 0/0 | S18: =(SUM(M19:R19)*50)+SUM(C19:L19)*100 -> 0
B19: Regiments | C19: 0 | D19: 0 | E19: 0 | F19: 0 | G19: 0 | H19: 0 | I19: 0 | J19: 0 | K19: 0 | L19: 0 | M19: 0 | N19: 0 | O19: 0 | P19: 0 | Q19: 0 | R19: 0
B20: Reinforcing | C20: TRUE | D20: TRUE | E20: TRUE | F20: TRUE | G20: TRUE | H20: TRUE | I20: TRUE | J20: TRUE | K20: TRUE | L20: TRUE | M20: TRUE | N20: TRUE | O20: TRUE | P20: TRUE | Q20: TRUE | R20: TRUE
B21: Cost | C21: =((C22*(C19*C$35)*C$33)+IF(C20,(((1-C22)*C$35)*C$34*C19))) -> 0 | D21: =((D22*(D19*D$35)*D$33)+IF(D20,(((1-D22)*D$35)*D$34*D19))) -> 0 | E21: =((E22*(E19*E$35)*E$33)+IF(E20,(((1-E22)*E$35)*E$34*E19))) -> 0 | F21: =((F22*(F19*F$35)*F$33)+IF(F20,(((1-F22)*F$35)*F$34*F19))) -> 0 | G21: =((G22*(G19*G$35)*G$33)+IF(G20,(((1-G22)*G$35)*G$34*G19))) -> 0 | H21: =((H22*(H19*H$35)*H$33)+IF(H20,(((1-H22)*H$35)*H$34*H19))) -> 0 | I21: =((I22*(I19*I$35)*I$33)+IF(I20,(((1-I22)*I$35)*I$34*I19))) -> 0 | J21: =((J22*(J19*J$35)*J$33)+IF(J20,(((1-J22)*J$35)*J$34*J19))) -> 0 | ... R21: =((R22*(R19*R$35)*R$33)+IF(R20,(((1-R22)*R$35)*R$34*R19))) -> 0 | S21: =SUM(B21:R21) -> 0
B22: Cohesion | C22: 0 | D22: 0 | E22: 0 | F22: 0 | G22: 0 | H22: 0 | I22: 0 | J22: 0 | K22: 0 | L22: 0 | M22: 0 | N22: 0 | O22: 0 | P22: 0 | Q22: 0 | R22: 0
A23: Sirong | B23: Current Count | C23: =IFERROR(__xludf.DUMMYFUNCTION("TO_TEXT(C27*100*C24)&TO_TEXT(""/"")&TO_TEXT(C24*100)"),"100/100") -> 100/100 | D23: =IFERROR(__xludf.DUMMYFUNCTION("TO_TEXT(D27*100*D24)&TO_TEXT(""/"")&TO_TEXT(D24*100)"),"0/0") -> 0/0 | E23: =IFERROR(__xludf.DUMMYFUNCTION("TO_TEXT(E27*100*E24)&TO_TEXT(""/"")&TO_TEXT(E24*100)"),"0/0") -> 0/0 | F23: =IFERROR(__xludf.DUMMYFUNCTION("TO_TEXT(F27*100*F24)&TO_TEXT(""/"")&TO_TEXT(F24*100)"),"0/0") -> 0/0 | G23: =IFERROR(__xludf.DUMMYFUNCTION("TO_TEXT(G27*100*G24)&TO_TEXT(""/"")&TO_TEXT(G24*100)"),"0/0") -> 0/0 | H23: =IFERROR(__xludf.DUMMYFUNCTION("TO_TEXT(H27*100*H24)&TO_TEXT(""/"")&TO_TEXT(H24*100)"),"100/100") -> 100/100 | I23: =IFERROR(__xludf.DUMMYFUNCTION("TO_TEXT(I27*100*I24)&TO_TEXT(""/"")&TO_TEXT(I24*100)"),"0/0") -> 0/0 | J23: =IFERROR(__xludf.DUMMYFUNCTION("TO_TEXT(J27*100*J24)&TO_TEXT(""/"")&TO_TEXT(J24*100)"),"0/0") -> 0/0 | K23: =IFERROR(__xludf.DUMMYFUNCTION("TO_TEXT(K27*100*K24)&TO_TEXT(""/"")&TO_TEXT(K24*100)"),"0/0") -> 0/0 | L23: =IFERROR(__xludf.DUMMYFUNCTION("TO_TEXT(L27*100*L24)&TO_TEXT(""/"")&TO_TEXT(L24*100)"),"0/0") -> 0/0 | M23: =IFERROR(__xludf.DUMMYFUNCTION("TO_TEXT((M27/2)*100*M24)&TO_TEXT(""/"")&TO_TEXT(M24*50)"),"0/0") -> 0/0 | N23: =IFERROR(__xludf.DUMMYFUNCTION("TO_TEXT((N27/2)*100*N24)&TO_TEXT(""/"")&TO_TEXT(N24*50)"),"0/0") -> 0/0 | O23: =IFERROR(__xludf.DUMMYFUNCTION("TO_TEXT((O27/2)*100*O24)&TO_TEXT(""/"")&TO_TEXT(O24*50)"),"0/0") -> 0/0 | P23: =IFERROR(__xludf.DUMMYFUNCTION("TO_TEXT((P27/2)*100*P24)&TO_TEXT(""/"")&TO_TEXT(P24*50)"),"0/0") -> 0/0 | Q23: =IFERROR(__xludf.DUMMYFUNCTION("TO_TEXT((Q27/2)*100*Q24)&TO_TEXT(""/"")&TO_TEXT(Q24*50)"),"0/0") -> 0/0 | R23: =IFERROR(__xludf.DUMMYFUNCTION("TO_TEXT((R27/2)*100*R24)&TO_TEXT(""/"")&TO_TEXT(R24*50)"),"0/0") -> 0/0 | S23: =(SUM(M24:R24)*50)+SUM(C24:L24)*100 -> 200
B24: Regiments | C24: 1 | D24: 0 | E24: 0 | F24: 0 | G24: 0 | H24: 1 | I24: 0 | J24: 0 | K24: 0 | L24: 0 | M24: 0 | N24: 0 | O24: 0 | P24: 0 | Q24: 0 | R24: 0
B25: Reinforcing | C25: TRUE | D25: TRUE | E25: TRUE | F25: TRUE | G25: TRUE | H25: TRUE | I25: TRUE | J25: TRUE | K25: TRUE | L25: TRUE | M25: TRUE | N25: TRUE | O25: TRUE | P25: TRUE | Q25: TRUE | R25: TRUE
B26: Cost | C26: =((C27*(C24*C$35)*C$33)+IF(C25,(((1-C27)*C$35)*C$34*C24))) -> 50 | D26: =((D27*(D24*D$35)*D$33)+IF(D25,(((1-D27)*D$35)*D$34*D24))) -> 0 | E26: =((E27*(E24*E$35)*E$33)+IF(E25,(((1-E27)*E$35)*E$34*E24))) -> 0 | F26: =((F27*(F24*F$35)*F$33)+IF(F25,(((1-F27)*F$35)*F$34*F24))) -> 0 | G26: =((G27*(G24*G$35)*G$33)+IF(G25,(((1-G27)*G$35)*G$34*G24))) -> 0 | H26: =((H27*(H24*H$35)*H$33)+IF(H25,(((1-H27)*H$35)*H$34*H24))) -> 50 | I26: =((I27*(I24*I$35)*I$33)+IF(I25,(((1-I27)*I$35)*I$34*I24))) -> 0 | J26: =((J27*(J24*J$35)*J$33)+IF(J25,(((1-J27)*J$35)*J$34*J24))) -> 0 | ... R26: =((R27*(R24*R$35)*R$33)+IF(R25,(((1-R27)*R$35)*R$34*R24))) -> 0 | S26: =SUM(B26:R26) -> 100
B27: Cohesion | C27: 1 | D27: 0 | E27: 0 | F27: 0 | G27: 0 | H27: 1 | I27: 0 | J27: 0 | K27: 0 | L27: 0 | M27: 0 | N27: 0 | O27: 0 | P27: 0 | Q27: 0 | R27: 0
A28: Swanhall | B28: Current Count | C28: =IFERROR(__xludf.DUMMYFUNCTION("TO_TEXT(C32*100*C29)&TO_TEXT(""/"")&TO_TEXT(C29*100)"),"0/0") -> 0/0 | D28: =IFERROR(__xludf.DUMMYFUNCTION("TO_TEXT(D32*100*D29)&TO_TEXT(""/"")&TO_TEXT(D29*100)"),"0/0") -> 0/0 | E28: =IFERROR(__xludf.DUMMYFUNCTION("TO_TEXT(E32*100*E29)&TO_TEXT(""/"")&TO_TEXT(E29*100)"),"0/0") -> 0/0 | F28: =IFERROR(__xludf.DUMMYFUNCTION("TO_TEXT(F32*100*F29)&TO_TEXT(""/"")&TO_TEXT(F29*100)"),"0/0") -> 0/0 | G28: =IFERROR(__xludf.DUMMYFUNCTION("TO_TEXT(G32*100*G29)&TO_TEXT(""/"")&TO_TEXT(G29*100)"),"0/0") -> 0/0 | H28: =IFERROR(__xludf.DUMMYFUNCTION("TO_TEXT(H32*100*H29)&TO_TEXT(""/"")&TO_TEXT(H29*100)"),"0/0") -> 0/0 | I28: =IFERROR(__xludf.DUMMYFUNCTION("TO_TEXT(I32*100*I29)&TO_TEXT(""/"")&TO_TEXT(I29*100)"),"0/0") -> 0/0 | J28: =IFERROR(__xludf.DUMMYFUNCTION("TO_TEXT(J32*100*J29)&TO_TEXT(""/"")&TO_TEXT(J29*100)"),"0/0") -> 0/0 | K28: =IFERROR(__xludf.DUMMYFUNCTION("TO_TEXT(K32*100*K29)&TO_TEXT(""/"")&TO_TEXT(K29*100)"),"0/0") -> 0/0 | L28: =IFERROR(__xludf.DUMMYFUNCTION("TO_TEXT(L32*100*L29)&TO_TEXT(""/"")&TO_TEXT(L29*100)"),"0/0") -> 0/0 | M28: =IFERROR(__xludf.DUMMYFUNCTION("TO_TEXT((M32/2)*100*M29)&TO_TEXT(""/"")&TO_TEXT(M29*50)"),"0/0") -> 0/0 | N28: =IFERROR(__xludf.DUMMYFUNCTION("TO_TEXT((N32/2)*100*N29)&TO_TEXT(""/"")&TO_TEXT(N29*50)"),"0/0") -> 0/0 | O28: =IFERROR(__xludf.DUMMYFUNCTION("TO_TEXT((O32/2)*100*O29)&TO_TEXT(""/"")&TO_TEXT(O29*50)"),"0/0") -> 0/0 | P28: =IFERROR(__xludf.DUMMYFUNCTION("TO_TEXT((P32/2)*100*P29)&TO_TEXT(""/"")&TO_TEXT(P29*50)"),"0/0") -> 0/0 | Q28: =IFERROR(__xludf.DUMMYFUNCTION("TO_TEXT((Q32/2)*100*Q29)&TO_TEXT(""/"")&TO_TEXT(Q29*50)"),"0/0") -> 0/0 | R28: =IFERROR(__xludf.DUMMYFUNCTION("TO_TEXT((R32/2)*100*R29)&TO_TEXT(""/"")&TO_TEXT(R29*50)"),"0/0") -> 0/0 | S28: =(SUM(M29:R29)*50)+SUM(C29:L29)*100 -> 0
B29: Regiments | C29: 0 | D29: 0 | E29: 0 | F29: 0 | G29: 0 | H29: 0 | I29: 0 | J29: 0 | K29: 0 | L29: 0 | M29: 0 | N29: 0 | O29: 0 | P29: 0 | Q29: 0 | R29: 0
B30: Reinforcing | C30: TRUE | D30: TRUE | E30: TRUE | F30: TRUE | G30: TRUE | H30: TRUE | I30: TRUE | J30: TRUE | K30: TRUE | L30: TRUE | M30: TRUE | N30: TRUE | O30: TRUE | P30: TRUE | Q30: TRUE | R30: TRUE
B31: Cost | C31: =((C32*(C29*C$35)*C$33)+IF(C30,(((1-C32)*C$35)*C$34*C29))) -> 0 | D31: =((D32*(D29*D$35)*D$33)+IF(D30,(((1-D32)*D$35)*D$34*D29))) -> 0 | E31: =((E32*(E29*E$35)*E$33)+IF(E30,(((1-E32)*E$35)*E$34*E29))) -> 0 | F31: =((F32*(F29*F$35)*F$33)+IF(F30,(((1-F32)*F$35)*F$34*F29))) -> 0 | G31: =((G32*(G29*G$35)*G$33)+IF(G30,(((1-G32)*G$35)*G$34*G29))) -> 0 | H31: =((H32*(H29*H$35)*H$33)+IF(H30,(((1-H32)*H$35)*H$34*H29))) -> 0 | I31: =((I32*(I29*I$35)*I$33)+IF(I30,(((1-I32)*I$35)*I$34*I29))) -> 0 | J31: =((J32*(J29*J$35)*J$33)+IF(J30,(((1-J32)*J$35)*J$34*J29))) -> 0 | ... R31: =((R32*(R29*R$35)*R$33)+IF(R30,(((1-R32)*R$35)*R$34*R29))) -> 0 | S31: =SUM(B31:R31) -> 0
B32: Cohesion | C32: 0 | D32: 0 | E32: 0 | F32: 0 | G32: 0 | H32: 0 | I32: 0 | J32: 0 | K32: 0 | L32: 0 | M32: 0 | N32: 0 | O32: 0 | P32: 0 | Q32: 0 | R32: 0
B33: Active Maintenance | C33: 0.5 | D33: 0.75 | E33: 1 | F33: 1 | G33: 1 | H33: 0.5 | I33: 0.75 | J33: 1 | K33: 1 | L33: 1 | M33: 2 | N33: 2 | O33: 2 | P33: 2 | Q33: 2 | R33: 2
B34: Dead Maintenance | C34: 1 | D34: 2 | E34: 3 | F34: 4 | G34: 5 | H34: 1 | I34: 2 | J34: 3 | K34: 4 | L34: 5 | M34: 10 | N34: 11.5 | O34: 13 | P34: 15 | Q34: 18 | R34: 20
B35: # Per Regiment | C35: 100 | D35: 100 | E35: 100 | F35: 100 | G35: 100 | H35: 100 | I35: 100 | J35: 100 | K35: 100 | L35: 100 | M35: 50 | N35: 50 | O35: 50 | P35: 50 | Q35: 50 | R35: 50

Sheet The Crown
B1: Gold Kastar Coins | C1: Total Population | D1: Urban Population | E1: Rural Population | F1: Net Gold Income | G1: Gold Income | H1: Gold Spending | I1: Projected Gold
A2: Kingdom of Shavia Total | B2: 620.74326 | C2: =Provinces!C10 -> 66910375 | D2: =Provinces!D10 -> 1689588 | E2: =Provinces!E10 -> 65220787 | F2: =G2-H2 -> 17365.042 | G2: =Economics!B10 -> 20782.99 | H2: =Economics!C10 -> 3417.9483 | I2: =B2+F2 -> 17985.785

Sheet Ducal Economics
B1: Province | C1: Gold Income | D1: Gold Spending | E1: Final Total Tax Income | F1: Raw Total Tax Income | G1: Urban Tax Income | H1: Rural Tax Income | I1: Liege Taxes | J1: Diplomatic Income | K1: Total Military Spending | L1: Retinue Spending | M1: Levy Spending | N1: Diplomatic Spending | O1: Tax Rate | S1: Basal Tax Rate | T1: Avg. Rural Peasant Income
A2: ='Duchies Summary'!A2 -> Swanhall | B2: Swanhall | C2: =E2+J2 -> 1831.0121 | D2: =K2+N2 -> 5922.3132 | E2: =F2*(1-O2) -> 1831.0121 | F2: =SUM(G2:H2) -> 2441.3494 | G2: ='New Cities'!B132 -> 1708.44 | H2: =S2*(('Duchies Summary'!I2)*T2) -> 732.90943 | I2: =F2-E2 -> 610.33736 | J2: 0 | K2: =L2+M2 -> 5922.3132 | M2: ='Duchies Secret Sheet'!C2*2+'Duchies Secret Sheet'!E2*0.008 -> 5922.3132 | O2: 0.25 | S2: 0.15 | T2: 0.02
A3: ='Duchies Summary'!A3 -> Slutiarm | B3: Madinglia | C3: =E3+J3 -> 789.7235 | D3: =K3+N3 -> 11.92268 | E3: =F3*(1-O3) -> 789.7235 | F3: =SUM(G3:H3) -> 1052.9647 | G3: ='New Cities'!B116 -> 815.88667 | H3: =S3*(('Duchies Summary'!I3)*T3) -> 237.078 | I3: =F3-E3 -> 263.24117 | J3: 0 | K3: =L3+M3 -> 11.92268 | M3: ='Duchies Secret Sheet'!C3*2+'Duchies Secret Sheet'!E3*0.008 -> 11.92268 | O3: 0.25 | S3: 0.15 | T3: 0.02
A4: ='Duchies Summary'!A4 -> Dreghold | B4: Dreghold | C4: =E4+J4 -> 3876.8602 | D4: =K4+N4 -> 5398.7936 | E4: =F4*(1-O4) -> 3876.8602 | F4: =SUM(G4:H4) -> 5169.1469 | G4: ='New Cities'!B13 -> 3925.4283 | H4: =S4*(('Duchies Summary'!I4)*T4) -> 1243.7186 | I4: =F4-E4 -> 1292.2867 | K4: =L4+M4 -> 5398.7936 | M4: ='Duchies Secret Sheet'!C4*2+'Duchies Secret Sheet'!E4*0.008 -> 5398.7936 | O4: 0.25 | S4: 0.15 | T4: 0.02
A5: ='Duchies Summary'!A5 -> Sirong | B5: Sirong | C5: =E5+J5 -> 3086.6723 | D5: =K5+N5 -> 20090.483 | E5: =F5*(1-O5) -> 3086.6723 | F5: =SUM(G5:H5) -> 4115.563 | G5: ='New Cities'!B113 -> 2227.4333 | H5: =S5*(('Duchies Summary'!I5)*T5) -> 1888.1297 | I5: =F5-E5 -> 1028.8908 | K5: =L5+M5 -> 20090.483 | M5: ='Duchies Secret Sheet'!C5*2+'Duchies Secret Sheet'!E5*0.008 -> 20090.483 | O5: 0.25 | S5: 0.15 | T5: 0.02
A6: ='Duchies Summary'!A6 -> Brookward | B6: Ralim | C6: =E6+J6 -> 3600.0564 | D6: =K6+N6 -> 13108.221 | E6: =F6*(1-O6) -> 3600.0564 | F6: =SUM(G6:H6) -> 4800.0752 | G6: ='New Cities'!B10 -> 3750.5167 | H6: =S6*(('Duchies Summary'!I6)*T6) -> 1049.5586 | I6: =F6-E6 -> 1200.0188 | K6: =L6+M6 -> 13108.221 | M6: ='Duchies Secret Sheet'!C6*2+'Duchies Secret Sheet'!E6*0.008 -> 13108.221 | O6: 0.25 | S6: 0.15 | T6: 0.02
A7: ='Duchies Summary'!A7 -> Vhalian Marches | B7: Sirong | C7: =E7+J7 -> 4717.9266 | D7: =K7+N7 -> 40219.636 | E7: =F7*(1-O7) -> 4717.9266 | F7: =SUM(G7:H7) -> 6290.5689 | G7: ='New Cities'!B150 -> 1641.48 | H7: =S7*(('Duchies Summary'!I7)*T7) -> 4649.0889 | I7: =F7-E7 -> 1572.6422 | K7: =L7+M7 -> 40219.636 | M7: ='Duchies Secret Sheet'!C7*2+'Duchies Secret Sheet'!E7*0.008 -> 40219.636 | O7: 0.25 | S7: 0.15 | T7: 0.02
A8: ='Duchies Summary'!A8 -> Southern Shores | B8: Sirong | C8: =E8+J8 -> 1498.3118 | D8: =K8+N8 -> 10048.967 | E8: =F8*(1-O8) -> 1498.3118 | F8: =SUM(G8:H8) -> 1997.749 | G8: ='New Cities'!B118 -> 976.045 | H8: =S8*(('Duchies Summary'!I8)*T8) -> 1021.704 | I8: =F8-E8 -> 499.43725 | K8: =L8+M8 -> 10048.967 | M8: ='Duchies Secret Sheet'!C8*2+'Duchies Secret Sheet'!E8*0.008 -> 10048.967 | O8: 0.25 | S8: 0.15 | T8: 0.02
A9: ='Duchies Summary'!A9 -> Dregsten Bay | B9: Sirong | C9: =E9+J9 -> 3314.2312 | D9: =K9+N9 -> 86.88224 | E9: =F9*(1-O9) -> 3314.2312 | F9: =SUM(G9:H9) -> 4418.9749 | G9: ='New Cities'!B19 -> 2613.6683 | H9: =S9*(('Duchies Summary'!I9)*T9) -> 1805.3066 | I9: =F9-E9 -> 1104.7437 | K9: =L9+M9 -> 86.88224 | M9: ='Duchies Secret Sheet'!C9*2+'Duchies Secret Sheet'!E9*0.008 -> 86.88224 | O9: 0.25 | S9: 0.15 | T9: 0.02
A10: ='Duchies Summary'!A10 -> Amber Shores | B10: Sirong | C10: =E10+J10 -> 849.16475 | D10: =K10+N10 -> 35.884 | E10: =F10*(1-O10) -> 849.16475 | F10: =SUM(G10:H10) -> 1132.2197 | G10: ='New Cities'!B2 -> 371.79167 | H10: =S10*(('Duchies Summary'!I10)*T10) -> 760.428 | I10: =F10-E10 -> 283.05492 | K10: =L10+M10 -> 35.884 | M10: ='Duchies Secret Sheet'!C10*2+'Duchies Secret Sheet'!E10*0.008 -> 35.884 | O10: 0.25 | S10: 0.15 | T10: 0.02
A11: ='Duchies Summary'!A11 -> Griffin's Bay | B11: Sirong | C11: =E11+J11 -> 4080.9626 | D11: =K11+N11 -> 4090.0459 | E11: =F11*(1-O11) -> 4080.9626 | F11: =SUM(G11:H11) -> 5441.2835 | G11: ='New Cities'!B34 -> 3612.0867 | H11: =S11*(('Duchies Summary'!I11)*T11) -> 1829.1969 | I11: =F11-E11 -> 1360.3209 | K11: =L11+M11 -> 4090.0459 | L11: ='Retinue Breakdown'!R21 -> 0 | M11: ='Duchies Secret Sheet'!C11*2+'Duchies Secret Sheet'!E11*0.008 -> 4090.0459 | O11: 0.25 | S11: 0.15 | T11: 0.02
A12: ='Duchies Summary'!A12 -> Lesserlands | B12: Sirong | C12: =E12+J12 -> 1776.1785 | D12: =K12+N12 -> 8067.125 | E12: =F12*(1-O12) -> 1776.1785 | F12: =SUM(G12:H12) -> 2368.238 | G12: ='New Cities'!B46 -> 955.34167 | H12: =S12*(('Duchies Summary'!I12)*T12) -> 1412.8963 | I12: =F12-E12 -> 592.05949 | K12: =L12+M12 -> 8067.125 | L12: ='Retinue Breakdown'!R22 -> 0 | M12: ='Duchies Secret Sheet'!C12*2+'Duchies Secret Sheet'!E12*0.008 -> 8067.125 | O12: 0.25 | S12: 0.15 | T12: 0.02
A13: ='Duchies Summary'!A13 -> ShadowWood | B13: Ralim | C13: =E13+J13 -> 1391.0372 | D13: =K13+N13 -> 2481.6021 | E13: =F13*(1-O13) -> 1391.0372 | F13: =SUM(G13:H13) -> 1854.7163 | G13: ='New Cities'!B109 -> 107.95 | H13: =S13*(('Duchies Summary'!I13)*T13) -> 1746.7663 | I13: =F13-E13 -> 463.67907 | K13: =L13+M13 -> 2481.6021 | M13: ='Duchies Secret Sheet'!C13*2+'Duchies Secret Sheet'!E13*0.008 -> 2481.6021 | O13: 0.25 | S13: 0.15 | T13: 0.02
A14: ='Duchies Summary'!A14 -> Mondwatch | B14: Ralim | C14: =E14+J14 -> 2388.3807 | D14: =K14+N14 -> 6894.1537 | E14: =F14*(1-O14) -> 2388.3807 | F14: =SUM(G14:H14) -> 3184.5076 | G14: ='New Cities'!B75 -> 1413.7533 | H14: =S14*(('Duchies Summary'!I14)*T14) -> 1770.7543 | I14: =F14-E14 -> 796.1269 | K14: =L14+M14 -> 6894.1537 | M14: ='Duchies Secret Sheet'!C14*2+'Duchies Secret Sheet'!E14*0.008 -> 6894.1537 | O14: 0.25 | S14: 0.15 | T14: 0.02
A15: ='Duchies Summary'!A15 -> Ratermarch | B15: Ralim | C15: =E15+J15 -> 1921.6182 | D15: =K15+N15 -> 9486.5434 | E15: =F15*(1-O15) -> 1921.6182 | F15: =SUM(G15:H15) -> 2562.1576 | G15: ='New Cities'!B94 -> 726.33333 | H15: =S15*(('Duchies Summary'!I15)*T15) -> 1835.8243 | I15: =F15-E15 -> 640.5394 | K15: =L15+M15 -> 9486.5434 | M15: ='Duchies Secret Sheet'!C15*2+'Duchies Secret Sheet'!E15*0.008 -> 9486.5434 | O15: 0.25 | S15: 0.15 | T15: 0.02
A16: ='Duchies Summary'!A16 -> Vinh | B16: Crownlands | C16: =E16+J16 -> 1381.6846 | D16: =K16+N16 -> 12037.962 | E16: =F16*(1-O16) -> 1381.6846 | F16: =SUM(G16:H16) -> 1842.2461 | G16: ='New Cities'!B157 -> 835.255 | H16: =S16*(('Duchies Summary'!I16)*T16) -> 1006.9911 | I16: =F16-E16 -> 460.56154 | K16: =L16+M16 -> 12037.962 | M16: ='Duchies Secret Sheet'!C16*2+'Duchies Secret Sheet'!E16*0.008 -> 12037.962 | O16: 0.25 | S16: 0.15 | T16: 0.02
A17: ='Duchies Summary'!A17 -> Drelme | B17: Crownlands | C17: =E17+J17 -> 1545.1213 | D17: =K17+N17 -> 10823.118 | E17: =F17*(1-O17) -> 1545.1213 | F17: =SUM(G17:H17) -> 2060.1617 | G17: ='New Cities'!B25 -> 1165.53 | H17: =S17*(('Duchies Summary'!I17)*T17) -> 894.63171 | I17: =F17-E17 -> 515.04043 | K17: =L17+M17 -> 10823.118 | M17: ='Duchies Secret Sheet'!C17*2+'Duchies Secret Sheet'!E17*0.008 -> 10823.118 | O17: 0.25 | S17: 0.15 | T17: 0.02
A18: ='Duchies Summary'!A18 -> Oal's Reach | B18: Crownlands | C18: =E18+J18 -> 1111.988 | D18: =K18+N18 -> 12170.485 | E18: =F18*(1-O18) -> 1111.988 | F18: =SUM(G18:H18) -> 1482.6507 | G18: ='New Cities'!B79 -> 465.20667 | H18: =S18*(('Duchies Summary'!I18)*T18) -> 1017.444 | I18: =F18-E18 -> 370.66267 | K18: =L18+M18 -> 12170.485 | M18: ='Duchies Secret Sheet'!C18*2+'Duchies Secret Sheet'!E18*0.008 -> 12170.485 | O18: 0.25 | S18: 0.15 | T18: 0.02
A19: ='Duchies Summary'!A19 -> Swiftme | B19: Crownlands | C19: =E19+J19 -> 2468.9778 | D19: =K19+N19 -> 15099.632 | E19: =F19*(1-O19) -> 2468.9778 | F19: =SUM(G19:H19) -> 3291.9704 | G19: ='New Cities'!B136 -> 1188.775 | H19: =S19*(('Duchies Summary'!I19)*T19) -> 2103.1954 | I19: =F19-E19 -> 822.99261 | K19: =L19+M19 -> 15099.632 | M19: ='Duchies Secret Sheet'!C19*2+'Duchies Secret Sheet'!E19*0.008 -> 15099.632 | O19: 0.25 | S19: 0.15 | T19: 0.02
A20: ='Duchies Summary'!A20 -> Heartwell | B20: Crownlands | C20: =E20+J20 -> 3798.4257 | D20: =K20+N20 -> 2014.5494 | E20: =F20*(1-O20) -> 3798.4257 | F20: =SUM(G20:H20) -> 5064.5677 | G20: ='New Cities'!B45 -> 4838.6017 | H20: =S20*(('Duchies Summary'!I20)*T20) -> 225.966 | I20: =F20-E20 -> 1266.1419 | K20: =L20+M20 -> 2014.5494 | M20: ='Duchies Secret Sheet'!C20*2+'Duchies Secret Sheet'!E20*0.008 -> 2014.5494 | O20: 0.25 | S20: 0.15 | T20: 0.02
A21: ='Duchies Summary'!A21 -> Pearlpass | B21: Dreghold | C21: =E21+J21 -> 2782.4113 | D21: =K21+N21 -> 47.870557 | E21: =F21*(1-O21) -> 2782.4113 | F21: =SUM(G21:H21) -> 3709.8818 | G21: ='New Cities'!B82 -> 987.70833 | H21: =S21*(('Duchies Summary'!I21)*T21) -> 2722.1734 | I21: =F21-E21 -> 927.47044 | K21: =L21+M21 -> 47.870557 | M21: ='Duchies Secret Sheet'!C21*2+'Duchies Secret Sheet'!E21*0.008 -> 47.870557 | O21: 0.25 | S21: 0.15 | T21: 0.02
A22: ='Duchies Summary'!A22 -> Prince's Boot | B22: Dreghold | C22: =E22+J22 -> 1060.8134 | D22: =K22+N22 -> 60.29076 | E22: =F22*(1-O22) -> 1060.8134 | F22: =SUM(G22:H22) -> 1414.4179 | G22: ='New Cities'!B87 -> 125.27333 | H22: =S22*(('Duchies Summary'!I22)*T22) -> 1289.1446 | I22: =F22-E22 -> 353.60448 | K22: =L22+M22 -> 60.29076 | M22: ='Duchies Secret Sheet'!C22*2+'Duchies Secret Sheet'!E22*0.008 -> 60.29076 | O22: 0.25 | S22: 0.15 | T22: 0.02
A23: ='Duchies Summary'!A23 -> Swan's Reach | B23: Dreghold | C23: =E23+J23 -> 2473.29 | D23: =K23+N23 -> 8707.4424 | E23: =F23*(1-O23) -> 2473.29 | F23: =SUM(G23:H23) -> 3297.72 | G23: ='New Cities'!B124 -> 899.55167 | H23: =S23*(('Duchies Summary'!I23)*T23) -> 2398.1683 | I23: =F23-E23 -> 824.42999 | K23: =L23+M23 -> 8707.4424 | M23: ='Duchies Secret Sheet'!C23*2+'Duchies Secret Sheet'!E23*0.008 -> 8707.4424 | O23: 0.25 | S23: 0.15 | T23: 0.02
A24: ='Duchies Summary'!A24 -> Malhold | B24: Dreghold | C24: =E24+J24 -> 2427.4079 | D24: =K24+N24 -> 14003.796 | E24: =F24*(1-O24) -> 2427.4079 | F24: =SUM(G24:H24) -> 3236.5438 | G24: ='New Cities'!B51 -> 2118.2167 | H24: =S24*(('Duchies Summary'!I24)*T24) -> 1118.3271 | I24: =F24-E24 -> 809.13595 | K24: =L24+M24 -> 14003.796 | M24: ='Duchies Secret Sheet'!C24*2+'Duchies Secret Sheet'!E24*0.008 -> 14003.796 | O24: 0.25 | S24: 0.15 | T24: 0.02
A25: ='Duchies Summary'!A25 -> Westleden | B25: Dreghold | C25: =E25+J25 -> 1142.0521 | D25: =K25+N25 -> 13252.931 | E25: =F25*(1-O25) -> 1142.0521 | F25: =SUM(G25:H25) -> 1522.7361 | G25: ='New Cities'!B159 -> 405.795 | H25: =S25*(('Duchies Summary'!I25)*T25) -> 1116.9411 | I25: =F25-E25 -> 380.68404 | K25: =L25+M25 -> 13252.931 | M25: ='Duchies Secret Sheet'!C25*2+'Duchies Secret Sheet'!E25*0.008 -> 13252.931 | O25: 0.25 | S25: 0.15 | T25: 0.02
A26: ='Duchies Summary'!A26 -> Shurestar | B26: Dreghold | C26: =E26+J26 -> 1544.0494 | D26: =K26+N26 -> 12031.933 | E26: =F26*(1-O26) -> 1544.0494 | F26: =SUM(G26:H26) -> 2058.7325 | G26: ='New Cities'!B110 -> 1070.0833 | H26: =S26*(('Duchies Summary'!I26)*T26) -> 988.64914 | I26: =F26-E26 -> 514.68312 | K26: =L26+M26 -> 12031.933 | M26: ='Duchies Secret Sheet'!C26*2+'Duchies Secret Sheet'!E26*0.008 -> 12031.933 | O26: 0.25 | S26: 0.15 | T26: 0.02
A27: ='Duchies Summary'!A27 -> Raven's Reach | B27: Swanhall | C27: =E27+J27 -> 2495.4514 | D27: =K27+N27 -> 75.53136 | E27: =F27*(1-O27) -> 2495.4514 | F27: =SUM(G27:H27) -> 3327.2685 | G27: ='New Cities'!B98 -> 1744.5233 | H27: =S27*(('Duchies Summary'!I27)*T27) -> 1582.7451 | I27: =F27-E27 -> 831.81712 | K27: =L27+M27 -> 75.53136 | M27: ='Duchies Secret Sheet'!C27*2+'Duchies Secret Sheet'!E27*0.008 -> 75.53136 | O27: 0.25 | S27: 0.15 | T27: 0.02
A28: ='Duchies Summary'!A28 -> Northfold | B28: Swanhall | C28: =E28+J28 -> 800.35007 | D28: =K28+N28 -> 17.93472 | E28: =F28*(1-O28) -> 800.35007 | F28: =SUM(G28:H28) -> 1067.1334 | G28: ='New Cities'!B78 -> 702.9 | H28: =S28*(('Duchies Summary'!I28)*T28) -> 364.23343 | I28: =F28-E28 -> 266.78336 | K28: =L28+M28 -> 17.93472 | M28: ='Duchies Secret Sheet'!C28*2+'Duchies Secret Sheet'!E28*0.008 -> 17.93472 | O28: 0.25 | S28: 0.15 | T28: 0.02
A29: ='Duchies Summary'!A29 -> Blackstone | B29: Swanhall | C29: =E29+J29 -> 3069.8678 | D29: =K29+N29 -> 84.29272 | E29: =F29*(1-O29) -> 3069.8678 | F29: =SUM(G29:H29) -> 4093.157 | G29: ='New Cities'!B6 -> 2335.295 | H29: =S29*(('Duchies Summary'!I29)*T29) -> 1757.862 | I29: =F29-E29 -> 1023.2892 | K29: =L29+M29 -> 84.29272 | M29: ='Duchies Secret Sheet'!C29*2+'Duchies Secret Sheet'!E29*0.008 -> 84.29272 | O29: 0.25 | S29: 0.15 | T29: 0.02
A30: ='Duchies Summary'!A30 -> Ravenmark | B30: Swanhall | C30: =E30+J30 -> 1114.7415 | D30: =K30+N30 -> 32.57944 | E30: =F30*(1-O30) -> 1114.7415 | F30: =SUM(G30:H30) -> 1486.322 | G30: ='New Cities'!B103 -> 809.6 | H30: =S30*(('Duchies Summary'!I30)*T30) -> 676.722 | I30: =F30-E30 -> 371.5805 | K30: =L30+M30 -> 32.57944 | M30: ='Duchies Secret Sheet'!C30*2+'Duchies Secret Sheet'!E30*0.008 -> 32.57944 | O30: 0.25 | S30: 0.15 | T30: 0.02
A31: ='Duchies Summary'!A31 -> Wet Shoor | B31: Swanhall | C31: =E31+J31 -> 763.7325 | D31: =K31+N31 -> 45.06364 | E31: =F31*(1-O31) -> 763.7325 | F31: =SUM(G31:H31) -> 1018.31 | G31: ='New Cities'!C166 -> 65.6 | H31: =S31*(('Duchies Summary'!I31)*T31) -> 952.71 | I31: =F31-E31 -> 254.5775 | K31: =L31+M31 -> 45.06364 | M31: ='Duchies Secret Sheet'!C31*2+'Duchies Secret Sheet'!E31*0.008 -> 45.06364 | O31: 0.25 | S31: 0.15 | T31: 0.02
A32: ='Duchies Summary'!A32 -> Quickwatch | B32: Swanhall | C32: =E32+J32 -> 2223.5819 | D32: =K32+N32 -> 84.66312 | E32: =F32*(1-O32) -> 2223.5819 | F32: =SUM(G32:H32) -> 2964.7759 | G32: ='New Cities'!B88 -> 1190.365 | H32: =S32*(('Duchies Summary'!I32)*T32) -> 1774.4109 | I32: =F32-E32 -> 741.19396 | K32: =L32+M32 -> 84.66312 | M32: ='Duchies Secret Sheet'!C32*2+'Duchies Secret Sheet'!E32*0.008 -> 84.66312 | O32: 0.25 | S32: 0.15 | T32: 0.02
A33: ='Duchies Summary'!A33 -> The Deepwood | B33: Swanhall | C33: =E33+J33 -> 1636.211 | D33: =K33+N33 -> 34.33712 | E33: =F33*(1-O33) -> 1636.211 | F33: =SUM(G33:H33) -> 2181.6147 | G33: ='New Cities'!B139 -> 1476.925 | H33: =S33*(('Duchies Summary'!I33)*T33) -> 704.68971 | I33: =F33-E33 -> 545.40368 | K33: =L33+M33 -> 34.33712 | M33: ='Duchies Secret Sheet'!C33*2+'Duchies Secret Sheet'!E33*0.008 -> 34.33712 | O33: 0.25 | S33: 0.15 | T33: 0.02
A34: ='Duchies Summary'!A34 -> Swan's Shoor | B34: Swanhall | C34: =E34+J34 -> 2369.769 | D34: =K34+N34 -> 10040.682 | E34: =F34*(1-O34) -> 2369.769 | F34: =SUM(G34:H34) -> 3159.692 | G34: ='New Cities'!B126 -> 2349.2283 | H34: =S34*(('Duchies Summary'!I34)*T34) -> 810.46371 | I34: =F34-E34 -> 789.92301 | K34: =L34+M34 -> 10040.682 | M34: ='Duchies Secret Sheet'!C34*2+'Duchies Secret Sheet'!E34*0.008 -> 10040.682 | O34: 0.25 | S34: 0.15 | T34: 0.02
A35: ='Duchies Summary'!A35 -> The Shield | B35: Swanhall | C35: =E35+J35 -> 1786.6014 | D35: =K35+N35 -> 51.52004 | E35: =F35*(1-O35) -> 1786.6014 | F35: =SUM(G35:H35) -> 2382.1351 | G35: ='New Cities'!B146 -> 1307.65 | H35: =S35*(('Duchies Summary'!I35)*T35) -> 1074.4851 | I35: =F35-E35 -> 595.53379 | K35: =L35+M35 -> 51.52004 | M35: ='Duchies Secret Sheet'!C35*2+'Duchies Secret Sheet'!E35*0.008 -> 51.52004 | O35: 0.25 | S35: 0.15 | T35: 0.02
A36: ='Duchies Summary'!A36 -> Elreach | B36: Swanhall | C36: =E36+J36 -> 1738.9688 | D36: =K36+N36 -> 60.3836 | E36: =F36*(1-O36) -> 1738.9688 | F36: =SUM(G36:H36) -> 2318.625 | G36: ='New Cities'!B31 -> 1061.2033 | H36: =S36*(('Duchies Summary'!I36)*T36) -> 1257.4217 | I36: =F36-E36 -> 579.65626 | K36: =L36+M36 -> 60.3836 | M36: ='Duchies Secret Sheet'!C36*2+'Duchies Secret Sheet'!E36*0.008 -> 60.3836 | O36: 0.25 | S36: 0.15 | T36: 0.02
A37: ='Duchies Summary'!A37 -> Mightkeep | B37: Swanhall | C37: =E37+J37 -> 2802.0225 | D37: =K37+N37 -> 11044.723 | E37: =F37*(1-O37) -> 2802.0225 | F37: =SUM(G37:H37) -> 3736.03 | G37: ='New Cities'!B65 -> 2855.2283 | H37: =S37*(('Duchies Summary'!I37)*T37) -> 880.80171 | I37: =F37-E37 -> 934.00751 | K37: =L37+M37 -> 11044.723 | M37: ='Duchies Secret Sheet'!C37*2+'Duchies Secret Sheet'!E37*0.008 -> 11044.723 | O37: 0.25 | S37: 0.15 | T37: 0.02
A38: ='Duchies Summary'!A38 -> Mightfall | B38: Swanhall | C38: =E38+J38 -> 1443.6026 | D38: =K38+N38 -> 10042.835 | E38: =F38*(1-O38) -> 1443.6026 | F38: =SUM(G38:H38) -> 1924.8035 | G38: ='New Cities'!B60 -> 1040.6667 | H38: =S38*(('Duchies Summary'!I38)*T38) -> 884.13686 | I38: =F38-E38 -> 481.20088 | K38: =L38+M38 -> 10042.835 | M38: ='Duchies Secret Sheet'!C38*2+'Duchies Secret Sheet'!E38*0.008 -> 10042.835 | O38: 0.25 | S38: 0.15 | T38: 0.02
A39: ='Duchies Summary'!A39 -> Eguard | B39: Swanhall | C39: =E39+J39 -> 1664.942 | D39: =K39+N39 -> 6827.9631 | E39: =F39*(1-O39) -> 1664.942 | F39: =SUM(G39:H39) -> 2219.9227 | G39: ='New Cities'!B29 -> 1651.175 | H39: =S39*(('Duchies Summary'!I39)*T39) -> 568.74771 | I39: =F39-E39 -> 554.98068 | K39: =L39+M39 -> 6827.9631 | M39: ='Duchies Secret Sheet'!C39*2+'Duchies Secret Sheet'!E39*0.008 -> 6827.9631 | O39: 0.25 | S39: 0.15 | T39: 0.02
A40: ='Duchies Summary'!A40 -> Lonely Light | B40: Swanhall | C40: =E40+J40 -> 249.34514 | D40: =K40+N40 -> 2.39616 | E40: =F40*(1-O40) -> 249.34514 | F40: =SUM(G40:H40) -> 332.46019 | G40: ='New Cities'!B50 -> 288.53333 | H40: =S40*(('Duchies Summary'!I40)*T40) -> 43.926857 | I40: =F40-E40 -> 83.115048 | K40: =L40+M40 -> 2.39616 | M40: ='Duchies Secret Sheet'!C40*2+'Duchies Secret Sheet'!E40*0.008 -> 2.39616 | O40: 0.25 | S40: 0.15 | T40: 0.02
A41: ='Duchies Summary'!A41 -> The Valley | B41: Madinglia | C41: =E41+J41 -> 685.25861 | D41: =K41+N41 -> 41.38208 | E41: =F41*(1-O41) -> 685.25861 | F41: =SUM(G41:H41) -> 913.67814 | G41: ='New Cities'!B149 -> 27.875 | H41: =S41*(('Duchies Summary'!I41)*T41) -> 885.80314 | I41: =F41-E41 -> 228.41954 | K41: =L41+M41 -> 41.38208 | M41: ='Duchies Secret Sheet'!C41*2+'Duchies Secret Sheet'!E41*0.008 -> 41.38208 | O41: 0.25 | S41: 0.15 | T41: 0.02
A42: ='Duchies Summary'!A42 -> The Knolls | B42: Madinglia | C42: =E42+J42 -> 978.17771 | D42: =K42+N42 -> 46.49292 | E42: =F42*(1-O42) -> 978.17771 | F42: =SUM(G42:H42) -> 1304.237 | G42: ='New Cities'!B143 -> 316.38667 | H42: =S42*(('Duchies Summary'!I42)*T42) -> 987.85029 | I42: =F42-E42 -> 326.05924 | K42: =L42+M42 -> 46.49292 | M42: ='Duchies Secret Sheet'!C42*2+'Duchies Secret Sheet'!E42*0.008 -> 46.49292 | O42: 0.25 | S42: 0.15 | T42: 0.02
A43: ='Duchies Summary'!A43 -> Persterton Pass | B43: Madinglia | C43: =E43+J43 -> 343.06154 | D43: =K43+N43 -> 12.4072 | E43: =F43*(1-O43) -> 343.06154 | F43: =SUM(G43:H43) -> 457.41538 | G43: ='New Cities'!B83 -> 197.96167 | H43: =S43*(('Duchies Summary'!I43)*T43) -> 259.45371 | I43: =F43-E43 -> 114.35385 | K43: =L43+M43 -> 12.4072 | M43: ='Duchies Secret Sheet'!C43*2+'Duchies Secret Sheet'!E43*0.008 -> 12.4072 | O43: 0.25 | S43: 0.15 | T43: 0.02
A44: ='Duchies Summary'!A44 -> Rordgoz | B44: Madinglia | C44: =E44+J44 -> 387.31346 | D44: =K44+N44 -> 22.30392 | E44: =F44*(1-O44) -> 387.31346 | F44: =SUM(G44:H44) -> 516.41795 | G44: ='New Cities'!B108 -> 40.061667 | H44: =S44*(('Duchies Summary'!I44)*T44) -> 476.35629 | I44: =F44-E44 -> 129.10449 | K44: =L44+M44 -> 22.30392 | M44: ='Duchies Secret Sheet'!C44*2+'Duchies Secret Sheet'!E44*0.008 -> 22.30392 | O44: 0.25 | S44: 0.15 | T44: 0.02
A45: ='Duchies Summary'!A45 -> Briduan | B45: Madinglia | C45: =E45+J45 -> 280.88046 | D45: =K45+N45 -> 15.37348 | E45: =F45*(1-O45) -> 280.88046 | F45: =SUM(G45:H45) -> 374.50729 | G45: ='New Cities'!B9 -> 46.675 | H45: =S45*(('Duchies Summary'!I45)*T45) -> 327.83229 | I45: =F45-E45 -> 93.626821 | K45: =L45+M45 -> 15.37348 | M45: ='Duchies Secret Sheet'!C45*2+'Duchies Secret Sheet'!E45*0.008 -> 15.37348 | O45: 0.25 | S45: 0.15 | T45: 0.02
A46: Sum | C46: =SUM(C2:C45) -> 83692.237 | D46: =SUM(D2:D45) -> 264775.45 | E46: =SUM(E2:E45) -> 83692.237 | F46: =SUM(F2:F45) -> 111589.65 | G46: =SUM(G2:G45) -> 58454.005 | H46: =SUM(H2:H45) -> 53135.644 | I46: =SUM(I2:I45) -> 27897.412 | J46: =SUM(J2:J45) -> 0 | ... M46: =SUM(M2:M45) -> 264775.45
A47: Average | C47: =AVERAGE(C2:C45) -> 1902.0963 | D47: =AVERAGE(D2:D45) -> 6017.6238 | E47: =AVERAGE(E2:E45) -> 1902.0963 | F47: =AVERAGE(F2:F45) -> 2536.1284 | G47: =AVERAGE(G2:G45) -> 1328.5001 | H47: =AVERAGE(H2:H45) -> 1207.6283 | I47: =AVERAGE(I2:I45) -> 634.0321 | J47: =AVERAGE(J2:J45) -> 0 | K47: =AVERAGE(K2:K45) -> 6017.6238 | M47: =AVERAGE(M2:M45) -> 6017.6238

Sheet Provinces
B1: Gold Kastar Coins | C1: Total Population | D1: Urban Population | E1: Rural Population | F1: Gold Net Income | G1: Retinues | H1: Raised Levys | I1: Possible Levys | J1: Projected Gold | K1: Urban Population % | L1: Rural Population %
A2: The Crownlands | B2: N/A | C2: ='Province Import (Ignore)'!I5 -> 6198707 | D2: =SUM(Cities!E2:E13) -> 211771 | E2: =C2-D2 -> 5986936 | F2: N/A | G2: ='Retinue Breakdown'!R3 -> 113 | H2: ='Secret Sheet'!D1 -> 0 | I2: =IFERROR(__xludf.DUMMYFUNCTION("TO_TEXT(round(RANDBETWEEN(1000,10000)+(C2*0.005)))&TO_TEXT(round(RANDBETWEEN(1000,10000)-(C2*0.005)))"),"40114-23824") -> 40114-23824 | J2: N/A | K2: =D2/C2 -> 0.034163738 | L2: =E2/C2 -> 0.96583626
A3: Dreghold | B3: -301469.79 | C3: ='Province Import (Ignore)'!I4 -> 13047830 | D3: =SUM(Cities!E14:E38) -> 210019 | E3: =C3-D3 -> 12837811 | F3: =Economics!B3-Economics!C3 -> -84280.87 | G3: ='Retinue Breakdown'!R4 -> 50 | H3: ='Secret Sheet'!D2 -> 45561 | I3: =IFERROR(__xludf.DUMMYFUNCTION("TO_TEXT(round(RANDBETWEEN(1000,10000)+(C3*0.005)))&TO_TEXT(round(RANDBETWEEN(1000,10000)-(C3*0.005)))"),"69002-57386") -> 69002-57386 | J3: =B3+F3 -> -385750.66 | K3: =D3/C3 -> 0.016096086 | L3: =E3/C3 -> 0.98390391
A4: Madinglia | B4: 7582.784 | C4: ='Province Import (Ignore)'!I3 -> 3739211 | D4: =SUM(Cities!E39:E50) -> 72536 | E4: =C4-D4 -> 3666675 | F4: =Economics!B4-Economics!C4 -> -31409.242 | G4: ='Retinue Breakdown'!R5 -> 250 | H4: ='Secret Sheet'!D3 -> 18000 | I4: =IFERROR(__xludf.DUMMYFUNCTION("TO_TEXT(round(RANDBETWEEN(1000,10000)+(C4*0.005)))&TO_TEXT(round(RANDBETWEEN(1000,10000)-(C4*0.005)))"),"24354-9266") -> 24354-9266 | J4: =B4+F4 -> -23826.458 | K4: =D4/C4 -> 0.019398745 | L4: =E4/C4 -> 0.98060126
A5: Pearlpass | B5: 6105.5957 | C5: ='Province Import (Ignore)'!I8 -> 3182524 | D5: 22576 | E5: =C5-D5 -> 3159948 | F5: =Economics!B5-Economics!C5 -> 3057.4531 | G5: ='Retinue Breakdown'!R6 -> 50 | H5: ='Secret Sheet'!D4 -> 0 | I5: =IFERROR(__xludf.DUMMYFUNCTION("TO_TEXT(round(RANDBETWEEN(1000,10000)+(C5*0.005)))&TO_TEXT(round(RANDBETWEEN(1000,10000)-(C5*0.005)))"),"21599-7125") -> 21599-7125 | J5: =B5+F5 -> 9163.0489 | K5: =D5/C5 -> 0.0070937407 | L5: =E5/C5 -> 0.99290626
A6: Ralim | B6: 2105 | C6: ='Province Import (Ignore)'!I7 -> 7694131 | D6: =SUM(Cities!E52:E63) -> 132591 | E6: =C6-D6 -> 7561540 | F6: =Economics!B6-Economics!C6 -> 4809.9853 | G6: ='Retinue Breakdown'!R7 -> 50 | H6: ='Secret Sheet'!D5 -> 0 | I6: =IFERROR(__xludf.DUMMYFUNCTION("TO_TEXT(round(RANDBETWEEN(1000,10000)+(C6*0.005)))&TO_TEXT(round(RANDBETWEEN(1000,10000)-(C6*0.005)))"),"46300-32713") -> 46300-32713 | J6: =B6+F6 -> 6914.9853 | K6: =D6/C6 -> 0.017232745 | L6: =E6/C6 -> 0.98276725
A7: Sirong | B7: -135014.53 | C7: ='Province Import (Ignore)'!I6 -> 16040936 | D7: =SUM(Cities!E65:E104) -> 460501 | E7: =C7-D7 -> 15580435 | F7: =Economics!B7-Economics!C7 -> -24849.709 | G7: ='Retinue Breakdown'!R8 -> 70 | H7: ='Secret Sheet'!D6 -> 16275 | I7: =IFERROR(__xludf.DUMMYFUNCTION("TO_TEXT(round(RANDBETWEEN(1000,10000)+(C7*0.005)))&TO_TEXT(round(RANDBETWEEN(1000,10000)-(C7*0.005)))"),"87808-77387") -> 87808-77387 | J7: =B7+F7 -> -159864.24 | K7: =D7/C7 -> 0.028707863 | L7: =E7/C7 -> 0.97129214
A8: Swanhall | B8: 29622.822 | C8: ='Province Import (Ignore)'!I2 -> 17007036 | D8: =SUM(Cities!E105:E166) -> 579594 | E8: =C8-D8 -> 16427442 | F8: =Economics!B8-Economics!C8 -> 6312.087 | G8: ='Retinue Breakdown'!R9 -> 50 | H8: ='Secret Sheet'!D7 -> 1111 | I8: =IFERROR(__xludf.DUMMYFUNCTION("TO_TEXT(round(RANDBETWEEN(1000,10000)+(C8*0.005)))&TO_TEXT(round(RANDBETWEEN(1000,10000)-(C8*0.005)))"),"87415-79183") -> 87415-79183 | J8: =B8+F8 -> 35934.908 | K8: =D8/C8 -> 0.03407966 | L8: =E8/C8 -> 0.96592034
A9: Average | B9: -20320.069 | C9: =AVERAGE(C2:C8) -> 9558625 | D9: =AVERAGE(D2:D8) -> 241369.71 | E9: =AVERAGE(E2:E8) -> 9317255.3 | F9: =AVERAGE(F2:F8) -> -21060.049 | G9: =AVERAGE(G2:G8) -> 90.428571 | I9: =AVERAGE('Secret Sheet'!E1:E7) -> 44714.125 | J9: =AVERAGE(J2:J8) -> -86238.069 | K9: =AVERAGE(K2:K8) -> 0.022396083 | L9: =AVERAGE(L2:L8) -> 0.97760392
A10: Total | B10: =SUM(B2:B8) -> -391068.12 | C10: =SUM(C2:C8) -> 66910375 | D10: =SUM(D2:D8) -> 1689588 | E10: =SUM(E2:E8) -> 65220787 | F10: =SUM(F2:F8) -> -126360.3 | G10: =SUM(G2:G8) -> 633 | I10: =SUM('Secret Sheet'!E1:E7) -> 312998.88 | J10: =SUM(J2:J8) -> -517428.42

Sheet Duchies Secret Sheet
A1: Duchy | B1: Province | C1: True Raised | D1: Raised Levies | E1: True Possible Levies | F1: Possible Levies | G1: Casualties | H1: Injured | I1: Dead | J1: Deserted | K1: Ticks Without Pay | L1: Without Pay T/F | M1: Recovered Injured | N1: Future Injured | O1: Future Ticks Without Pay
A2: ='Duchies Summary'!A2 -> Swanhall | B2: ='Ducal Economics'!B2 -> Swanhall | C2: =IF(D2>0,D2-G2,0) -> 2949.3599 | D2: 4490 | E2: =('Duchies Summary'!J2*0.005)-G2 -> 2949.1899 | F2: =('Duchies Summary'!J2*0.005) -> 4489.83 | G2: =SUM(H2:J2) -> 1540.6401 | H2: 686.64015 | I2: 854 | J2: =(D2*0.02)*K2 -> 0 | K2: 0 | L2: =IF(AND('Duchies Summary'!E2<=0,E2>0),1,0) -> 0 | M2: =H2*0.05 -> 34.332007 | N2: =H2-M2 -> 652.30814 | O2: {=K2+IF(L2=1,1,_xlfn.IFS(K2>0,-1,K2=0,0))} -> 0
A3: ='Duchies Summary'!A3 -> Slutiarm | B3: ='Ducal Economics'!B3 -> Madinglia | C3: =IF(D3>0,D3-G3,0) -> 0 | D3: 0 | E3: =('Duchies Summary'!J3*0.005)-G3 -> 1490.335 | F3: =('Duchies Summary'!J3*0.005) -> 1490.335 | G3: =SUM(H3:J3) -> 0 | H3: 0 | J3: =(D3*0.02)*K3 -> 0 | K3: 0 | L3: =IF(AND('Duchies Summary'!E3<=0,E3>0),1,0) -> 0 | M3: =H3*0.05 -> 0 | N3: =H3-M3 -> 0 | O3: {=K3+IF(L3=1,1,_xlfn.IFS(K3>0,-1,K3=0,0))} -> 0
A4: ='Duchies Summary'!A4 -> Dreghold | B4: ='Ducal Economics'!B4 -> Dreghold | C4: =IF(D4>0,D4-G4,0) -> 2688.6408 | D4: 7758 | E4: =('Duchies Summary'!J4*0.005)-G4 -> 2688.9958 | F4: =('Duchies Summary'!J4*0.005) -> 7758.355 | G4: =SUM(H4:J4) -> 5069.3592 | H4: 2583.3592 | I4: 2486 | J4: =(D4*0.02)*K4 -> 0 | K4: 0 | L4: =IF(AND('Duchies Summary'!E4<=0,E4>0),1,0) -> 0 | M4: =H4*0.05 -> 129.16796 | N4: =H4-M4 -> 2454.1912 | O4: {=K4+IF(L4=1,1,_xlfn.IFS(K4>0,-1,K4=0,0))} -> 0
A5: ='Duchies Summary'!A5 -> Sirong | B5: ='Ducal Economics'!B5 -> Sirong | C5: =IF(D5>0,D5-G5,0) -> 10000 | D5: 10000 | E5: =('Duchies Summary'!J5*0.005)-G5 -> 11310.385 | F5: =('Duchies Summary'!J5*0.005) -> 11310.385 | G5: =SUM(H5:J5) -> 0 | H5: 0 | J5: =(D5*0.02)*K5 -> 0 | K5: 0 | L5: =IF(AND('Duchies Summary'!E5<=0,E5>0),1,0) -> 1 | M5: =H5*0.05 -> 0 | N5: =H5-M5 -> 0 | O5: {=K5+IF(L5=1,1,_xlfn.IFS(K5>0,-1,K5=0,0))} -> 1
A6: ='Duchies Summary'!A6 -> Brookward | B6: ='Ducal Economics'!B6 -> Ralim | C6: =IF(D6>0,D6-G6,0) -> 6528 | D6: 6528 | E6: =('Duchies Summary'!J6*0.005)-G6 -> 6527.635 | F6: =('Duchies Summary'!J6*0.005) -> 6527.635 | G6: =SUM(H6:J6) -> 0 | H6: 0 | J6: =(D6*0.02)*K6 -> 0 | K6: 0 | L6: =IF(AND('Duchies Summary'!E6<=0,E6>0),1,0) -> 0 | M6: =H6*0.05 -> 0 | N6: =H6-M6 -> 0 | O6: {=K6+IF(L6=1,1,_xlfn.IFS(K6>0,-1,K6=0,0))} -> 0
A7: ='Duchies Summary'!A7 -> Vhalian Marches | B7: ='Ducal Economics'!B7 -> Sirong | C7: =IF(D7>0,D7-G7,0) -> 20000 | D7: 20000 | E7: =('Duchies Summary'!J7*0.005)-G7 -> 27454.545 | F7: =('Duchies Summary'!J7*0.005) -> 27454.545 | G7: =SUM(H7:J7) -> 0 | H7: 0 | J7: =(D7*0.02)*K7 -> 0 | K7: 0 | L7: =IF(AND('Duchies Summary'!E7<=0,E7>0),1,0) -> 0 | M7: =H7*0.05 -> 0 | N7: =H7-M7 -> 0 | O7: {=K7+IF(L7=1,1,_xlfn.IFS(K7>0,-1,K7=0,0))} -> 0
A8: ='Duchies Summary'!A8 -> Southern Shores | B8: ='Ducal Economics'!B8 -> Sirong | C8: =IF(D8>0,D8-G8,0) -> 5000 | D8: 5000 | E8: =('Duchies Summary'!J8*0.005)-G8 -> 6120.835 | F8: =('Duchies Summary'!J8*0.005) -> 6120.835 | G8: =SUM(H8:J8) -> 0 | H8: 0 | J8: =(D8*0.02)*K8 -> 0 | K8: 0 | L8: =IF(AND('Duchies Summary'!E8<=0,E8>0),1,0) -> 1 | M8: =H8*0.05 -> 0 | N8: =H8-M8 -> 0 | O8: {=K8+IF(L8=1,1,_xlfn.IFS(K8>0,-1,K8=0,0))} -> 1
A9: ='Duchies Summary'!A9 -> Dregsten Bay | B9: ='Ducal Economics'!B9 -> Sirong | C9: =IF(D9>0,D9-G9,0) -> 0 | D9: 0 | E9: =('Duchies Summary'!J9*0.005)-G9 -> 10860.28 | F9: =('Duchies Summary'!J9*0.005) -> 10860.28 | G9: =SUM(H9:J9) -> 0 | H9: 0 | J9: =(D9*0.02)*K9 -> 0 | K9: 0 | L9: =IF(AND('Duchies Summary'!E9<=0,E9>0),1,0) -> 0 | M9: =H9*0.05 -> 0 | N9: =H9-M9 -> 0 | O9: {=K9+IF(L9=1,1,_xlfn.IFS(K9>0,-1,K9=0,0))} -> 0
A10: ='Duchies Summary'!A10 -> Amber Shores | B10: ='Ducal Economics'!B10 -> Sirong | C10: =IF(D10>0,D10-G10,0) -> 0 | D10: 0 | E10: =('Duchies Summary'!J10*0.005)-G10 -> 4485.5 | F10: =('Duchies Summary'!J10*0.005) -> 4485.5 | G10: =SUM(H10:J10) -> 0 | H10: 0 | J10: =(D10*0.02)*K10 -> 0 | K10: 0 | L10: =IF(AND('Duchies Summary'!E10<=0,E10>0),1,0) -> 0 | M10: =H10*0.05 -> 0 | N10: =H10-M10 -> 0 | O10: {=K10+IF(L10=1,1,_xlfn.IFS(K10>0,-1,K10=0,0))} -> 0
A11: ='Duchies Summary'!A11 -> Griffin's Bay | B11: ='Ducal Economics'!B11 -> Sirong | C11: =IF(D11>0,D11-G11,0) -> 2000 | D11: 2000 | E11: =('Duchies Summary'!J11*0.005)-G11 -> 11255.74 | F11: =('Duchies Summary'!J11*0.005) -> 11255.74 | G11: =SUM(H11:J11) -> 0 | H11: 0 | J11: =(D11*0.02)*K11 -> 0 | K11: 0 | L11: =IF(AND('Duchies Summary'!E11<=0,E11>0),1,0) -> 0 | M11: =H11*0.05 -> 0 | N11: =H11-M11 -> 0 | O11: {=K11+IF(L11=1,1,_xlfn.IFS(K11>0,-1,K11=0,0))} -> 0
A12: ='Duchies Summary'!A12 -> Lesserlands | B12: ='Ducal Economics'!B12 -> Sirong | C12: =IF(D12>0,D12-G12,0) -> 4000 | D12: 4000 | E12: =('Duchies Summary'!J12*0.005)-G12 -> 8390.62 | F12: =('Duchies Summary'!J12*0.005) -> 8390.62 | G12: =SUM(H12:J12) -> 0 | H12: 0 | J12: =(D12*0.02)*K12 -> 0 | K12: 0 | L12: =IF(AND('Duchies Summary'!E12<=0,E12>0),1,0) -> 0 | M12: =H12*0.05 -> 0 | N12: =H12-M12 -> 0 | O12: {=K12+IF(L12=1,1,_xlfn.IFS(K12>0,-1,K12=0,0))} -> 0
A13: ='Duchies Summary'!A13 -> ShadowWood | B13: ='Ducal Economics'!B13 -> Ralim | C13: =IF(D13>0,D13-G13,0) -> 1200 | D13: 1200 | E13: =('Duchies Summary'!J13*0.005)-G13 -> 10200.265 | F13: =('Duchies Summary'!J13*0.005) -> 10200.265 | G13: =SUM(H13:J13) -> 0 | H13: 0 | J13: =(D13*0.02)*K13 -> 0 | K13: 0 | L13: =IF(AND('Duchies Summary'!E13<=0,E13>0),1,0) -> 0 | M13: =H13*0.05 -> 0 | N13: =H13-M13 -> 0 | O13: {=K13+IF(L13=1,1,_xlfn.IFS(K13>0,-1,K13=0,0))} -> 0
A14: ='Duchies Summary'!A14 -> Mondwatch | B14: ='Ducal Economics'!B14 -> Ralim | C14: =IF(D14>0,D14-G14,0) -> 3405 | D14: 3405 | E14: =('Duchies Summary'!J14*0.005)-G14 -> 10519.215 | F14: =('Duchies Summary'!J14*0.005) -> 10519.215 | G14: =SUM(H14:J14) -> 0 | H14: 0 | J14: =(D14*0.02)*K14 -> 0 | K14: 0 | L14: =IF(AND('Duchies Summary'!E14<=0,E14>0),1,0) -> 0 | M14: =H14*0.05 -> 0 | N14: =H14-M14 -> 0 | O14: {=K14+IF(L14=1,1,_xlfn.IFS(K14>0,-1,K14=0,0))} -> 0
A15: ='Duchies Summary'!A15 -> Ratermarch | B15: ='Ducal Economics'!B15 -> Ralim | C15: =IF(D15>0,D15-G15,0) -> 4700 | D15: 4700 | E15: =('Duchies Summary'!J15*0.005)-G15 -> 10817.92 | F15: =('Duchies Summary'!J15*0.005) -> 10817.92 | G15: =SUM(H15:J15) -> 0 | H15: 0 | J15: =(D15*0.02)*K15 -> 0 | K15: 0 | L15: =IF(AND('Duchies Summary'!E15<=0,E15>0),1,0) -> 0 | M15: =H15*0.05 -> 0 | N15: =H15-M15 -> 0 | O15: {=K15+IF(L15=1,1,_xlfn.IFS(K15>0,-1,K15=0,0))} -> 0
A16: ='Duchies Summary'!A16 -> Vinh | B16: ='Ducal Economics'!B16 -> Crownlands | C16: =IF(D16>0,D16-G16,0) -> 5995 | D16: 5995 | E16: =('Duchies Summary'!J16*0.005)-G16 -> 5995.31 | F16: =('Duchies Summary'!J16*0.005) -> 5995.31 | G16: =SUM(H16:J16) -> 0 | H16: 0 | J16: =(D16*0.02)*K16 -> 0 | K16: 0 | L16: =IF(AND('Duchies Summary'!E16<=0,E16>0),1,0) -> 1 | M16: =H16*0.05 -> 0 | N16: =H16-M16 -> 0 | O16: {=K16+IF(L16=1,1,_xlfn.IFS(K16>0,-1,K16=0,0))} -> 1
... A20: ='Duchies Summary'!A20 -> Heartwell | B20: ='Ducal Economics'!B20 -> Crownlands | C20: =IF(D20>0,D20-G20,0) -> 1000 | D20: 1000 | E20: =('Duchies Summary'!J20*0.005)-G20 -> 1818.68 | F20: =('Duchies Summary'!J20*0.005) -> 1818.68 | G20: =SUM(H20:J20) -> 0 | H20: 0 | J20: =(D20*0.02)*K20 -> 0 | K20: 0 | L20: =IF(AND('Duchies Summary'!E20<=0,E20>0),1,0) -> 0 | M20: =H20*0.05 -> 0 | N20: =H20-M20 -> 0 | O20: {=K20+IF(L20=1,1,_xlfn.IFS(K20>0,-1,K20=0,0))} -> 0
A21: ='Duchies Summary'!A21 -> Pearlpass | B21: ='Ducal Economics'!B21 -> Dreghold | C21: =IF(D21>0,D21-G21,0) -> 0 | D21: 0 | E21: =('Duchies Summary'!J21*0.005)-G21 -> 5983.8196 | F21: =('Duchies Summary'!J21*0.005) -> 15997.87 | G21: =SUM(H21:J21) -> 10014.05 | H21: 6325.0504 | I21: 3689 | J21: =(D21*0.02)*K21 -> 0 | K21: 0 | L21: =IF(AND('Duchies Summary'!E21<=0,E21>0),1,0) -> 0 | M21: =H21*0.05 -> 316.25252 | N21: =H21-M21 -> 6008.7979 | O21: {=K21+IF(L21=1,1,_xlfn.IFS(K21>0,-1,K21=0,0))} -> 0
A22: ='Duchies Summary'!A22 -> Prince's Boot | B22: ='Ducal Economics'!B22 -> Dreghold | C22: =IF(D22>0,D22-G22,0) -> 0 | D22: 0 | E22: =('Duchies Summary'!J22*0.005)-G22 -> 7536.345 | F22: =('Duchies Summary'!J22*0.005) -> 7536.345 | G22: =SUM(H22:J22) -> 0 | H22: 0 | J22: =(D22*0.02)*K22 -> 0 | K22: 5 | L22: =IF(AND('Duchies Summary'!E22<=0,E22>0),1,0) -> 0 | M22: =H22*0.05 -> 0 | N22: =H22-M22 -> 0 | O22: {=K22+IF(L22=1,1,_xlfn.IFS(K22>0,-1,K22=0,0))} -> 4
A23: ='Duchies Summary'!A23 -> Swan's Reach | B23: ='Ducal Economics'!B23 -> Dreghold | C23: =IF(D23>0,D23-G23,0) -> 4300 | D23: 5000 | E23: =('Duchies Summary'!J23*0.005)-G23 -> 13430.295 | F23: =('Duchies Summary'!J23*0.005) -> 14130.295 | G23: =SUM(H23:J23) -> 700 | H23: 0 | J23: =(D23*0.02)*K23 -> 700 | K23: 7 | L23: =IF(AND('Duchies Summary'!E23<=0,E23>0),1,0) -> 1 | M23: =H23*0.05 -> 0 | N23: =H23-M23 -> 0 | O23: {=K23+IF(L23=1,1,_xlfn.IFS(K23>0,-1,K23=0,0))} -> 8
A24: ='Duchies Summary'!A24 -> Malhold | B24: ='Ducal Economics'!B24 -> Dreghold | C24: =IF(D24>0,D24-G24,0) -> 6974 | D24: 6974 | E24: =('Duchies Summary'!J24*0.005)-G24 -> 6974.45 | F24: =('Duchies Summary'!J24*0.005) -> 6974.45 | G24: =SUM(H24:J24) -> 0 | H24: 0 | J24: =(D24*0.02)*K24 -> 0 | K24: 0 | L24: =IF(AND('Duchies Summary'!E24<=0,E24>0),1,0) -> 0 | M24: =H24*0.05 -> 0 | N24: =H24-M24 -> 0 | O24: {=K24+IF(L24=1,1,_xlfn.IFS(K24>0,-1,K24=0,0))} -> 0
A25: ='Duchies Summary'!A25 -> Westleden | B25: ='Ducal Economics'!B25 -> Dreghold | C25: =IF(D25>0,D25-G25,0) -> 6600 | D25: 6600 | E25: =('Duchies Summary'!J25*0.005)-G25 -> 6616.39 | F25: =('Duchies Summary'!J25*0.005) -> 6616.39 | G25: =SUM(H25:J25) -> 0 | H25: 0 | J25: =(D25*0.02)*K25 -> 0 | K25: 0 | L25: =IF(AND('Duchies Summary'!E25<=0,E25>0),1,0) -> 1 | M25: =H25*0.05 -> 0 | N25: =H25-M25 -> 0 | O25: {=K25+IF(L25=1,1,_xlfn.IFS(K25>0,-1,K25=0,0))} -> 1
A26: ='Duchies Summary'!A26 -> Shurestar | B26: ='Ducal Economics'!B26 -> Dreghold | C26: =IF(D26>0,D26-G26,0) -> 5992 | D26: 5992 | E26: =('Duchies Summary'!J26*0.005)-G26 -> 5991.685 | F26: =('Duchies Summary'!J26*0.005) -> 5991.685 | G26: =SUM(H26:J26) -> 0 | H26: 0 | J26: =(D26*0.02)*K26 -> 0 | K26: 0 | L26: =IF(AND('Duchies Summary'!E26<=0,E26>0),1,0) -> 1 | M26: =H26*0.05 -> 0 | N26: =H26-M26 -> 0 | O26: {=K26+IF(L26=1,1,_xlfn.IFS(K26>0,-1,K26=0,0))} -> 1
A27: ='Duchies Summary'!A27 -> Raven's Reach | B27: ='Ducal Economics'!B27 -> Swanhall | C27: =IF(D27>0,D27-G27,0) -> 0 | D27: 0 | E27: =('Duchies Summary'!J27*0.005)-G27 -> 9441.42 | F27: =('Duchies Summary'!J27*0.005) -> 9441.42 | G27: =SUM(H27:J27) -> 0 | H27: 0 | J27: =(D27*0.02)*K27 -> 0 | K27: 0 | L27: =IF(AND('Duchies Summary'!E27<=0,E27>0),1,0) -> 0 | M27: =H27*0.05 -> 0 | N27: =H27-M27 -> 0 | O27: {=K27+IF(L27=1,1,_xlfn.IFS(K27>0,-1,K27=0,0))} -> 0
A28: ='Duchies Summary'!A28 -> Northfold | B28: ='Ducal Economics'!B28 -> Swanhall | C28: =IF(D28>0,D28-G28,0) -> 0 | D28: 0 | E28: =('Duchies Summary'!J28*0.005)-G28 -> 2241.84 | F28: =('Duchies Summary'!J28*0.005) -> 2241.84 | G28: =SUM(H28:J28) -> 0 | H28: 0 | J28: =(D28*0.02)*K28 -> 0 | K28: 0 | L28: =IF(AND('Duchies Summary'!E28<=0,E28>0),1,0) -> 0 | M28: =H28*0.05 -> 0 | N28: =H28-M28 -> 0 | O28: {=K28+IF(L28=1,1,_xlfn.IFS(K28>0,-1,K28=0,0))} -> 0
A29: ='Duchies Summary'!A29 -> Blackstone | B29: ='Ducal Economics'!B29 -> Swanhall | C29: =IF(D29>0,D29-G29,0) -> 0 | D29: 0 | E29: =('Duchies Summary'!J29*0.005)-G29 -> 10536.59 | F29: =('Duchies Summary'!J29*0.005) -> 10536.59 | G29: =SUM(H29:J29) -> 0 | H29: 0 | J29: =(D29*0.02)*K29 -> 0 | K29: 0 | L29: =IF(AND('Duchies Summary'!E29<=0,E29>0),1,0) -> 0 | M29: =H29*0.05 -> 0 | N29: =H29-M29 -> 0 | O29: {=K29+IF(L29=1,1,_xlfn.IFS(K29>0,-1,K29=0,0))} -> 0
A30: ='Duchies Summary'!A30 -> Ravenmark | B30: ='Ducal Economics'!B30 -> Swanhall | C30: =IF(D30>0,D30-G30,0) -> 0 | D30: 0 | E30: =('Duchies Summary'!J30*0.005)-G30 -> 4072.43 | F30: =('Duchies Summary'!J30*0.005) -> 4072.43 | G30: =SUM(H30:J30) -> 0 | H30: 0 | J30: =(D30*0.02)*K30 -> 0 | K30: 0 | L30: =IF(AND('Duchies Summary'!E30<=0,E30>0),1,0) -> 0 | M30: =H30*0.05 -> 0 | N30: =H30-M30 -> 0 | O30: {=K30+IF(L30=1,1,_xlfn.IFS(K30>0,-1,K30=0,0))} -> 0
A31: ='Duchies Summary'!A31 -> Wet Shoor | B31: ='Ducal Economics'!B31 -> Swanhall | C31: =IF(D31>0,D31-G31,0) -> 0 | D31: 0 | E31: =('Duchies Summary'!J31*0.005)-G31 -> 5632.955 | F31: =('Duchies Summary'!J31*0.005) -> 5632.955 | G31: =SUM(H31:J31) -> 0 | H31: 0 | J31: =(D31*0.02)*K31 -> 0 | K31: 0 | L31: =IF(AND('Duchies Summary'!E31<=0,E31>0),1,0) -> 0 | M31: =H31*0.05 -> 0 | N31: =H31-M31 -> 0 | O31: {=K31+IF(L31=1,1,_xlfn.IFS(K31>0,-1,K31=0,0))} -> 0
A32: ='Duchies Summary'!A32 -> Quickwatch | B32: ='Ducal Economics'!B32 -> Swanhall | C32: =IF(D32>0,D32-G32,0) -> 0 | D32: 0 | E32: =('Duchies Summary'!J32*0.005)-G32 -> 10582.89 | F32: =('Duchies Summary'!J32*0.005) -> 10582.89 | G32: =SUM(H32:J32) -> 0 | H32: 0 | J32: =(D32*0.02)*K32 -> 0 | K32: 0 | L32: =IF(AND('Duchies Summary'!E32<=0,E32>0),1,0) -> 0 | M32: =H32*0.05 -> 0 | N32: =H32-M32 -> 0 | O32: {=K32+IF(L32=1,1,_xlfn.IFS(K32>0,-1,K32=0,0))} -> 0
A33: ='Duchies Summary'!A33 -> The Deepwood | B33: ='Ducal Economics'!B33 -> Swanhall | C33: =IF(D33>0,D33-G33,0) -> 0 | D33: 0 | E33: =('Duchies Summary'!J33*0.005)-G33 -> 4292.14 | F33: =('Duchies Summary'!J33*0.005) -> 4292.14 | G33: =SUM(H33:J33) -> 0 | H33: 0 | J33: =(D33*0.02)*K33 -> 0 | K33: 0 | L33: =IF(AND('Duchies Summary'!E33<=0,E33>0),1,0) -> 0 | M33: =H33*0.05 -> 0 | N33: =H33-M33 -> 0 | O33: {=K33+IF(L33=1,1,_xlfn.IFS(K33>0,-1,K33=0,0))} -> 0
... A45: ='Duchies Summary'!A45 -> Briduan | B45: ='Ducal Economics'!B45 -> Madinglia | C45: =IF(D45>0,D45-G45,0) -> 0 | D45: 0 | E45: =('Duchies Summary'!J45*0.005)-G45 -> 1921.685 | F45: =('Duchies Summary'!J45*0.005) -> 1921.685 | G45: =SUM(H45:J45) -> 0 | H45: 0 | J45: =(D45*0.02)*K45 -> 0 | K45: 0 | L45: =IF(AND('Duchies Summary'!E45<=0,E45>0),1,0) -> 0 | M45: =H45*0.05 -> 0 | N45: =H45-M45 -> 0 | O45: {=K45+IF(L45=1,1,_xlfn.IFS(K45>0,-1,K45=0,0))} -> 0

Sheet Provincial Secret Sheet
A1: Crownlands | B1: 0 | C1: =SUM('Duchies Secret Sheet'!C$16:C$20) -> 25946 | D1: =C1 -> 25946 | E1: =SUM('Duchies Secret Sheet'!E$16:E$20) -> 31718.415 | F1: =SUM(G1:I1) -> 0 | G1: =SUM('Duchies Secret Sheet'!H$16:H$20) -> 0 | H1: =SUM('Duchies Secret Sheet'!I$16:I$20) -> 0 | I1: =SUM('Duchies Secret Sheet'!J$16:J$20) -> 0
A2: Dreghold | B2: 0 | C2: =SUM('Duchies Secret Sheet'!C$4,'Duchies Secret Sheet'!C20:C$26) -> 27554.641 | D2: =C2 -> 27554.641 | E2: =SUM('Duchies Secret Sheet'!E$4,'Duchies Secret Sheet'!E20:E$26) -> 51040.66 | F2: =SUM(G2:I2) -> 15783.41 | G2: =SUM('Duchies Secret Sheet'!H$4,'Duchies Secret Sheet'!H20:H$26) -> 8908.4096 | H2: =SUM('Duchies Secret Sheet'!I$4,'Duchies Secret Sheet'!I20:I$26) -> 6175 | I2: =SUM('Duchies Secret Sheet'!J$4,'Duchies Secret Sheet'!J20:J$26) -> 700
A3: Madinglia | B3: 0.25 | C3: =SUM('Duchies Secret Sheet'!C$41:C$45,'Duchies Secret Sheet'!C$3) -> 0 | D3: =C3 -> 0 | E3: =SUM('Duchies Secret Sheet'!E$41:E$45,'Duchies Secret Sheet'!E$3) -> 18735.285 | F3: =SUM(G3:I3) -> 0 | G3: =SUM('Duchies Secret Sheet'!H$41:H$45,'Duchies Secret Sheet'!H$3) -> 0 | H3: =SUM('Duchies Secret Sheet'!I$41:I$45,'Duchies Secret Sheet'!I$3) -> 0 | I3: =SUM('Duchies Secret Sheet'!J$41:J$45,'Duchies Secret Sheet'!J$3) -> 0
A4: Ralim | B4: 0.25 | C4: =SUM('Duchies Secret Sheet'!C$6,'Duchies Secret Sheet'!C$13:C$15) -> 15833 | D4: =C4 -> 15833 | E4: =SUM('Duchies Secret Sheet'!E$6,'Duchies Secret Sheet'!E$13:E$15) -> 38065.035 | F4: =SUM(G4:I4) -> 0 | G4: =SUM('Duchies Secret Sheet'!H$6,'Duchies Secret Sheet'!H$13:H$15) -> 0 | H4: =SUM('Duchies Secret Sheet'!I$6,'Duchies Secret Sheet'!I$13:I$15) -> 0 | I4: =SUM('Duchies Secret Sheet'!J$6,'Duchies Secret Sheet'!J$13:J$15) -> 0
A5: Sirong | B5: 0.25 | C5: =SUM('Duchies Secret Sheet'!C$5,'Duchies Secret Sheet'!C$7:C$12) -> 41000 | D5: =C5 -> 41000 | E5: =SUM('Duchies Secret Sheet'!E$5,'Duchies Secret Sheet'!E$7:E$12) -> 79877.905 | F5: =SUM(G5:I5) -> 0 | G5: =SUM('Duchies Secret Sheet'!H$5,'Duchies Secret Sheet'!H$7:H$12) -> 0 | H5: =SUM('Duchies Secret Sheet'!I$5,'Duchies Secret Sheet'!I$7:I$12) -> 0 | I5: =SUM('Duchies Secret Sheet'!J$5,'Duchies Secret Sheet'!J$7:J$12) -> 0
A6: Swanhall | B6: 0 | C6: =SUM('Duchies Secret Sheet'!C$2,'Duchies Secret Sheet'!C$27:C$40) -> 21849.36 | D6: =C6 -> 21849.36 | E6: =SUM('Duchies Secret Sheet'!E$2,'Duchies Secret Sheet'!E$27:E$40) -> 83562.375 | F6: =SUM(G6:I6) -> 1540.6401 | G6: =SUM('Duchies Secret Sheet'!H$2,'Duchies Secret Sheet'!H$27:H$40) -> 686.64015 | H6: =SUM('Duchies Secret Sheet'!I$2,'Duchies Secret Sheet'!I$27:I$40) -> 854 | I6: =SUM('Duchies Secret Sheet'!J$2,'Duchies Secret Sheet'!J$27:J$40) -> 0
B7: Province Tax Rates | C7: Raised Levies | D7: True Raised | E7: True Possible Levies | F7: Casualties | G7: Injured | H7: Dead | I7: Deserted

Sheet Household Guard Breakdown
A1: House | B1: Count | C1: Quality | D1: Budget | E1: Pay Per Guards | F1: Houshold Members | G1: Guards Per Household Member
A2: Princeps | B2: 50 | C2: =IFERROR(__xludf.DUMMYFUNCTION("TO_TEXT((E2/50)*10)&(TO_TEXT(""/10""))"),"8/10") -> 8/10 | D2: 2000 | E2: =D2/B2 -> 40 | F2: 3 | G2: =B2/F2 -> 16.666667
A3: Mereks | B3: 50 | C3: =IFERROR(__xludf.DUMMYFUNCTION("TO_TEXT((E3/50)*10)&(TO_TEXT(""/10""))"),"8/10") -> 8/10 | D3: 2000 | E3: =D3/B3 -> 40 | F3: 3 | G3: =B3/F3 -> 16.666667
A4: Hearstons | B4: 50 | C4: =IFERROR(__xludf.DUMMYFUNCTION("TO_TEXT((E4/50)*10)&(TO_TEXT(""/10""))"),"8/10") -> 8/10 | D4: 2000 | E4: =D4/B4 -> 40 | F4: 6 | G4: =B4/F4 -> 8.3333333
A5: Carthen | B5: 50 | C5: =IFERROR(__xludf.DUMMYFUNCTION("TO_TEXT((E5/50)*10)&(TO_TEXT(""/10""))"),"8/10") -> 8/10 | D5: 2000 | E5: =D5/B5 -> 40 | F5: 5 | G5: =B5/F5 -> 10
A6: Kontherns | B6: 50 | C6: =IFERROR(__xludf.DUMMYFUNCTION("TO_TEXT((E6/50)*10)&(TO_TEXT(""/10""))"),"8/10") -> 8/10 | D6: 2000 | E6: =D6/B6 -> 40 | F6: 3 | G6: =B6/F6 -> 16.666667

Sheet New Cities
A1: Duchy | B1: Summative Profit (Per Duchy) | C1: Tax Income | D1: City | E1: Culture | F1: Religion | G1: Population | H1: {='New Cities Filter'!Q1:W166} -> Capital | I1: Port | J1: Citadel | K1: Walls | L1: Plaza | M1: Temple | N1: Shanty Town | O1: Road | P1: Tax Rate from Buildings | Q1: Total Tax Rate | R1: City Guard | S1: City Guard Surplus | T1: City Guard Casualties
A2: ='New Cities Filter'!C2 -> Amber Shores | B2: =SUM(C2:C5) -> 371.79167 | C2: {=Q2*('Price Sheet (Ignore)'!$H$2+_xlfn.IFS(O2="dirt",0.15,O2="gravel",0.3,O2="paved",0.4,O2="none",0))*(G2/3)} -> 41.3 | D2: ='New Cities Filter'!B:B -> Belldedagon | E2: {='New Cities Filter'!G2:G166} -> Central Shavian | F2: {='New Cities Filter'!H2:H166} -> Path of Guiding Light | G2: {='New Cities Filter'!I2:I166} -> 1652 | O2: none | P2: =IF(H2="capital",0.1)+IF(I2="port",0.1)+IF(J2="citadel",0.05)+IF(K2="walls",-0.07)+IF(L2="plaza",0.05)+IF(M2="temple",0.01)+IF(N2="shanty town",0.05) -> 0 | Q2: =IF(P2>0.25,P2,P2+'Price Sheet (Ignore)'!$G$2) -> 0.15 | R2: =((G2*0.012)+IF(G2*0.012<100,100))+(S2-T2) -> 119.824
A3: ='New Cities Filter'!C3 -> Amber Shores | C3: {=Q3*('Price Sheet (Ignore)'!$H$2+_xlfn.IFS(O3="dirt",0.15,O3="gravel",0.3,O3="paved",0.4,O3="none",0))*(G3/3)} -> 172.91667 | D3: ='New Cities Filter'!B:B -> Cryspide | E3: Central Shavian | F3: Path of Guiding Light | G3: 4150 | J3: citadel | L3: plaza | O3: none | P3: =IF(H3="capital",0.1)+IF(I3="port",0.1)+IF(J3="citadel",0.05)+IF(K3="walls",-0.07)+IF(L3="plaza",0.05)+IF(M3="temple",0.01)+IF(N3="shanty town",0.05) -> 0.1 | Q3: =IF(P3>0.25,P3,P3+'Price Sheet (Ignore)'!$G$2) -> 0.25 | R3: =((G3*0.012)+IF(G3*0.012<100,100))+(S3-T3) -> 149.8
A4: ='New Cities Filter'!C4 -> Amber Shores | C4: {=Q4*('Price Sheet (Ignore)'!$H$2+_xlfn.IFS(O4="dirt",0.15,O4="gravel",0.3,O4="paved",0.4,O4="none",0))*(G4/3)} -> 108.55 | D4: ='New Cities Filter'!B:B -> Amber Waters | E4: Central Shavian | F4: Path of Guiding Light | G4: 2171 | I4: port | J4: citadel | O4: none | P4: =IF(H4="capital",0.1)+IF(I4="port",0.1)+IF(J4="citadel",0.05)+IF(K4="walls",-0.07)+IF(L4="plaza",0.05)+IF(M4="temple",0.01)+IF(N4="shanty town",0.05) -> 0.15 | Q4: =IF(P4>0.25,P4,P4+'Price Sheet (Ignore)'!$G$2) -> 0.3 | R4: =((G4*0.012)+IF(G4*0.012<100,100))+(S4-T4) -> 126.052
A5: ='New Cities Filter'!C5 -> Amber Shores | C5: {=Q5*('Price Sheet (Ignore)'!$H$2+_xlfn.IFS(O5="dirt",0.15,O5="gravel",0.3,O5="paved",0.4,O5="none",0))*(G5/3)} -> 49.025 | D5: ='New Cities Filter'!B:B -> Snavenbell | E5: Central Shavian | F5: Path of Guiding Light | G5: 1961 | O5: none | P5: =IF(H5="capital",0.1)+IF(I5="port",0.1)+IF(J5="citadel",0.05)+IF(K5="walls",-0.07)+IF(L5="plaza",0.05)+IF(M5="temple",0.01)+IF(N5="shanty town",0.05) -> 0 | Q5: =IF(P5>0.25,P5,P5+'Price Sheet (Ignore)'!$G$2) -> 0.15 | R5: =((G5*0.012)+IF(G5*0.012<100,100))+(S5-T5) -> 123.532
A6: ='New Cities Filter'!C6 -> Blackstone | B6: =SUM(C6:C8) -> 2335.295 | C6: {=Q6*('Price Sheet (Ignore)'!$H$2+_xlfn.IFS(O6="dirt",0.15,O6="gravel",0.3,O6="paved",0.4,O6="none",0))*(G6/3)} -> 1316.9917 | D6: ='New Cities Filter'!B:B -> Blackstone | E6: Eastern Shavian | F6: Path of Guiding Light | G6: 22577 | I6: port | J6: citadel | L6: plaza | O6: none | P6: =IF(H6="capital",0.1)+IF(I6="port",0.1)+IF(J6="citadel",0.05)+IF(K6="walls",-0.07)+IF(L6="plaza",0.05)+IF(M6="temple",0.01)+IF(N6="shanty town",0.05) -> 0.2 | Q6: =IF(P6>0.25,P6,P6+'Price Sheet (Ignore)'!$G$2) -> 0.35 | R6: =((G6*0.012)+IF(G6*0.012<100,100))+(S6-T6) -> 270.924
A7: ='New Cities Filter'!C7 -> Blackstone | C7: {=Q7*('Price Sheet (Ignore)'!$H$2+_xlfn.IFS(O7="dirt",0.15,O7="gravel",0.3,O7="paved",0.4,O7="none",0))*(G7/3)} -> 591.16667 | D7: ='New Cities Filter'!B:B -> Anhelm | E7: Eastern Shavian | F7: Path of Guiding Light | G7: 14188 | J7: citadel | L7: plaza | O7: none | P7: =IF(H7="capital",0.1)+IF(I7="port",0.1)+IF(J7="citadel",0.05)+IF(K7="walls",-0.07)+IF(L7="plaza",0.05)+IF(M7="temple",0.01)+IF(N7="shanty town",0.05) -> 0.1 | Q7: =IF(P7>0.25,P7,P7+'Price Sheet (Ignore)'!$G$2) -> 0.25 | R7: =((G7*0.012)+IF(G7*0.012<100,100))+(S7-T7) -> 170.256
A8: ='New Cities Filter'!C8 -> Blackstone | C8: {=Q8*('Price Sheet (Ignore)'!$H$2+_xlfn.IFS(O8="dirt",0.15,O8="gravel",0.3,O8="paved",0.4,O8="none",0))*(G8/3)} -> 427.13667 | D8: ='New Cities Filter'!B:B -> Sprinkeep | E8: Eastern Shavian | F8: Path of Guiding Light | G8: 19714 | K8: walls | L8: plaza | O8: none | P8: =IF(H8="capital",0.1)+IF(I8="port",0.1)+IF(J8="citadel",0.05)+IF(K8="walls",-0.07)+IF(L8="plaza",0.05)+IF(M8="temple",0.01)+IF(N8="shanty town",0.05) -> -0.02 | Q8: =IF(P8>0.25,P8,P8+'Price Sheet (Ignore)'!$G$2) -> 0.13 | R8: =((G8*0.012)+IF(G8*0.012<100,100))+(S8-T8) -> 236.568
A9: ='New Cities Filter'!C9 -> Briduan | B9: =SUM(C9) -> 46.675 | C9: {=Q9*('Price Sheet (Ignore)'!$H$2+_xlfn.IFS(O9="dirt",0.15,O9="gravel",0.3,O9="paved",0.4,O9="none",0))*(G9/3)} -> 46.675 | D9: ='New Cities Filter'!B:B -> Brid | E9: Madinglian | F9: Children of Stone | G9: 1867 | O9: none | P9: =IF(H9="capital",0.1)+IF(I9="port",0.1)+IF(J9="citadel",0.05)+IF(K9="walls",-0.07)+IF(L9="plaza",0.05)+IF(M9="temple",0.01)+IF(N9="shanty town",0.05) -> 0 | Q9: =IF(P9>0.25,P9,P9+'Price Sheet (Ignore)'!$G$2) -> 0.15 | R9: =((G9*0.012)+IF(G9*0.012<100,100))+(S9-T9) -> 122.404
A10: ='New Cities Filter'!C10 -> Brookward | B10: =SUM(C10:C12) -> 3750.5167 | C10: {=Q10*('Price Sheet (Ignore)'!$H$2+_xlfn.IFS(O10="dirt",0.15,O10="gravel",0.3,O10="paved",0.4,O10="none",0))*(G10/3)} -> 63.166667 | D10: ='New Cities Filter'!B:B -> Direlight | E10: Ralimers | F10: Path of Guiding Light | G10: 1895 | J10: citadel | O10: none | P10: =IF(H10="capital",0.1)+IF(I10="port",0.1)+IF(J10="citadel",0.05)+IF(K10="walls",-0.07)+IF(L10="plaza",0.05)+IF(M10="temple",0.01)+IF(N10="shanty town",0.05) -> 0.05 | Q10: =IF(P10>0.25,P10,P10+'Price Sheet (Ignore)'!$G$2) -> 0.2 | R10: =((G10*0.012)+IF(G10*0.012<100,100))+(S10-T10) -> 122.74
A11: ='New Cities Filter'!C11 -> Brookward | C11: {=Q11*('Price Sheet (Ignore)'!$H$2+_xlfn.IFS(O11="dirt",0.15,O11="gravel",0.3,O11="paved",0.4,O11="none",0))*(G11/3)} -> 549.25 | D11: ='New Cities Filter'!B:B -> Heartle | E11: Ralimers | F11: Path of Guiding Light | G11: 25350 | K11: walls | L11: plaza | O11: none | P11: =IF(H11="capital",0.1)+IF(I11="port",0.1)+IF(J11="citadel",0.05)+IF(K11="walls",-0.07)+IF(L11="plaza",0.05)+IF(M11="temple",0.01)+IF(N11="shanty town",0.05) -> -0.02 | Q11: =IF(P11>0.25,P11,P11+'Price Sheet (Ignore)'!$G$2) -> 0.13 | R11: =((G11*0.012)+IF(G11*0.012<100,100))+(S11-T11) -> 304.2
A12: ='New Cities Filter'!C12 -> Brookward | C12: {=Q12*('Price Sheet (Ignore)'!$H$2+_xlfn.IFS(O12="dirt",0.15,O12="gravel",0.3,O12="paved",0.4,O12="none",0))*(G12/3)} -> 3138.1 | D12: ='New Cities Filter'!B:B -> Brookward | E12: Ralimers | F12: Path of Guiding Light | G12: 53796 | I12: port | J12: citadel | L12: plaza | O12: none | P12: =IF(H12="capital",0.1)+IF(I12="port",0.1)+IF(J12="citadel",0.05)+IF(K12="walls",-0.07)+IF(L12="plaza",0.05)+IF(M12="temple",0.01)+IF(N12="shanty town",0.05) -> 0.2 | Q12: =IF(P12>0.25,P12,P12+'Price Sheet (Ignore)'!$G$2) -> 0.35 | R12: =((G12*0.012)+IF(G12*0.012<100,100))+(S12-T12) -> 645.552
A13: ='New Cities Filter'!C13 -> Dreghold | B13: =SUM(C13:C18) -> 3925.4283 | C13: {=Q13*('Price Sheet (Ignore)'!$H$2+_xlfn.IFS(O13="dirt",0.15,O13="gravel",0.3,O13="paved",0.4,O13="none",0))*(G13/3)} -> 255.32 | D13: ='New Cities Filter'!B:B -> Nehalle | E13: Baymen | F13: Path of Guiding Light | G13: 11784 | J13: citadel | K13: walls | O13: none | P13: =IF(H13="capital",0.1)+IF(I13="port",0.1)+IF(J13="citadel",0.05)+IF(K13="walls",-0.07)+IF(L13="plaza",0.05)+IF(M13="temple",0.01)+IF(N13="shanty town",0.05) -> -0.02 | Q13: =IF(P13>0.25,P13,P13+'Price Sheet (Ignore)'!$G$2) -> 0.13 | R13: =((G13*0.012)+IF(G13*0.012<100,100))+(S13-T13) -> 141.408
A14: ='New Cities Filter'!C14 -> Dreghold | C14: {=Q14*('Price Sheet (Ignore)'!$H$2+_xlfn.IFS(O14="dirt",0.15,O14="gravel",0.3,O14="paved",0.4,O14="none",0))*(G14/3)} -> 1868.7083 | D14: ='New Cities Filter'!B:B -> Dreghold | E14: Baymen | F14: Path of Guiding Light | G14: 32035 | I14: port | J14: citadel | L14: plaza | O14: none | P14: =IF(H14="capital",0.1)+IF(I14="port",0.1)+IF(J14="citadel",0.05)+IF(K14="walls",-0.07)+IF(L14="plaza",0.05)+IF(M14="temple",0.01)+IF(N14="shanty town",0.05) -> 0.2 | Q14: =IF(P14>0.25,P14,P14+'Price Sheet (Ignore)'!$G$2) -> 0.35 | R14: =((G14*0.012)+IF(G14*0.012<100,100))+(S14-T14) -> 384.42
A15: ='New Cities Filter'!C15 -> Dreghold | C15: {=Q15*('Price Sheet (Ignore)'!$H$2+_xlfn.IFS(O15="dirt",0.15,O15="gravel",0.3,O15="paved",0.4,O15="none",0))*(G15/3)} -> 44.975 | D15: ='New Cities Filter'!B:B -> Clearse | E15: Baymen | F15: Path of Guiding Light | G15: 1799 | O15: none | P15: =IF(H15="capital",0.1)+IF(I15="port",0.1)+IF(J15="citadel",0.05)+IF(K15="walls",-0.07)+IF(L15="plaza",0.05)+IF(M15="temple",0.01)+IF(N15="shanty town",0.05) -> 0 | Q15: =IF(P15>0.25,P15,P15+'Price Sheet (Ignore)'!$G$2) -> 0.15 | R15: =((G15*0.012)+IF(G15*0.012<100,100))+(S15-T15) -> 121.588
A16: ='New Cities Filter'!C16 -> Dreghold | C16: {=Q16*('Price Sheet (Ignore)'!$H$2+_xlfn.IFS(O16="dirt",0.15,O16="gravel",0.3,O16="paved",0.4,O16="none",0))*(G16/3)} -> 1278.685 | D16: ='New Cities Filter'!B:B -> Eagrasp | E16: Baymen | F16: Path of Guiding Light | G16: 33357 | J16: citadel | K16: walls | L16: plaza | N16: shanty town | O16: none | P16: =IF(H16="capital",0.1)+IF(I16="port",0.1)+IF(J16="citadel",0.05)+IF(K16="walls",-0.07)+IF(L16="plaza",0.05)+IF(M16="temple",0.01)+IF(N16="shanty town",0.05) -> 0.08 | Q16: =IF(P16>0.25,P16,P16+'Price Sheet (Ignore)'!$G$2) -> 0.23 | R16: =((G16*0.012)+IF(G16*0.012<100,100))+(S16-T16) -> 400.284
A17: ='New Cities Filter'!C17 -> Dreghold | C17: {=Q17*('Price Sheet (Ignore)'!$H$2+_xlfn.IFS(O17="dirt",0.15,O17="gravel",0.3,O17="paved",0.4,O17="none",0))*(G17/3)} -> 419.315 | D17: ='New Cities Filter'!B:B -> Curcairn | E17: Baymen | F17: Path of Guiding Light | G17: 19353 | J17: citadel | K17: walls | O17: none | P17: =IF(H17="capital",0.1)+IF(I17="port",0.1)+IF(J17="citadel",0.05)+IF(K17="walls",-0.07)+IF(L17="plaza",0.05)+IF(M17="temple",0.01)+IF(N17="shanty town",0.05) -> -0.02 | Q17: =IF(P17>0.25,P17,P17+'Price Sheet (Ignore)'!$G$2) -> 0.13 | R17: =((G17*0.012)+IF(G17*0.012<100,100))+(S17-T17) -> 232.236
A18: ='New Cities Filter'!C18 -> Dreghold | C18: {=Q18*('Price Sheet (Ignore)'!$H$2+_xlfn.IFS(O18="dirt",0.15,O18="gravel",0.3,O18="paved",0.4,O18="none",0))*(G18/3)} -> 58.425 | D18: ='New Cities Filter'!B:B -> Grirevein | E18: Baymen | F18: Path of Guiding Light | G18: 2337 | O18: none | P18: =IF(H18="capital",0.1)+IF(I18="port",0.1)+IF(J18="citadel",0.05)+IF(K18="walls",-0.07)+IF(L18="plaza",0.05)+IF(M18="temple",0.01)+IF(N18="shanty town",0.05) -> 0 | Q18: =IF(P18>0.25,P18,P18+'Price Sheet (Ignore)'!$G$2) -> 0.15 | R18: =((G18*0.012)+IF(G18*0.012<100,100))+(S18-T18) -> 128.044
A19: ='New Cities Filter'!C19 -> Dregsten Bay | B19: =SUM(C19:C24) -> 2613.6683 | C19: {=Q19*('Price Sheet (Ignore)'!$H$2+_xlfn.IFS(O19="dirt",0.15,O19="gravel",0.3,O19="paved",0.4,O19="none",0))*(G19/3)} -> 164.61667 | D19: ='New Cities Filter'!B:B -> Goldbrook | E19: Baymen | F19: Path of Guiding Light | G19: 2822 | I19: port | J19: citadel | L19: plaza | O19: none | P19: =IF(H19="capital",0.1)+IF(I19="port",0.1)+IF(J19="citadel",0.05)+IF(K19="walls",-0.07)+IF(L19="plaza",0.05)+IF(M19="temple",0.01)+IF(N19="shanty town",0.05) -> 0.2 | Q19: =IF(P19>0.25,P19,P19+'Price Sheet (Ignore)'!$G$2) -> 0.35 | R19: =((G19*0.012)+IF(G19*0.012<100,100))+(S19-T19) -> 133.864
A20: ='New Cities Filter'!C20 -> Dregsten Bay | C20: {=Q20*('Price Sheet (Ignore)'!$H$2+_xlfn.IFS(O20="dirt",0.15,O20="gravel",0.3,O20="paved",0.4,O20="none",0))*(G20/3)} -> 25.4 | D20: ='New Cities Filter'!B:B -> Wolfpasstar | E20: Central Shavian | F20: Path of Guiding Light | G20: 1905 | K20: walls | O20: none | P20: =IF(H20="capital",0.1)+IF(I20="port",0.1)+IF(J20="citadel",0.05)+IF(K20="walls",-0.07)+IF(L20="plaza",0.05)+IF(M20="temple",0.01)+IF(N20="shanty town",0.05) -> -0.07 | Q20: =IF(P20>0.25,P20,P20+'Price Sheet (Ignore)'!$G$2) -> 0.08 | R20: =((G20*0.012)+IF(G20*0.012<100,100))+(S20-T20) -> 122.86
A21: ='New Cities Filter'!C21 -> Dregsten Bay | C21: {=Q21*('Price Sheet (Ignore)'!$H$2+_xlfn.IFS(O21="dirt",0.15,O21="gravel",0.3,O21="paved",0.4,O21="none",0))*(G21/3)} -> 88.375 | D21: ='New Cities Filter'!B:B -> Southtligh | E21: Central Shavian | F21: Path of Guiding Light | G21: 2121 | J21: citadel | L21: plaza | O21: none | P21: =IF(H21="capital",0.1)+IF(I21="port",0.1)+IF(J21="citadel",0.05)+IF(K21="walls",-0.07)+IF(L21="plaza",0.05)+IF(M21="temple",0.01)+IF(N21="shanty town",0.05) -> 0.1 | Q21: =IF(P21>0.25,P21,P21+'Price Sheet (Ignore)'!$G$2) -> 0.25 | R21: =((G21*0.012)+IF(G21*0.012<100,100))+(S21-T21) -> 125.452
A22: ='New Cities Filter'!C22 -> Dregsten Bay | C22: {=Q22*('Price Sheet (Ignore)'!$H$2+_xlfn.IFS(O22="dirt",0.15,O22="gravel",0.3,O22="paved",0.4,O22="none",0))*(G22/3)} -> 483.46667 | D22: ='New Cities Filter'!B:B -> Mondhol | E22: Central Shavian | F22: Path of Guiding Light | G22: 14504 | J22: citadel | O22: none | P22: =IF(H22="capital",0.1)+IF(I22="port",0.1)+IF(J22="citadel",0.05)+IF(K22="walls",-0.07)+IF(L22="plaza",0.05)+IF(M22="temple",0.01)+IF(N22="shanty town",0.05) -> 0.05 | Q22: =IF(P22>0.25,P22,P22+'Price Sheet (Ignore)'!$G$2) -> 0.2 | R22: =((G22*0.012)+IF(G22*0.012<100,100))+(S22-T22) -> 174.048
A23: ='New Cities Filter'!C23 -> Dregsten Bay | C23: {=Q23*('Price Sheet (Ignore)'!$H$2+_xlfn.IFS(O23="dirt",0.15,O23="gravel",0.3,O23="paved",0.4,O23="none",0))*(G23/3)} -> 260.15 | D23: ='New Cities Filter'!B:B -> Shimhand | E23: Central Shavian | F23: Path of Guiding Light | G23: 10406 | O23: none | P23: =IF(H23="capital",0.1)+IF(I23="port",0.1)+IF(J23="citadel",0.05)+IF(K23="walls",-0.07)+IF(L23="plaza",0.05)+IF(M23="temple",0.01)+IF(N23="shanty town",0.05) -> 0 | Q23: =IF(P23>0.25,P23,P23+'Price Sheet (Ignore)'!$G$2) -> 0.15 | R23: =((G23*0.012)+IF(G23*0.012<100,100))+(S23-T23) -> 124.872
A24: ='New Cities Filter'!C24 -> Dregsten Bay | C24: {=Q24*('Price Sheet (Ignore)'!$H$2+_xlfn.IFS(O24="dirt",0.15,O24="gravel",0.3,O24="paved",0.4,O24="none",0))*(G24/3)} -> 1591.66 | D24: ='New Cities Filter'!B:B -> Dryvaterga | E24: Baymen | F24: Path of Guiding Light | G24: 34107 | I24: port | K24: walls | L24: plaza | N24: shanty town | O24: none | P24: =IF(H24="capital",0.1)+IF(I24="port",0.1)+IF(J24="citadel",0.05)+IF(K24="walls",-0.07)+IF(L24="plaza",0.05)+IF(M24="temple",0.01)+IF(N24="shanty town",0.05) -> 0.13 | Q24: =IF(P24>0.25,P24,P24+'Price Sheet (Ignore)'!$G$2) -> 0.28 | R24: =((G24*0.012)+IF(G24*0.012<100,100))+(S24-T24) -> 409.284
A25: ='New Cities Filter'!C25 -> Drelme | B25: =SUM(C25:C28) -> 1165.53 | C25: {=Q25*('Price Sheet (Ignore)'!$H$2+_xlfn.IFS(O25="dirt",0.15,O25="gravel",0.3,O25="paved",0.4,O25="none",0))*(G25/3)} -> 239.48167 | D25: ='New Cities Filter'!B:B -> Drelme | E25: Ralimers | F25: Path of Guiding Light | G25: 11053 | K25: walls | L25: plaza | O25: none | P25: =IF(H25="capital",0.1)+IF(I25="port",0.1)+IF(J25="citadel",0.05)+IF(K25="walls",-0.07)+IF(L25="plaza",0.05)+IF(M25="temple",0.01)+IF(N25="shanty town",0.05) -> -0.02 | Q25: =IF(P25>0.25,P25,P25+'Price Sheet (Ignore)'!$G$2) -> 0.13 | R25: =((G25*0.012)+IF(G25*0.012<100,100))+(S25-T25) -> 132.636
A26: ='New Cities Filter'!C26 -> Drelme | C26: {=Q26*('Price Sheet (Ignore)'!$H$2+_xlfn.IFS(O26="dirt",0.15,O26="gravel",0.3,O26="paved",0.4,O26="none",0))*(G26/3)} -> 481.375 | D26: ='New Cities Filter'!B:B -> Dawnsites | E26: Central Shavian | F26: Path of Guiding Light | G26: 11553 | I26: port | O26: none | P26: =IF(H26="capital",0.1)+IF(I26="port",0.1)+IF(J26="citadel",0.05)+IF(K26="walls",-0.07)+IF(L26="plaza",0.05)+IF(M26="temple",0.01)+IF(N26="shanty town",0.05) -> 0.1 | Q26: =IF(P26>0.25,P26,P26+'Price Sheet (Ignore)'!$G$2) -> 0.25 | R26: =((G26*0.012)+IF(G26*0.012<100,100))+(S26-T26) -> 138.636
A27: ='New Cities Filter'!C27 -> Drelme | C27: {=Q27*('Price Sheet (Ignore)'!$H$2+_xlfn.IFS(O27="dirt",0.15,O27="gravel",0.3,O27="paved",0.4,O27="none",0))*(G27/3)} -> 42.423333 | D27: ='New Cities Filter'!B:B -> Metagith | E27: Ralimers | F27: Path of Guiding Light | G27: 1958 | K27: walls | L27: plaza | O27: none | P27: =IF(H27="capital",0.1)+IF(I27="port",0.1)+IF(J27="citadel",0.05)+IF(K27="walls",-0.07)+IF(L27="plaza",0.05)+IF(M27="temple",0.01)+IF(N27="shanty town",0.05) -> -0.02 | Q27: =IF(P27>0.25,P27,P27+'Price Sheet (Ignore)'!$G$2) -> 0.13 | R27: =((G27*0.012)+IF(G27*0.012<100,100))+(S27-T27) -> 123.496
A28: ='New Cities Filter'!C28 -> Drelme | C28: {=Q28*('Price Sheet (Ignore)'!$H$2+_xlfn.IFS(O28="dirt",0.15,O28="gravel",0.3,O28="paved",0.4,O28="none",0))*(G28/3)} -> 402.25 | D28: ='New Cities Filter'!B:B -> Vojhamenz | E28: Ralimers | F28: Path of Guiding Light | G28: 9654 | I28: port | O28: none | P28: =IF(H28="capital",0.1)+IF(I28="port",0.1)+IF(J28="citadel",0.05)+IF(K28="walls",-0.07)+IF(L28="plaza",0.05)+IF(M28="temple",0.01)+IF(N28="shanty town",0.05) -> 0.1 | Q28: =IF(P28>0.25,P28,P28+'Price Sheet (Ignore)'!$G$2) -> 0.25 | R28: =((G28*0.012)+IF(G28*0.012<100,100))+(S28-T28) -> 115.848
A29: ='New Cities Filter'!C29 -> Eguard | B29: =SUM(C29:C30) -> 1651.175 | C29: {=Q29*('Price Sheet (Ignore)'!$H$2+_xlfn.IFS(O29="dirt",0.15,O29="gravel",0.3,O29="paved",0.4,O29="none",0))*(G29/3)} -> 147.76667 | D29: ='New Cities Filter'!B:B -> Mudband | E29: Swanmen | F29: Path of Guiding Light | G29: 4433 | J29: citadel | O29: none | P29: =IF(H29="capital",0.1)+IF(I29="port",0.1)+IF(J29="citadel",0.05)+IF(K29="walls",-0.07)+IF(L29="plaza",0.05)+IF(M29="temple",0.01)+IF(N29="shanty town",0.05) -> 0.05 | Q29: =IF(P29>0.25,P29,P29+'Price Sheet (Ignore)'!$G$2) -> 0.2 | R29: =((G29*0.012)+IF(G29*0.012<100,100))+(S29-T29) -> 153.196
A30: ='New Cities Filter'!C30 -> Eguard | C30: {=Q30*('Price Sheet (Ignore)'!$H$2+_xlfn.IFS(O30="dirt",0.15,O30="gravel",0.3,O30="paved",0.4,O30="none",0))*(G30/3)} -> 1503.4083 | D30: ='New Cities Filter'!B:B -> Eguard | E30: Swanmen | F30: Path of Guiding Light | G30: 31105 | I30: port | K30: walls | L30: plaza | M30: temple | N30: shanty town | O30: none | P30: =IF(H30="capital",0.1)+IF(I30="port",0.1)+IF(J30="citadel",0.05)+IF(K30="walls",-0.07)+IF(L30="plaza",0.05)+IF(M30="temple",0.01)+IF(N30="shanty town",0.05) -> 0.14 | Q30: =IF(P30>0.25,P30,P30+'Price Sheet (Ignore)'!$G$2) -> 0.29 | R30: =((G30*0.012)+IF(G30*0.012<100,100))+(S30-T30) -> 373.26
A31: ='New Cities Filter'!C31 -> Elreach | B31: =SUM(C31:C33) -> 1061.2033 | C31: {=Q31*('Price Sheet (Ignore)'!$H$2+_xlfn.IFS(O31="dirt",0.15,O31="gravel",0.3,O31="paved",0.4,O31="none",0))*(G31/3)} -> 345.93333 | D31: ='New Cities Filter'!B:B -> Elreach | E31: Swanmen | F31: Path of Guiding Light | G31: 10378 | J31: citadel | O31: none | P31: =IF(H31="capital",0.1)+IF(I31="port",0.1)+IF(J31="citadel",0.05)+IF(K31="walls",-0.07)+IF(L31="plaza",0.05)+IF(M31="temple",0.01)+IF(N31="shanty town",0.05) -> 0.05 | Q31: =IF(P31>0.25,P31,P31+'Price Sheet (Ignore)'!$G$2) -> 0.2 | R31: =((G31*0.012)+IF(G31*0.012<100,100))+(S31-T31) -> 124.536
A32: ='New Cities Filter'!C32 -> Elreach | C32: {=Q32*('Price Sheet (Ignore)'!$H$2+_xlfn.IFS(O32="dirt",0.15,O32="gravel",0.3,O32="paved",0.4,O32="none",0))*(G32/3)} -> 586.495 | D32: ='New Cities Filter'!B:B -> Clifpass | E32: Swanmen | F32: Path of Guiding Light | G32: 27069 | K32: walls | L32: plaza | O32: none | P32: =IF(H32="capital",0.1)+IF(I32="port",0.1)+IF(J32="citadel",0.05)+IF(K32="walls",-0.07)+IF(L32="plaza",0.05)+IF(M32="temple",0.01)+IF(N32="shanty town",0.05) -> -0.02 | Q32: =IF(P32>0.25,P32,P32+'Price Sheet (Ignore)'!$G$2) -> 0.13 | R32: =((G32*0.012)+IF(G32*0.012<100,100))+(S32-T32) -> 324.828
A33: ='New Cities Filter'!C33 -> Elreach | C33: {=Q33*('Price Sheet (Ignore)'!$H$2+_xlfn.IFS(O33="dirt",0.15,O33="gravel",0.3,O33="paved",0.4,O33="none",0))*(G33/3)} -> 128.775 | D33: ='New Cities Filter'!B:B -> Edenhelmer | E33: Swanmen | F33: Path of Guiding Light | G33: 5151 | O33: none | P33: =IF(H33="capital",0.1)+IF(I33="port",0.1)+IF(J33="citadel",0.05)+IF(K33="walls",-0.07)+IF(L33="plaza",0.05)+IF(M33="temple",0.01)+IF(N33="shanty town",0.05) -> 0 | Q33: =IF(P33>0.25,P33,P33+'Price Sheet (Ignore)'!$G$2) -> 0.15 | R33: =((G33*0.012)+IF(G33*0.012<100,100))+(S33-T33) -> 161.812
A34: ='New Cities Filter'!C34 -> Griffin's Bay | B34: =SUM(C34:C44) -> 3612.0867 | C34: {=Q34*('Price Sheet (Ignore)'!$H$2+_xlfn.IFS(O34="dirt",0.15,O34="gravel",0.3,O34="paved",0.4,O34="none",0))*(G34/3)} -> 212.675 | D34: ='New Cities Filter'!B:B -> Barondrith | E34: Westerling | F34: Path of Guiding Light | G34: 8507 | O34: none | P34: =IF(H34="capital",0.1)+IF(I34="port",0.1)+IF(J34="citadel",0.05)+IF(K34="walls",-0.07)+IF(L34="plaza",0.05)+IF(M34="temple",0.01)+IF(N34="shanty town",0.05) -> 0 | Q34: =IF(P34>0.25,P34,P34+'Price Sheet (Ignore)'!$G$2) -> 0.15 | R34: =((G34*0.012)+IF(G34*0.012<100,100))+(S34-T34) -> 102.084
A35: ='New Cities Filter'!C35 -> Griffin's Bay | C35: {=Q35*('Price Sheet (Ignore)'!$H$2+_xlfn.IFS(O35="dirt",0.15,O35="gravel",0.3,O35="paved",0.4,O35="none",0))*(G35/3)} -> 976.08 | D35: ='New Cities Filter'!B:B -> Retha | E35: Westerling | F35: Path of Guiding Light | G35: 32536 | J35: citadel | K35: walls | L35: plaza | O35: none | P35: =IF(H35="capital",0.1)+IF(I35="port",0.1)+IF(J35="citadel",0.05)+IF(K35="walls",-0.07)+IF(L35="plaza",0.05)+IF(M35="temple",0.01)+IF(N35="shanty town",0.05) -> 0.03 | Q35: =IF(P35>0.25,P35,P35+'Price Sheet (Ignore)'!$G$2) -> 0.18 | R35: =((G35*0.012)+IF(G35*0.012<100,100))+(S35-T35) -> 390.432
A36: ='New Cities Filter'!C36 -> Griffin's Bay | C36: {=Q36*('Price Sheet (Ignore)'!$H$2+_xlfn.IFS(O36="dirt",0.15,O36="gravel",0.3,O36="paved",0.4,O36="none",0))*(G36/3)} -> 808.89333 | D36: ='New Cities Filter'!B:B -> Jaallugausthei | E36: Westerling | F36: Path of Guiding Light | G36: 25544 | J36: citadel | K36: walls | M36: temple | N36: shanty town | O36: none | P36: =IF(H36="capital",0.1)+IF(I36="port",0.1)+IF(J36="citadel",0.05)+IF(K36="walls",-0.07)+IF(L36="plaza",0.05)+IF(M36="temple",0.01)+IF(N36="shanty town",0.05) -> 0.04 | Q36: =IF(P36>0.25,P36,P36+'Price Sheet (Ignore)'!$G$2) -> 0.19 | R36: =((G36*0.012)+IF(G36*0.012<100,100))+(S36-T36) -> 306.528
A37: ='New Cities Filter'!C37 -> Griffin's Bay | C37: {=Q37*('Price Sheet (Ignore)'!$H$2+_xlfn.IFS(O37="dirt",0.15,O37="gravel",0.3,O37="paved",0.4,O37="none",0))*(G37/3)} -> 719.775 | D37: ='New Cities Filter'!B:B -> Eldhembenlean | E37: Golden Men | F37: Path of Guiding Light | G37: 12339 | I37: port | J37: citadel | L37: plaza | O37: none | P37: =IF(H37="capital",0.1)+IF(I37="port",0.1)+IF(J37="citadel",0.05)+IF(K37="walls",-0.07)+IF(L37="plaza",0.05)+IF(M37="temple",0.01)+IF(N37="shanty town",0.05) -> 0.2 | Q37: =IF(P37>0.25,P37,P37+'Price Sheet (Ignore)'!$G$2) -> 0.35 | R37: =((G37*0.012)+IF(G37*0.012<100,100))+(S37-T37) -> 148.068
A38: ='New Cities Filter'!C38 -> Griffin's Bay | C38: {=Q38*('Price Sheet (Ignore)'!$H$2+_xlfn.IFS(O38="dirt",0.15,O38="gravel",0.3,O38="paved",0.4,O38="none",0))*(G38/3)} -> 81.416667 | D38: ='New Cities Filter'!B:B -> Houndwell | E38: Central Shavian | F38: Path of Guiding Light | G38: 1954 | J38: citadel | L38: plaza | O38: none | P38: =IF(H38="capital",0.1)+IF(I38="port",0.1)+IF(J38="citadel",0.05)+IF(K38="walls",-0.07)+IF(L38="plaza",0.05)+IF(M38="temple",0.01)+IF(N38="shanty town",0.05) -> 0.1 | Q38: =IF(P38>0.25,P38,P38+'Price Sheet (Ignore)'!$G$2) -> 0.25 | R38: =((G38*0.012)+IF(G38*0.012<100,100))+(S38-T38) -> 123.448
A39: ='New Cities Filter'!C39 -> Griffin's Bay | C39: {=Q39*('Price Sheet (Ignore)'!$H$2+_xlfn.IFS(O39="dirt",0.15,O39="gravel",0.3,O39="paved",0.4,O39="none",0))*(G39/3)} -> 66.32 | D39: ='New Cities Filter'!B:B -> Chaunzandyn | E39: Westerling | F39: Path of Guiding Light | G39: 4974 | K39: walls | O39: none | P39: =IF(H39="capital",0.1)+IF(I39="port",0.1)+IF(J39="citadel",0.05)+IF(K39="walls",-0.07)+IF(L39="plaza",0.05)+IF(M39="temple",0.01)+IF(N39="shanty town",0.05) -> -0.07 | Q39: =IF(P39>0.25,P39,P39+'Price Sheet (Ignore)'!$G$2) -> 0.08 | R39: =((G39*0.012)+IF(G39*0.012<100,100))+(S39-T39) -> 159.688
A40: ='New Cities Filter'!C40 -> Griffin's Bay | C40: {=Q40*('Price Sheet (Ignore)'!$H$2+_xlfn.IFS(O40="dirt",0.15,O40="gravel",0.3,O40="paved",0.4,O40="none",0))*(G40/3)} -> 235.68 | D40: ='New Cities Filter'!B:B -> Dewgronac | E40: Westerling | F40: Path of Guiding Light | G40: 17676 | K40: walls | O40: none | P40: =IF(H40="capital",0.1)+IF(I40="port",0.1)+IF(J40="citadel",0.05)+IF(K40="walls",-0.07)+IF(L40="plaza",0.05)+IF(M40="temple",0.01)+IF(N40="shanty town",0.05) -> -0.07 | Q40: =IF(P40>0.25,P40,P40+'Price Sheet (Ignore)'!$G$2) -> 0.08 | R40: =((G40*0.012)+IF(G40*0.012<100,100))+(S40-T40) -> 212.112
A41: ='New Cities Filter'!C41 -> Griffin's Bay | C41: {=Q41*('Price Sheet (Ignore)'!$H$2+_xlfn.IFS(O41="dirt",0.15,O41="gravel",0.3,O41="paved",0.4,O41="none",0))*(G41/3)} -> 73.033333 | D41: ='New Cities Filter'!B:B -> Vidanntyr | E41: Westerling | F41: Path of Guiding Light | G41: 2191 | J41: citadel | O41: none | P41: =IF(H41="capital",0.1)+IF(I41="port",0.1)+IF(J41="citadel",0.05)+IF(K41="walls",-0.07)+IF(L41="plaza",0.05)+IF(M41="temple",0.01)+IF(N41="shanty town",0.05) -> 0.05 | Q41: =IF(P41>0.25,P41,P41+'Price Sheet (Ignore)'!$G$2) -> 0.2 | R41: =((G41*0.012)+IF(G41*0.012<100,100))+(S41-T41) -> 126.292
A42: ='New Cities Filter'!C42 -> Griffin's Bay | C42: {=Q42*('Price Sheet (Ignore)'!$H$2+_xlfn.IFS(O42="dirt",0.15,O42="gravel",0.3,O42="paved",0.4,O42="none",0))*(G42/3)} -> 65.7 | D42: ='New Cities Filter'!B:B -> Shaven | E42: Westerling | F42: Path of Guiding Light | G42: 1971 | J42: citadel | O42: none | P42: =IF(H42="capital",0.1)+IF(I42="port",0.1)+IF(J42="citadel",0.05)+IF(K42="walls",-0.07)+IF(L42="plaza",0.05)+IF(M42="temple",0.01)+IF(N42="shanty town",0.05) -> 0.05 | Q42: =IF(P42>0.25,P42,P42+'Price Sheet (Ignore)'!$G$2) -> 0.2 | R42: =((G42*0.012)+IF(G42*0.012<100,100))+(S42-T42) -> 123.652
A43: ='New Cities Filter'!C43 -> Griffin's Bay | C43: {=Q43*('Price Sheet (Ignore)'!$H$2+_xlfn.IFS(O43="dirt",0.15,O43="gravel",0.3,O43="paved",0.4,O43="none",0))*(G43/3)} -> 186.78333 | D43: ='New Cities Filter'!B:B -> Ulport | E43: Westerling | F43: Path of Guiding Light | G43: 3202 | I43: port | J43: citadel | L43: plaza | O43: none | P43: =IF(H43="capital",0.1)+IF(I43="port",0.1)+IF(J43="citadel",0.05)+IF(K43="walls",-0.07)+IF(L43="plaza",0.05)+IF(M43="temple",0.01)+IF(N43="shanty town",0.05) -> 0.2 | Q43: =IF(P43>0.25,P43,P43+'Price Sheet (Ignore)'!$G$2) -> 0.35 | R43: =((G43*0.012)+IF(G43*0.012<100,100))+(S43-T43) -> 138.424
A44: ='New Cities Filter'!C44 -> Griffin's Bay | C44: {=Q44*('Price Sheet (Ignore)'!$H$2+_xlfn.IFS(O44="dirt",0.15,O44="gravel",0.3,O44="paved",0.4,O44="none",0))*(G44/3)} -> 185.73 | D44: ='New Cities Filter'!B:B -> Dregrefrant | E44: Westerling | F44: Path of Guiding Light | G44: 6191 | J44: citadel | K44: walls | L44: plaza | O44: none | P44: =IF(H44="capital",0.1)+IF(I44="port",0.1)+IF(J44="citadel",0.05)+IF(K44="walls",-0.07)+IF(L44="plaza",0.05)+IF(M44="temple",0.01)+IF(N44="shanty town",0.05) -> 0.03 | Q44: =IF(P44>0.25,P44,P44+'Price Sheet (Ignore)'!$G$2) -> 0.18 | R44: =((G44*0.012)+IF(G44*0.012<100,100))+(S44-T44) -> 174.292
A45: ='New Cities Filter'!C45 -> Heartwell | B45: =SUM(C45) -> 4838.6017 | C45: {=Q45*('Price Sheet (Ignore)'!$H$2+_xlfn.IFS(O45="dirt",0.15,O45="gravel",0.3,O45="paved",0.4,O45="none",0))*(G45/3)} -> 4838.6017 | D45: ='New Cities Filter'!B:B -> Heartwell | E45: Central Shavian | F45: Path of Guiding Light | G45: 100109 | H45: capital | I45: port | J45: citadel | K45: walls | L45: plaza | M45: temple | N45: shanty town | O45: none | P45: =IF(H45="capital",0.1)+IF(I45="port",0.1)+IF(J45="citadel",0.05)+IF(K45="walls",-0.07)+IF(L45="plaza",0.05)+IF(M45="temple",0.01)+IF(N45="shanty town",0.05) -> 0.29 | Q45: =IF(P45>0.25,P45,P45+'Price Sheet (Ignore)'!$G$2) -> 0.29 | R45: =((G45*0.012)+IF(G45*0.012<100,100))+(S45-T45) -> 1201.308
A46: ='New Cities Filter'!C46 -> Lesserlands | B46: =SUM(C46:C49) -> 955.34167 | C46: {=Q46*('Price Sheet (Ignore)'!$H$2+_xlfn.IFS(O46="dirt",0.15,O46="gravel",0.3,O46="paved",0.4,O46="none",0))*(G46/3)} -> 108.575 | D46: ='New Cities Filter'!B:B -> Sirongrasp | E46: Westerling | F46: Path of Guiding Light | G46: 4343 | O46: none | P46: =IF(H46="capital",0.1)+IF(I46="port",0.1)+IF(J46="citadel",0.05)+IF(K46="walls",-0.07)+IF(L46="plaza",0.05)+IF(M46="temple",0.01)+IF(N46="shanty town",0.05) -> 0 | Q46: =IF(P46>0.25,P46,P46+'Price Sheet (Ignore)'!$G$2) -> 0.15 | R46: =((G46*0.012)+IF(G46*0.012<100,100))+(S46-T46) -> 152.116
A47: ='New Cities Filter'!C47 -> Lesserlands | C47: {=Q47*('Price Sheet (Ignore)'!$H$2+_xlfn.IFS(O47="dirt",0.15,O47="gravel",0.3,O47="paved",0.4,O47="none",0))*(G47/3)} -> 140.53333 | D47: ='New Cities Filter'!B:B -> Eldefones | E47: Central Shavian | F47: Path of Guiding Light | G47: 4216 | J47: citadel | O47: none | P47: =IF(H47="capital",0.1)+IF(I47="port",0.1)+IF(J47="citadel",0.05)+IF(K47="walls",-0.07)+IF(L47="plaza",0.05)+IF(M47="temple",0.01)+IF(N47="shanty town",0.05) -> 0.05 | Q47: =IF(P47>0.25,P47,P47+'Price Sheet (Ignore)'!$G$2) -> 0.2 | R47: =((G47*0.012)+IF(G47*0.012<100,100))+(S47-T47) -> 150.592
A48: ='New Cities Filter'!C48 -> Lesserlands | C48: {=Q48*('Price Sheet (Ignore)'!$H$2+_xlfn.IFS(O48="dirt",0.15,O48="gravel",0.3,O48="paved",0.4,O48="none",0))*(G48/3)} -> 622.43333 | D48: ='New Cities Filter'!B:B -> Casthclif | E48: Central Shavian | F48: Path of Guiding Light | G48: 18673 | J48: citadel | O48: none | P48: =IF(H48="capital",0.1)+IF(I48="port",0.1)+IF(J48="citadel",0.05)+IF(K48="walls",-0.07)+IF(L48="plaza",0.05)+IF(M48="temple",0.01)+IF(N48="shanty town",0.05) -> 0.05 | Q48: =IF(P48>0.25,P48,P48+'Price Sheet (Ignore)'!$G$2) -> 0.2 | R48: =((G48*0.012)+IF(G48*0.012<100,100))+(S48-T48) -> 224.076
A49: ='New Cities Filter'!C49 -> Lesserlands | C49: {=Q49*('Price Sheet (Ignore)'!$H$2+_xlfn.IFS(O49="dirt",0.15,O49="gravel",0.3,O49="paved",0.4,O49="none",0))*(G49/3)} -> 83.8 | D49: ='New Cities Filter'!B:B -> Saltvaven | E49: Central Shavian | F49: Path of Guiding Light | G49: 2514 | J49: citadel | O49: none | P49: =IF(H49="capital",0.1)+IF(I49="port",0.1)+IF(J49="citadel",0.05)+IF(K49="walls",-0.07)+IF(L49="plaza",0.05)+IF(M49="temple",0.01)+IF(N49="shanty town",0.05) -> 0.05 | Q49: =IF(P49>0.25,P49,P49+'Price Sheet (Ignore)'!$G$2) -> 0.2 | R49: =((G49*0.012)+IF(G49*0.012<100,100))+(S49-T49) -> 130.168
A50: ='New Cities Filter'!C50 -> Lonely Light | B50: =SUM(C50) -> 288.53333 | C50: {=Q50*('Price Sheet (Ignore)'!$H$2+_xlfn.IFS(O50="dirt",0.15,O50="gravel",0.3,O50="paved",0.4,O50="none",0))*(G50/3)} -> 288.53333 | D50: ='New Cities Filter'!B:B -> Lonely Light | E50: Dail | F50: Path of Guiding Light | G50: 8656 | J50: citadel | O50: none | P50: =IF(H50="capital",0.1)+IF(I50="port",0.1)+IF(J50="citadel",0.05)+IF(K50="walls",-0.07)+IF(L50="plaza",0.05)+IF(M50="temple",0.01)+IF(N50="shanty town",0.05) -> 0.05 | Q50: =IF(P50>0.25,P50,P50+'Price Sheet (Ignore)'!$G$2) -> 0.2 | R50: =((G50*0.012)+IF(G50*0.012<100,100))+(S50-T50) -> 103.872
A51: ='New Cities Filter'!C51 -> Malhold | B51: =SUM(C51:C59) -> 2118.2167 | C51: {=Q51*('Price Sheet (Ignore)'!$H$2+_xlfn.IFS(O51="dirt",0.15,O51="gravel",0.3,O51="paved",0.4,O51="none",0))*(G51/3)} -> 230.53333 | D51: ='New Cities Filter'!B:B -> Timbergro | E51: Eastern Shavian | F51: Path of Guiding Light | G51: 6916 | J51: citadel | O51: none | P51: =IF(H51="capital",0.1)+IF(I51="port",0.1)+IF(J51="citadel",0.05)+IF(K51="walls",-0.07)+IF(L51="plaza",0.05)+IF(M51="temple",0.01)+IF(N51="shanty town",0.05) -> 0.05 | Q51: =IF(P51>0.25,P51,P51+'Price Sheet (Ignore)'!$G$2) -> 0.2 | R51: =((G51*0.012)+IF(G51*0.012<100,100))+(S51-T51) -> 182.992
A52: ='New Cities Filter'!C52 -> Malhold | C52: {=Q52*('Price Sheet (Ignore)'!$H$2+_xlfn.IFS(O52="dirt",0.15,O52="gravel",0.3,O52="paved",0.4,O52="none",0))*(G52/3)} -> 91.666667 | D52: ='New Cities Filter'!B:B -> Drakefair | E52: Eastern Shavian | F52: Path of Guiding Light | G52: 2200 | J52: citadel | L52: plaza | O52: none | P52: =IF(H52="capital",0.1)+IF(I52="port",0.1)+IF(J52="citadel",0.05)+IF(K52="walls",-0.07)+IF(L52="plaza",0.05)+IF(M52="temple",0.01)+IF(N52="shanty town",0.05) -> 0.1 | Q52: =IF(P52>0.25,P52,P52+'Price Sheet (Ignore)'!$G$2) -> 0.25 | R52: =((G52*0.012)+IF(G52*0.012<100,100))+(S52-T52) -> 126.4
A53: ='New Cities Filter'!C53 -> Malhold | C53: {=Q53*('Price Sheet (Ignore)'!$H$2+_xlfn.IFS(O53="dirt",0.15,O53="gravel",0.3,O53="paved",0.4,O53="none",0))*(G53/3)} -> 348.915 | D53: ='New Cities Filter'!B:B -> Pondhol | E53: Eastern Shavian | F53: Path of Guiding Light | G53: 23261 | K53: walls | M53: temple | O53: none | P53: =IF(H53="capital",0.1)+IF(I53="port",0.1)+IF(J53="citadel",0.05)+IF(K53="walls",-0.07)+IF(L53="plaza",0.05)+IF(M53="temple",0.01)+IF(N53="shanty town",0.05) -> -0.06 | Q53: =IF(P53>0.25,P53,P53+'Price Sheet (Ignore)'!$G$2) -> 0.09 | R53: =((G53*0.012)+IF(G53*0.012<100,100))+(S53-T53) -> 279.132
A54: ='New Cities Filter'!C54 -> Malhold | C54: {=Q54*('Price Sheet (Ignore)'!$H$2+_xlfn.IFS(O54="dirt",0.15,O54="gravel",0.3,O54="paved",0.4,O54="none",0))*(G54/3)} -> 495.925 | D54: ='New Cities Filter'!B:B -> Brittvault | E54: Eastern Shavian | F54: Path of Guiding Light | G54: 19837 | O54: none | P54: =IF(H54="capital",0.1)+IF(I54="port",0.1)+IF(J54="citadel",0.05)+IF(K54="walls",-0.07)+IF(L54="plaza",0.05)+IF(M54="temple",0.01)+IF(N54="shanty town",0.05) -> 0 | Q54: =IF(P54>0.25,P54,P54+'Price Sheet (Ignore)'!$G$2) -> 0.15 | R54: =((G54*0.012)+IF(G54*0.012<100,100))+(S54-T54) -> 238.044
A55: ='New Cities Filter'!C55 -> Malhold | C55: {=Q55*('Price Sheet (Ignore)'!$H$2+_xlfn.IFS(O55="dirt",0.15,O55="gravel",0.3,O55="paved",0.4,O55="none",0))*(G55/3)} -> 64.366667 | D55: ='New Cities Filter'!B:B -> Bearowbay | E55: Eastern Shavian | F55: Path of Guiding Light | G55: 1931 | J55: citadel | O55: none | P55: =IF(H55="capital",0.1)+IF(I55="port",0.1)+IF(J55="citadel",0.05)+IF(K55="walls",-0.07)+IF(L55="plaza",0.05)+IF(M55="temple",0.01)+IF(N55="shanty town",0.05) -> 0.05 | Q55: =IF(P55>0.25,P55,P55+'Price Sheet (Ignore)'!$G$2) -> 0.2 | R55: =((G55*0.012)+IF(G55*0.012<100,100))+(S55-T55) -> 123.172
A56: ='New Cities Filter'!C56 -> Malhold | C56: {=Q56*('Price Sheet (Ignore)'!$H$2+_xlfn.IFS(O56="dirt",0.15,O56="gravel",0.3,O56="paved",0.4,O56="none",0))*(G56/3)} -> 89.166667 | D56: ='New Cities Filter'!B:B -> Malhold | E56: Baymen | F56: Path of Guiding Light | G56: 2675 | J56: citadel | O56: none | P56: =IF(H56="capital",0.1)+IF(I56="port",0.1)+IF(J56="citadel",0.05)+IF(K56="walls",-0.07)+IF(L56="plaza",0.05)+IF(M56="temple",0.01)+IF(N56="shanty town",0.05) -> 0.05 | Q56: =IF(P56>0.25,P56,P56+'Price Sheet (Ignore)'!$G$2) -> 0.2 | R56: =((G56*0.012)+IF(G56*0.012<100,100))+(S56-T56) -> 132.1
A57: ='New Cities Filter'!C57 -> Malhold | C57: {=Q57*('Price Sheet (Ignore)'!$H$2+_xlfn.IFS(O57="dirt",0.15,O57="gravel",0.3,O57="paved",0.4,O57="none",0))*(G57/3)} -> 53.85 | D57: ='New Cities Filter'!B:B -> Sunrun | E57: Eastern Shavian | F57: Path of Guiding Light | G57: 2154 | O57: none | P57: =IF(H57="capital",0.1)+IF(I57="port",0.1)+IF(J57="citadel",0.05)+IF(K57="walls",-0.07)+IF(L57="plaza",0.05)+IF(M57="temple",0.01)+IF(N57="shanty town",0.05) -> 0 | Q57: =IF(P57>0.25,P57,P57+'Price Sheet (Ignore)'!$G$2) -> 0.15 | R57: =((G57*0.012)+IF(G57*0.012<100,100))+(S57-T57) -> 125.848
A58: ='New Cities Filter'!C58 -> Malhold | C58: {=Q58*('Price Sheet (Ignore)'!$H$2+_xlfn.IFS(O58="dirt",0.15,O58="gravel",0.3,O58="paved",0.4,O58="none",0))*(G58/3)} -> 507.59333 | D58: ='New Cities Filter'!B:B -> Brimegcoast | E58: Eastern Shavian | F58: Path of Guiding Light | G58: 21754 | J58: citadel | K58: walls | M58: temple | O58: none | P58: =IF(H58="capital",0.1)+IF(I58="port",0.1)+IF(J58="citadel",0.05)+IF(K58="walls",-0.07)+IF(L58="plaza",0.05)+IF(M58="temple",0.01)+IF(N58="shanty town",0.05) -> -0.01 | Q58: =IF(P58>0.25,P58,P58+'Price Sheet (Ignore)'!$G$2) -> 0.14 | R58: =((G58*0.012)+IF(G58*0.012<100,100))+(S58-T58) -> 261.048
A59: ='New Cities Filter'!C59 -> Malhold | C59: {=Q59*('Price Sheet (Ignore)'!$H$2+_xlfn.IFS(O59="dirt",0.15,O59="gravel",0.3,O59="paved",0.4,O59="none",0))*(G59/3)} -> 236.2 | D59: ='New Cities Filter'!B:B -> Oatercoast | E59: Eastern Shavian | F59: Path of Guiding Light | G59: 9448 | O59: none | P59: =IF(H59="capital",0.1)+IF(I59="port",0.1)+IF(J59="citadel",0.05)+IF(K59="walls",-0.07)+IF(L59="plaza",0.05)+IF(M59="temple",0.01)+IF(N59="shanty town",0.05) -> 0 | Q59: =IF(P59>0.25,P59,P59+'Price Sheet (Ignore)'!$G$2) -> 0.15 | R59: =((G59*0.012)+IF(G59*0.012<100,100))+(S59-T59) -> 113.376
A60: ='New Cities Filter'!C60 -> Mightfall | B60: =SUM(C60:C64) -> 1040.6667 | C60: {=Q60*('Price Sheet (Ignore)'!$H$2+_xlfn.IFS(O60="dirt",0.15,O60="gravel",0.3,O60="paved",0.4,O60="none",0))*(G60/3)} -> 62.5 | D60: ='New Cities Filter'!B:B -> Drayvakec | E60: Swanmen | F60: Path of Guiding Light | G60: 1875 | L60: plaza | O60: none | P60: =IF(H60="capital",0.1)+IF(I60="port",0.1)+IF(J60="citadel",0.05)+IF(K60="walls",-0.07)+IF(L60="plaza",0.05)+IF(M60="temple",0.01)+IF(N60="shanty town",0.05) -> 0.05 | Q60: =IF(P60>0.25,P60,P60+'Price Sheet (Ignore)'!$G$2) -> 0.2 | R60: =((G60*0.012)+IF(G60*0.012<100,100))+(S60-T60) -> 122.5
A61: ='New Cities Filter'!C61 -> Mightfall | C61: {=Q61*('Price Sheet (Ignore)'!$H$2+_xlfn.IFS(O61="dirt",0.15,O61="gravel",0.3,O61="paved",0.4,O61="none",0))*(G61/3)} -> 411.13333 | D61: ='New Cities Filter'!B:B -> Dewbaymond | E61: Swanmen | F61: Path of Guiding Light | G61: 12334 | J61: citadel | O61: none | P61: =IF(H61="capital",0.1)+IF(I61="port",0.1)+IF(J61="citadel",0.05)+IF(K61="walls",-0.07)+IF(L61="plaza",0.05)+IF(M61="temple",0.01)+IF(N61="shanty town",0.05) -> 0.05 | Q61: =IF(P61>0.25,P61,P61+'Price Sheet (Ignore)'!$G$2) -> 0.2 | R61: =((G61*0.012)+IF(G61*0.012<100,100))+(S61-T61) -> 148.008
A62: ='New Cities Filter'!C62 -> Mightfall | C62: {=Q62*('Price Sheet (Ignore)'!$H$2+_xlfn.IFS(O62="dirt",0.15,O62="gravel",0.3,O62="paved",0.4,O62="none",0))*(G62/3)} -> 65.813333 | D62: ='New Cities Filter'!B:B -> Mudfpasstal | E62: Swanmen | F62: Path of Guiding Light | G62: 4936 | K62: walls | O62: none | P62: =IF(H62="capital",0.1)+IF(I62="port",0.1)+IF(J62="citadel",0.05)+IF(K62="walls",-0.07)+IF(L62="plaza",0.05)+IF(M62="temple",0.01)+IF(N62="shanty town",0.05) -> -0.07 | Q62: =IF(P62>0.25,P62,P62+'Price Sheet (Ignore)'!$G$2) -> 0.08 | R62: =((G62*0.012)+IF(G62*0.012<100,100))+(S62-T62) -> 159.232
A63: ='New Cities Filter'!C63 -> Mightfall | C63: {=Q63*('Price Sheet (Ignore)'!$H$2+_xlfn.IFS(O63="dirt",0.15,O63="gravel",0.3,O63="paved",0.4,O63="none",0))*(G63/3)} -> 322.48667 | D63: ='New Cities Filter'!B:B -> Smallverne | E63: Swanmen | F63: Path of Guiding Light | G63: 14884 | J63: citadel | K63: walls | O63: none | P63: =IF(H63="capital",0.1)+IF(I63="port",0.1)+IF(J63="citadel",0.05)+IF(K63="walls",-0.07)+IF(L63="plaza",0.05)+IF(M63="temple",0.01)+IF(N63="shanty town",0.05) -> -0.02 | Q63: =IF(P63>0.25,P63,P63+'Price Sheet (Ignore)'!$G$2) -> 0.13 | R63: =((G63*0.012)+IF(G63*0.012<100,100))+(S63-T63) -> 178.608
A64: ='New Cities Filter'!C64 -> Mightfall | C64: {=Q64*('Price Sheet (Ignore)'!$H$2+_xlfn.IFS(O64="dirt",0.15,O64="gravel",0.3,O64="paved",0.4,O64="none",0))*(G64/3)} -> 178.73333 | D64: ='New Cities Filter'!B:B -> Mightfall | E64: Swanmen | F64: Path of Guiding Light | G64: 5362 | J64: citadel | O64: none | P64: =IF(H64="capital",0.1)+IF(I64="port",0.1)+IF(J64="citadel",0.05)+IF(K64="walls",-0.07)+IF(L64="plaza",0.05)+IF(M64="temple",0.01)+IF(N64="shanty town",0.05) -> 0.05 | Q64: =IF(P64>0.25,P64,P64+'Price Sheet (Ignore)'!$G$2) -> 0.2 | R64: =((G64*0.012)+IF(G64*0.012<100,100))+(S64-T64) -> 164.344
A65: ='New Cities Filter'!C65 -> Mightkeep | B65: =SUM(C65:C74) -> 2855.2283 | C65: {=Q65*('Price Sheet (Ignore)'!$H$2+_xlfn.IFS(O65="dirt",0.15,O65="gravel",0.3,O65="paved",0.4,O65="none",0))*(G65/3)} -> 553.36667 | D65: ='New Cities Filter'!B:B -> Whitegulf | E65: Swanmen | F65: Path of Guiding Light | G65: 16601 | J65: citadel | O65: none | P65: =IF(H65="capital",0.1)+IF(I65="port",0.1)+IF(J65="citadel",0.05)+IF(K65="walls",-0.07)+IF(L65="plaza",0.05)+IF(M65="temple",0.01)+IF(N65="shanty town",0.05) -> 0.05 | Q65: =IF(P65>0.25,P65,P65+'Price Sheet (Ignore)'!$G$2) -> 0.2 | R65: =((G65*0.012)+IF(G65*0.012<100,100))+(S65-T65) -> 199.212
A66: ='New Cities Filter'!C66 -> Mightkeep | C66: {=Q66*('Price Sheet (Ignore)'!$H$2+_xlfn.IFS(O66="dirt",0.15,O66="gravel",0.3,O66="paved",0.4,O66="none",0))*(G66/3)} -> 43.175 | D66: ='New Cities Filter'!B:B -> Stagrasp | E66: Swanmen | F66: Path of Guiding Light | G66: 1727 | O66: none | P66: =IF(H66="capital",0.1)+IF(I66="port",0.1)+IF(J66="citadel",0.05)+IF(K66="walls",-0.07)+IF(L66="plaza",0.05)+IF(M66="temple",0.01)+IF(N66="shanty town",0.05) -> 0 | Q66: =IF(P66>0.25,P66,P66+'Price Sheet (Ignore)'!$G$2) -> 0.15 | R66: =((G66*0.012)+IF(G66*0.012<100,100))+(S66-T66) -> 120.724
A67: ='New Cities Filter'!C67 -> Mightkeep | C67: {=Q67*('Price Sheet (Ignore)'!$H$2+_xlfn.IFS(O67="dirt",0.15,O67="gravel",0.3,O67="paved",0.4,O67="none",0))*(G67/3)} -> 318.46667 | D67: ='New Cities Filter'!B:B -> Moonpasshi | E67: Swanmen | F67: Path of Guiding Light | G67: 9554 | L67: plaza | O67: none | P67: =IF(H67="capital",0.1)+IF(I67="port",0.1)+IF(J67="citadel",0.05)+IF(K67="walls",-0.07)+IF(L67="plaza",0.05)+IF(M67="temple",0.01)+IF(N67="shanty town",0.05) -> 0.05 | Q67: =IF(P67>0.25,P67,P67+'Price Sheet (Ignore)'!$G$2) -> 0.2 | R67: =((G67*0.012)+IF(G67*0.012<100,100))+(S67-T67) -> 114.648
A68: ='New Cities Filter'!C68 -> Mightkeep | C68: {=Q68*('Price Sheet (Ignore)'!$H$2+_xlfn.IFS(O68="dirt",0.15,O68="gravel",0.3,O68="paved",0.4,O68="none",0))*(G68/3)} -> 150.33333 | D68: ='New Cities Filter'!B:B -> Wingmire | E68: Swanmen | F68: Path of Guiding Light | G68: 3608 | J68: citadel | L68: plaza | O68: none | P68: =IF(H68="capital",0.1)+IF(I68="port",0.1)+IF(J68="citadel",0.05)+IF(K68="walls",-0.07)+IF(L68="plaza",0.05)+IF(M68="temple",0.01)+IF(N68="shanty town",0.05) -> 0.1 | Q68: =IF(P68>0.25,P68,P68+'Price Sheet (Ignore)'!$G$2) -> 0.25 | R68: =((G68*0.012)+IF(G68*0.012<100,100))+(S68-T68) -> 143.296
A69: ='New Cities Filter'!C69 -> Mightkeep | C69: {=Q69*('Price Sheet (Ignore)'!$H$2+_xlfn.IFS(O69="dirt",0.15,O69="gravel",0.3,O69="paved",0.4,O69="none",0))*(G69/3)} -> 64.133333 | D69: ='New Cities Filter'!B:B -> Mightkeep | E69: Swanmen | F69: Path of Guiding Light | G69: 1924 | L69: plaza | O69: none | P69: =IF(H69="capital",0.1)+IF(I69="port",0.1)+IF(J69="citadel",0.05)+IF(K69="walls",-0.07)+IF(L69="plaza",0.05)+IF(M69="temple",0.01)+IF(N69="shanty town",0.05) -> 0.05 | Q69: =IF(P69>0.25,P69,P69+'Price Sheet (Ignore)'!$G$2) -> 0.2 | R69: =((G69*0.012)+IF(G69*0.012<100,100))+(S69-T69) -> 123.088
A70: ='New Cities Filter'!C70 -> Mightkeep | C70: {=Q70*('Price Sheet (Ignore)'!$H$2+_xlfn.IFS(O70="dirt",0.15,O70="gravel",0.3,O70="paved",0.4,O70="none",0))*(G70/3)} -> 568.6 | D70: ='New Cities Filter'!B:B -> Sungelrock | E70: Swanmen | F70: Path of Guiding Light | G70: 17058 | J70: citadel | O70: none | P70: =IF(H70="capital",0.1)+IF(I70="port",0.1)+IF(J70="citadel",0.05)+IF(K70="walls",-0.07)+IF(L70="plaza",0.05)+IF(M70="temple",0.01)+IF(N70="shanty town",0.05) -> 0.05 | Q70: =IF(P70>0.25,P70,P70+'Price Sheet (Ignore)'!$G$2) -> 0.2 | R70: =((G70*0.012)+IF(G70*0.012<100,100))+(S70-T70) -> 204.696
A71: ='New Cities Filter'!C71 -> Mightkeep | C71: {=Q71*('Price Sheet (Ignore)'!$H$2+_xlfn.IFS(O71="dirt",0.15,O71="gravel",0.3,O71="paved",0.4,O71="none",0))*(G71/3)} -> 55.5 | D71: ='New Cities Filter'!B:B -> Houndford | E71: Swanmen | F71: Path of Guiding Light | G71: 2220 | O71: none | P71: =IF(H71="capital",0.1)+IF(I71="port",0.1)+IF(J71="citadel",0.05)+IF(K71="walls",-0.07)+IF(L71="plaza",0.05)+IF(M71="temple",0.01)+IF(N71="shanty town",0.05) -> 0 | Q71: =IF(P71>0.25,P71,P71+'Price Sheet (Ignore)'!$G$2) -> 0.15 | R71: =((G71*0.012)+IF(G71*0.012<100,100))+(S71-T71) -> 126.64
A72: ='New Cities Filter'!C72 -> Mightkeep | C72: {=Q72*('Price Sheet (Ignore)'!$H$2+_xlfn.IFS(O72="dirt",0.15,O72="gravel",0.3,O72="paved",0.4,O72="none",0))*(G72/3)} -> 450.13333 | D72: ='New Cities Filter'!B:B -> Bridtown | E72: Swanmen | F72: Path of Guiding Light | G72: 13504 | L72: plaza | O72: none | P72: =IF(H72="capital",0.1)+IF(I72="port",0.1)+IF(J72="citadel",0.05)+IF(K72="walls",-0.07)+IF(L72="plaza",0.05)+IF(M72="temple",0.01)+IF(N72="shanty town",0.05) -> 0.05 | Q72: =IF(P72>0.25,P72,P72+'Price Sheet (Ignore)'!$G$2) -> 0.2 | R72: =((G72*0.012)+IF(G72*0.012<100,100))+(S72-T72) -> 162.048
A73: ='New Cities Filter'!C73 -> Mightkeep | C73: {=Q73*('Price Sheet (Ignore)'!$H$2+_xlfn.IFS(O73="dirt",0.15,O73="gravel",0.3,O73="paved",0.4,O73="none",0))*(G73/3)} -> 358.06667 | D73: ='New Cities Filter'!B:B -> Mudfair | E73: Swanmen | F73: Path of Guiding Light | G73: 10742 | J73: citadel | O73: none | P73: =IF(H73="capital",0.1)+IF(I73="port",0.1)+IF(J73="citadel",0.05)+IF(K73="walls",-0.07)+IF(L73="plaza",0.05)+IF(M73="temple",0.01)+IF(N73="shanty town",0.05) -> 0.05 | Q73: =IF(P73>0.25,P73,P73+'Price Sheet (Ignore)'!$G$2) -> 0.2 | R73: =((G73*0.012)+IF(G73*0.012<100,100))+(S73-T73) -> 128.904
A74: ='New Cities Filter'!C74 -> Mightkeep | C74: {=Q74*('Price Sheet (Ignore)'!$H$2+_xlfn.IFS(O74="dirt",0.15,O74="gravel",0.3,O74="paved",0.4,O74="none",0))*(G74/3)} -> 293.45333 | D74: ='New Cities Filter'!B:B -> Mythspell | E74: Swanmen | F74: Path of Guiding Light | G74: 13544 | K74: walls | L74: plaza | O74: none | P74: =IF(H74="capital",0.1)+IF(I74="port",0.1)+IF(J74="citadel",0.05)+IF(K74="walls",-0.07)+IF(L74="plaza",0.05)+IF(M74="temple",0.01)+IF(N74="shanty town",0.05) -> -0.02 | Q74: =IF(P74>0.25,P74,P74+'Price Sheet (Ignore)'!$G$2) -> 0.13 | R74: =((G74*0.012)+IF(G74*0.012<100,100))+(S74-T74) -> 162.528
A75: ='New Cities Filter'!C75 -> Mondwatch | B75: =SUM(C75:C77) -> 1413.7533 | C75: {=Q75*('Price Sheet (Ignore)'!$H$2+_xlfn.IFS(O75="dirt",0.15,O75="gravel",0.3,O75="paved",0.4,O75="none",0))*(G75/3)} -> 354.16667 | D75: ='New Cities Filter'!B:B -> Heartmorest | E75: Westerling | F75: Path of Guiding Light | G75: 8500 | J75: citadel | L75: plaza | O75: none | P75: =IF(H75="capital",0.1)+IF(I75="port",0.1)+IF(J75="citadel",0.05)+IF(K75="walls",-0.07)+IF(L75="plaza",0.05)+IF(M75="temple",0.01)+IF(N75="shanty town",0.05) -> 0.1 | Q75: =IF(P75>0.25,P75,P75+'Price Sheet (Ignore)'!$G$2) -> 0.25 | R75: =((G75*0.012)+IF(G75*0.012<100,100))+(S75-T75) -> 102
A76: ='New Cities Filter'!C76 -> Mondwatch | C76: {=Q76*('Price Sheet (Ignore)'!$H$2+_xlfn.IFS(O76="dirt",0.15,O76="gravel",0.3,O76="paved",0.4,O76="none",0))*(G76/3)} -> 909.2 | D76: ='New Cities Filter'!B:B -> Bear Hall | E76: Westerling | F76: Path of Guiding Light | G76: 18184 | I76: port | L76: plaza | O76: none | P76: =IF(H76="capital",0.1)+IF(I76="port",0.1)+IF(J76="citadel",0.05)+IF(K76="walls",-0.07)+IF(L76="plaza",0.05)+IF(M76="temple",0.01)+IF(N76="shanty town",0.05) -> 0.15 | Q76: =IF(P76>0.25,P76,P76+'Price Sheet (Ignore)'!$G$2) -> 0.3 | R76: =((G76*0.012)+IF(G76*0.012<100,100))+(S76-T76) -> 218.208
A77: ='New Cities Filter'!C77 -> Mondwatch | C77: {=Q77*('Price Sheet (Ignore)'!$H$2+_xlfn.IFS(O77="dirt",0.15,O77="gravel",0.3,O77="paved",0.4,O77="none",0))*(G77/3)} -> 150.38667 | D77: ='New Cities Filter'!B:B -> Mondbaymond | E77: Ralimers | F77: Path of Guiding Light | G77: 11279 | K77: walls | O77: none | P77: =IF(H77="capital",0.1)+IF(I77="port",0.1)+IF(J77="citadel",0.05)+IF(K77="walls",-0.07)+IF(L77="plaza",0.05)+IF(M77="temple",0.01)+IF(N77="shanty town",0.05) -> -0.07 | Q77: =IF(P77>0.25,P77,P77+'Price Sheet (Ignore)'!$G$2) -> 0.08 | R77: =((G77*0.012)+IF(G77*0.012<100,100))+(S77-T77) -> 135.348
A78: ='New Cities Filter'!C78 -> Northfold | B78: =SUM(C78) -> 702.9 | C78: {=Q78*('Price Sheet (Ignore)'!$H$2+_xlfn.IFS(O78="dirt",0.15,O78="gravel",0.3,O78="paved",0.4,O78="none",0))*(G78/3)} -> 702.9 | D78: ='New Cities Filter'!B:B -> Northfold Manor | E78: Eastern Shavian | F78: Path of Guiding Light | G78: 23430 | J78: citadel | K78: walls | L78: plaza | O78: none | P78: =IF(H78="capital",0.1)+IF(I78="port",0.1)+IF(J78="citadel",0.05)+IF(K78="walls",-0.07)+IF(L78="plaza",0.05)+IF(M78="temple",0.01)+IF(N78="shanty town",0.05) -> 0.03 | Q78: =IF(P78>0.25,P78,P78+'Price Sheet (Ignore)'!$G$2) -> 0.18 | R78: =((G78*0.012)+IF(G78*0.012<100,100))+(S78-T78) -> 281.16
A79: ='New Cities Filter'!C79 -> Oal's Reach | B79: =SUM(C79:C81) -> 465.20667 | C79: {=Q79*('Price Sheet (Ignore)'!$H$2+_xlfn.IFS(O79="dirt",0.15,O79="gravel",0.3,O79="paved",0.4,O79="none",0))*(G79/3)} -> 247.97333 | D79: ='New Cities Filter'!B:B -> Oaledale | E79: Ralimers | F79: Path of Guiding Light | G79: 18598 | K79: walls | O79: none | P79: =IF(H79="capital",0.1)+IF(I79="port",0.1)+IF(J79="citadel",0.05)+IF(K79="walls",-0.07)+IF(L79="plaza",0.05)+IF(M79="temple",0.01)+IF(N79="shanty town",0.05) -> -0.07 | Q79: =IF(P79>0.25,P79,P79+'Price Sheet (Ignore)'!$G$2) -> 0.08 | R79: =((G79*0.012)+IF(G79*0.012<100,100))+(S79-T79) -> 223.176
A80: ='New Cities Filter'!C80 -> Oal's Reach | C80: {=Q80*('Price Sheet (Ignore)'!$H$2+_xlfn.IFS(O80="dirt",0.15,O80="gravel",0.3,O80="paved",0.4,O80="none",0))*(G80/3)} -> 59.1 | D80: ='New Cities Filter'!B:B -> Mistmorest | E80: Central Shavian | F80: Path of Guiding Light | G80: 1773 | J80: citadel | O80: none | P80: =IF(H80="capital",0.1)+IF(I80="port",0.1)+IF(J80="citadel",0.05)+IF(K80="walls",-0.07)+IF(L80="plaza",0.05)+IF(M80="temple",0.01)+IF(N80="shanty town",0.05) -> 0.05 | Q80: =IF(P80>0.25,P80,P80+'Price Sheet (Ignore)'!$G$2) -> 0.2 | R80: =((G80*0.012)+IF(G80*0.012<100,100))+(S80-T80) -> 121.276
A81: ='New Cities Filter'!C81 -> Oal's Reach | C81: {=Q81*('Price Sheet (Ignore)'!$H$2+_xlfn.IFS(O81="dirt",0.15,O81="gravel",0.3,O81="paved",0.4,O81="none",0))*(G81/3)} -> 158.13333 | D81: ='New Cities Filter'!B:B -> Shaledasinf | E81: Central Shavian | F81: Path of Guiding Light | G81: 4744 | J81: citadel | O81: none | P81: =IF(H81="capital",0.1)+IF(I81="port",0.1)+IF(J81="citadel",0.05)+IF(K81="walls",-0.07)+IF(L81="plaza",0.05)+IF(M81="temple",0.01)+IF(N81="shanty town",0.05) -> 0.05 | Q81: =IF(P81>0.25,P81,P81+'Price Sheet (Ignore)'!$G$2) -> 0.2 | R81: =((G81*0.012)+IF(G81*0.012<100,100))+(S81-T81) -> 156.928
A82: ='New Cities Filter'!C82 -> Pearlpass | B82: =SUM(C82) -> 987.70833 | C82: {=Q82*('Price Sheet (Ignore)'!$H$2+_xlfn.IFS(O82="dirt",0.15,O82="gravel",0.3,O82="paved",0.4,O82="none",0))*(G82/3)} -> 987.70833 | D82: ='New Cities Filter'!B:B -> Pearlpass | E82: Northerners | F82: Path of Guiding Light | G82: 23705 | J82: citadel | L82: plaza | O82: none | P82: =IF(H82="capital",0.1)+IF(I82="port",0.1)+IF(J82="citadel",0.05)+IF(K82="walls",-0.07)+IF(L82="plaza",0.05)+IF(M82="temple",0.01)+IF(N82="shanty town",0.05) -> 0.1 | Q82: =IF(P82>0.25,P82,P82+'Price Sheet (Ignore)'!$G$2) -> 0.25 | R82: =((G82*0.012)+IF(G82*0.012<100,100))+(S82-T82) -> 284.46
A83: ='New Cities Filter'!C83 -> Persterton Pass | B83: =SUM(C83:C86) -> 197.96167 | C83: {=Q83*('Price Sheet (Ignore)'!$H$2+_xlfn.IFS(O83="dirt",0.15,O83="gravel",0.3,O83="paved",0.4,O83="none",0))*(G83/3)} -> 98.233333 | D83: ='New Cities Filter'!B:B -> Nilbog | E83: Madinglian | F83: Children of Stone | G83: 2947 | L83: plaza | O83: none | P83: =IF(H83="capital",0.1)+IF(I83="port",0.1)+IF(J83="citadel",0.05)+IF(K83="walls",-0.07)+IF(L83="plaza",0.05)+IF(M83="temple",0.01)+IF(N83="shanty town",0.05) -> 0.05 | Q83: =IF(P83>0.25,P83,P83+'Price Sheet (Ignore)'!$G$2) -> 0.2 | R83: =((G83*0.012)+IF(G83*0.012<100,100))+(S83-T83) -> 135.364
A84: ='New Cities Filter'!C84 -> Persterton Pass | C84: {=Q84*('Price Sheet (Ignore)'!$H$2+_xlfn.IFS(O84="dirt",0.15,O84="gravel",0.3,O84="paved",0.4,O84="none",0))*(G84/3)} -> 15.653333 | D84: ='New Cities Filter'!B:B -> Persterton | E84: Wildlands | F84: Children of Stone | G84: 1174 | K84: walls | O84: none | P84: =IF(H84="capital",0.1)+IF(I84="port",0.1)+IF(J84="citadel",0.05)+IF(K84="walls",-0.07)+IF(L84="plaza",0.05)+IF(M84="temple",0.01)+IF(N84="shanty town",0.05) -> -0.07 | Q84: =IF(P84>0.25,P84,P84+'Price Sheet (Ignore)'!$G$2) -> 0.08 | R84: =((G84*0.012)+IF(G84*0.012<100,100))+(S84-T84) -> 114.088
A85: ='New Cities Filter'!C85 -> Persterton Pass | C85: {=Q85*('Price Sheet (Ignore)'!$H$2+_xlfn.IFS(O85="dirt",0.15,O85="gravel",0.3,O85="paved",0.4,O85="none",0))*(G85/3)} -> 46.425 | D85: ='New Cities Filter'!B:B -> Ishzit | E85: Madinglian | F85: Children of Stone | G85: 1857 | O85: none | P85: =IF(H85="capital",0.1)+IF(I85="port",0.1)+IF(J85="citadel",0.05)+IF(K85="walls",-0.07)+IF(L85="plaza",0.05)+IF(M85="temple",0.01)+IF(N85="shanty town",0.05) -> 0 | Q85: =IF(P85>0.25,P85,P85+'Price Sheet (Ignore)'!$G$2) -> 0.15 | R85: =((G85*0.012)+IF(G85*0.012<100,100))+(S85-T85) -> 122.284
A86: ='New Cities Filter'!C86 -> Persterton Pass | C86: {=Q86*('Price Sheet (Ignore)'!$H$2+_xlfn.IFS(O86="dirt",0.15,O86="gravel",0.3,O86="paved",0.4,O86="none",0))*(G86/3)} -> 37.65 | D86: ='New Cities Filter'!B:B -> Buggalhob | E86: Madinglian | F86: Children of Stone | G86: 1506 | O86: none | P86: =IF(H86="capital",0.1)+IF(I86="port",0.1)+IF(J86="citadel",0.05)+IF(K86="walls",-0.07)+IF(L86="plaza",0.05)+IF(M86="temple",0.01)+IF(N86="shanty town",0.05) -> 0 | Q86: =IF(P86>0.25,P86,P86+'Price Sheet (Ignore)'!$G$2) -> 0.15 | R86: =((G86*0.012)+IF(G86*0.012<100,100))+(S86-T86) -> 118.072
A87: ='New Cities Filter'!C87 -> Prince's Boot | B87: =SUM(C87) -> 125.27333 | C87: {=Q87*('Price Sheet (Ignore)'!$H$2+_xlfn.IFS(O87="dirt",0.15,O87="gravel",0.3,O87="paved",0.4,O87="none",0))*(G87/3)} -> 125.27333 | D87: ='New Cities Filter'!B:B -> Draven | E87: Northerners | F87: Path of Guiding Light | G87: 3268 | I87: port | J87: citadel | K87: walls | O87: none | P87: =IF(H87="capital",0.1)+IF(I87="port",0.1)+IF(J87="citadel",0.05)+IF(K87="walls",-0.07)+IF(L87="plaza",0.05)+IF(M87="temple",0.01)+IF(N87="shanty town",0.05) -> 0.08 | Q87: =IF(P87>0.25,P87,P87+'Price Sheet (Ignore)'!$G$2) -> 0.23 | R87: =((G87*0.012)+IF(G87*0.012<100,100))+(S87-T87) -> 139.216
A88: ='New Cities Filter'!C88 -> Quickwatch | B88: =SUM(C88:C93) -> 1190.365 | C88: {=Q88*('Price Sheet (Ignore)'!$H$2+_xlfn.IFS(O88="dirt",0.15,O88="gravel",0.3,O88="paved",0.4,O88="none",0))*(G88/3)} -> 132.77333 | D88: ='New Cities Filter'!B:B -> Quickwatch | E88: Eastern Shavian | F88: Path of Guiding Light | G88: 6128 | J88: citadel | K88: walls | O88: none | P88: =IF(H88="capital",0.1)+IF(I88="port",0.1)+IF(J88="citadel",0.05)+IF(K88="walls",-0.07)+IF(L88="plaza",0.05)+IF(M88="temple",0.01)+IF(N88="shanty town",0.05) -> -0.02 | Q88: =IF(P88>0.25,P88,P88+'Price Sheet (Ignore)'!$G$2) -> 0.13 | R88: =((G88*0.012)+IF(G88*0.012<100,100))+(S88-T88) -> 173.536
